Workbook
Name Tabla11: Tabla_Pivot_Facturacion[]

Sheet Panel Entrada
B1: TAPERIA DE CALDES · PANEL DE ENTRADA RÁPIDA
B2: Pega los datos del TPV en las zonas indicadas. Todo se actualiza automáticamente.
B4: RESUMEN DE DATOS CARGADOS
B5: Fuente de datos | C5: Registros | D5: Rango fechas | E5: Dónde pegar | F5: Estado
B6: ⚽ Tickets Caja 1 (Tabla 8) | C6: =COUNTA('Detalle Turnos'!I3:I5022)-1 -> 1793 | D6: =TEXT(MIN('Detalle Turnos'!I3:I5022),"dd/mm/yy")&" → "&TEXT(MAX('Detalle Turnos'!I3:I5022),"dd/mm/yy") -> 02/01/yy → 01/05/yy | E6: Detalle Turnos' I:O | F6: =IF(C6>0,"✅ "&C6&" tickets","❌ Vacío") -> ✅ 1793 tickets
B7: 🎽 Tickets Caja 2 (Tabla 9) | C7: =COUNTA('Detalle Turnos'!Q3:Q4992)-1 -> 204 | D7: =TEXT(MIN('Detalle Turnos'!Q3:Q4992),"dd/mm/yy")&" → "&TEXT(MAX('Detalle Turnos'!Q3:Q4992),"dd/mm/yy") -> 02/01/yy → 30/04/yy | E7: Detalle Turnos' Q:V | F7: =IF(C7>0,"✅ "&C7&" tickets","❌ Vacío") -> ✅ 204 tickets
B8: 👥 Horarios Personal | C8: =COUNTA('Horarios Personal'!A5:A602)-COUNTBLANK('Horarios Personal'!A5:A602) -> 598 | D8: =IFERROR(TEXT(MIN(DATEVALUE(LEFT('Horarios Personal'!A5,2)&"/"&MID('Horarios Personal'!A5,4,2)&"/"&RIGHT('Horarios Personal'!A5,4))),"dd/mm/yy")&" → "&'Horarios Personal'!A551,"Ene → Abr 2026") -> Ene → Abr 2026 | E8: Horarios Personal' A5+ | F8: =IF(C8>0,"✅ "&C8&" registros","❌ Vacío") -> ✅ 598 registros
B9: 📊 Ventas por Producto (Caja 1) | C9: =COUNTA('Ventas Caja 1'!B5:B7550) -> 5693 | D9: =IFERROR(TEXT(MIN('Ventas Caja 1'!B5:B7550),"dd/mm/yy")&" → "&TEXT(MAX('Ventas Caja 1'!B5:B7550),"dd/mm/yy"),"") -> 02/01/yy → 01/05/yy | E9: Ventas Caja 1' B5+ | F9: =IF(C9>0,"✅ "&C9&" líneas","❌ Vacío") -> ✅ 5693 líneas
B11: INSTRUCCIONES DE PEGADO
B13: ❶ TICKETS CAJA 1 — Tabla 8
B14: 📁 Hoja destino: | C14: Detalle Turnos
B15: 📍 Celda inicio: | C15: I (debajo del último dato)
B16: 📋 Columnas: | C16: I=Fecha | J=Hora | K=Importe | L=Pax | M=Día | N=Turno
B17: ➡️ Alimenta: | C17: Caja 1 → Facturación 2026 → Dashboard
B19: ❷ TICKETS CAJA 2 — Tabla 9
B20: 📁 Hoja destino: | C20: Detalle Turnos
B21: 📍 Celda inicio: | C21: Q (debajo del último dato)
B22: 📋 Columnas: | C22: Q=Fecha | R=Hora | S=Turno | T=Pax | U=Importe
B23: ➡️ Alimenta: | C23: Caja 2 → Facturación 2026 → Dashboard
B25: ❸ HORARIOS PERSONAL
B26: 📁 Hoja destino: | C26: Horarios Personal
B27: 📍 Celda inicio: | C27: A (debajo fila 551 o último dato)
B28: 📋 Columnas: | C28: A=Fecha(dd/mm/yyyy) | B=Día | C=Turno | D=Nombre | E=Entrada | F=Salida
B29: ➡️ Alimenta: | C29: Resumen Empleado → Facturación (Coste) → Cajas → Dashboard
B30: ⚠️ Importante: | C30: Fechas como TEXTO dd/mm/yyyy. Horas como decimales (0.29=7:00, 0.79=19:00)
B32: ❹ VENTAS POR PRODUCTO
B33: 📁 Hoja destino: | C33: Ventas Caja 1 (o nueva hoja)
B34: 📍 Celda inicio: | C34: B (debajo del último dato, actual: B22152)
B35: 📋 Columnas: | C35: B=Fecha | C=Familia | D=Producto | E=Cantidad | F=PVP | G=Total | H=Neto | I=%Cons | J=Coste | K=T.Coste
B36: ➡️ Alimenta: | C36: Análisis de productos y márgenes (pendiente de conectar)
B38: CADENA DE ACTUALIZACIÓN AUTOMÁTICA
B39: Pegas tickets → Detalle Turnos agrega → Cajas calculan → Facturación consolida → Dashboard muestra KPIs
B41: 📦 Tickets TPV | C41: ➡️ | D41: Detalle Turnos | E41: ➡️ | F41: Caja 1 + Caja 2
D42: (agrega por fecha+turno) | F42: (comensales, subtotal, ticket medio)
B44: 👥 Horarios | C44: ➡️ | D44: Facturación 2026 (J) | E44: ➡️ | F44: Dashboard Gerencia
D45: (coste personal por día) | F45: (KPIs, ratio, alertas)

Sheet Dashboard Gerencia
A1: TAPERIA DE CALDES · DASHBOARD GERENCIA — VISIÓN 360°
A2: Actualizado: Abril 2026 · Datos: Enero–Abril 2026 · Modelo basado en 250+ días históricos (2025) + datos reales 2026
A4: KPIs OPERATIVOS — ENERO A ABRIL 2026
A5: FACTURACIÓN REAL ENE–ABR | C5: FACTURACIÓN PREVISTA | E5: COSTE PERSONAL (CORREGIDO) | G5: RATIO COSTE/VENTA | I5: MARGEN BRUTO ENE–ABR | K5: MEJOR DÍA | M5: AHORRO FICHAJES CORR.
A6: =TEXT('Facturación 2026'!P16,"#.##0"&" €") -> 105.333 € | C6: =TEXT('Facturación 2026'!Q16,"#.##0"&" €") -> 390.218 € | E6: {=TEXT(SUMPRODUCT(('Facturación 2026'!$J$4:$J$253)*1),"#.##0"&" €")} -> 25.355 € | G6: {=TEXT(IFERROR(SUMPRODUCT(('Facturación 2026'!$J$4:$J$253)*1)/'Facturación 2026'!P16,0),"0,0%")} -> 24,1% | I6: {=TEXT('Facturación 2026'!P16-SUMPRODUCT(('Facturación 2026'!$J$4:$J$253)*1),"#.##0"&" €")} -> 79.978 € | K6: =TEXT(INDEX('Facturación 2026'!$A$4:$A$253,MATCH(MAX('Facturación 2026'!$F$4:$F$253),'Facturación 2026'!$F$4:$F$253,0)),"dd/mm")&" — "&TEXT(MAX('Facturación 2026'!$F$4:$F$253),"#.##0")&"€" -> 07/02 — 3.908€ | M6: −1.366 €
A9: FACTURACIÓN MENSUAL 2026 vs 2025 + PROYECCIÓN
A10: Mes | B10: Real 2025 | C10: Prev. 2026 | D10: Real 2026 | E10: Coste Pers. | F10: Margen € | G10: % Coste | H10: vs 2025 | I10: vs Prev. | J10: Índice | K10: Días | L10: Comentario
A11: Enero | B11: 24020 | C11: 35000 | D11: ='Facturación 2026'!P4 -> 26444.12 | E11: {=SUMPRODUCT((MONTH('Facturación 2026'!$A$4:$A$253)=1)*('Facturación 2026'!$J$4:$J$253)*1)} -> 10707.093 | F11: =IFERROR(D11-E11,"") -> 15737.027 | G11: =IFERROR(E11/D11,"") -> 0.40489502 | H11: =IFERROR((D11-B11)/B11,"") -> 0.1009209 | I11: =IFERROR((D11-C11)/C11,"") -> -0.24445371 | J11: 0.72 | K11: {=SUMPRODUCT((MONTH('Facturación 2026'!$A$4:$A$253)=1)*('Facturación 2026'!$F$4:$F$253>0)*1)} -> 22 | L11: Real ✓
A12: Febrero | B12: 26309 | C12: 32000 | D12: ='Facturación 2026'!P5 -> 26991.51 | E12: {=SUMPRODUCT((MONTH('Facturación 2026'!$A$4:$A$253)=2)*('Facturación 2026'!$J$4:$J$253)*1)} -> 8426.145 | F12: =IFERROR(D12-E12,"") -> 18565.365 | G12: =IFERROR(E12/D12,"") -> 0.31217761 | H12: =IFERROR((D12-B12)/B12,"") -> 0.025942073 | I12: =IFERROR((D12-C12)/C12,"") -> -0.15651531 | J12: 0.88 | K12: {=SUMPRODUCT((MONTH('Facturación 2026'!$A$4:$A$253)=2)*('Facturación 2026'!$F$4:$F$253>0)*1)} -> 16 | L12: Real ✓
A13: Marzo | B13: 20665 | C13: 28000 | D13: ='Facturación 2026'!P6 -> 20240.31 | E13: {=SUMPRODUCT((MONTH('Facturación 2026'!$A$4:$A$253)=3)*('Facturación 2026'!$J$4:$J$253)*1)} -> 6221.6925 | F13: =IFERROR(D13-E13,"") -> 14018.618 | G13: =IFERROR(E13/D13,"") -> 0.30739117 | H13: =IFERROR((D13-B13)/B13,"") -> -0.020551173 | I13: =IFERROR((D13-C13)/C13,"") -> -0.27713179 | J13: 0.95 | K13: {=SUMPRODUCT((MONTH('Facturación 2026'!$A$4:$A$253)=3)*('Facturación 2026'!$F$4:$F$253>0)*1)} -> 15 | L13: Real ✓
A14: Abril | B14: 28883 | C14: 26000 | D14: ='Facturación 2026'!P7 -> 31581.437 | E14: {=SUMPRODUCT((MONTH('Facturación 2026'!$A$4:$A$253)=4)*('Facturación 2026'!$J$4:$J$253)*1)} -> 0 | F14: =IFERROR(D14-E14,"") -> 31581.437 | G14: =IFERROR(E14/D14,"") -> 0 | H14: =IFERROR((D14-B14)/B14,"") -> 0.093426479 | I14: =IFERROR((D14-C14)/C14,"") -> 0.21467065 | J14: 0.98 | K14: {=SUMPRODUCT((MONTH('Facturación 2026'!$A$4:$A$253)=4)*('Facturación 2026'!$F$4:$F$253>0)*1)} -> 22 | L14: Parcial
A15: Mayo | B15: 24855 | C15: 25000 | F15: =IFERROR(D15-E15,"") -> 0 | G15: =IFERROR(E15/D15,"") | H15: =IFERROR((D15-B15)/B15,"") -> -1 | I15: =IFERROR((D15-C15)/C15,"") -> -1 | J15: 0.92 | K15: 20 | L15: Previsto
A16: Junio | B16: 34531 | C16: 30000 | F16: =IFERROR(D16-E16,"") -> 0 | G16: =IFERROR(E16/D16,"") | H16: =IFERROR((D16-B16)/B16,"") -> -1 | I16: =IFERROR((D16-C16)/C16,"") -> -1 | J16: 1.1 | K16: 22 | L16: Previsto
A17: Julio | B17: 44025 | C17: 50000 | F17: =IFERROR(D17-E17,"") -> 0 | G17: =IFERROR(E17/D17,"") | H17: =IFERROR((D17-B17)/B17,"") -> -1 | I17: =IFERROR((D17-C17)/C17,"") -> -1 | J17: 1.38 | K17: 23 | L17: Previsto — Escaldàrium
A18: Agosto | B18: 60081 | C18: 65000 | F18: =IFERROR(D18-E18,"") -> 0 | G18: =IFERROR(E18/D18,"") | H18: =IFERROR((D18-B18)/B18,"") -> -1 | I18: =IFERROR((D18-C18)/C18,"") -> -1 | J18: 1.48 | K18: 27 | L18: Previsto — pico
A19: Septiembre | B19: 30862 | C19: 38000 | F19: =IFERROR(D19-E19,"") -> 0 | G19: =IFERROR(E19/D19,"") | H19: =IFERROR((D19-B19)/B19,"") -> -1 | I19: =IFERROR((D19-C19)/C19,"") -> -1 | J19: 1.18 | K19: 21 | L19: Previsto
A20: Octubre | B20: 38013 | C20: 42000 | F20: =IFERROR(D20-E20,"") -> 0 | G20: =IFERROR(E20/D20,"") | H20: =IFERROR((D20-B20)/B20,"") -> -1 | I20: =IFERROR((D20-C20)/C20,"") -> -1 | J20: 1.22 | K20: 22 | L20: Previsto — Festa Major
A21: Noviembre | B21: 19490 | C21: 28000 | F21: =IFERROR(D21-E21,"") -> 0 | G21: =IFERROR(E21/D21,"") | H21: =IFERROR((D21-B21)/B21,"") -> -1 | I21: =IFERROR((D21-C21)/C21,"") -> -1 | J21: 1.02 | K21: 12 | L21: Previsto
A22: Diciembre | B22: 19797 | C22: 35000 | F22: =IFERROR(D22-E22,"") -> 0 | G22: =IFERROR(E22/D22,"") | H22: =IFERROR((D22-B22)/B22,"") -> -1 | I22: =IFERROR((D22-C22)/C22,"") -> -1 | J22: 1.18 | K22: 14 | L22: Previsto — Fira Nadal
A23: TOTAL ANUAL | B23: =SUM(B11:B22) -> 371531 | C23: =SUM(C11:C22) -> 434000 | D23: =SUM(D11:D22) -> 105257.38 | E23: =SUM(E11:E22) -> 25354.93 | F23: =IFERROR(D23-E23,"") -> 79902.447 | G23: =IFERROR(E23/D23,"") -> 0.24088506
A25: EFICIENCIA OPERATIVA — RATIO COSTE PERSONAL / VENTAS
A26: Día semana | B26: Fact. media | C26: Coste medio | D26: Ratio % | E26: Semáforo | F26: Objetivo % | G26: Estado | H26: Personal ideal | I26: Recomendación
A27: Miércoles | B27: {=IFERROR(SUMPRODUCT((WEEKDAY('Facturación 2026'!$A$4:$A$253,2)=3)*'Facturación 2026'!$F$4:$F$253)/SUMPRODUCT((WEEKDAY('Facturación 2026'!$A$4:$A$253,2)=3)*('Facturación 2026'!$F$4:$F$253>0)*1),0)} -> 780.6944 | C27: {=IFERROR(SUMPRODUCT((WEEKDAY('Facturación 2026'!$A$4:$A$253,2)=3)*'Facturación 2026'!$J$4:$J$253)/SUMPRODUCT((WEEKDAY('Facturación 2026'!$A$4:$A$253,2)=3)*('Facturación 2026'!$F$4:$F$253>0)*1),0)} -> 288.9715 | D27: =IFERROR(C27/B27,"—") -> 0.37014676 | E27: =IF(D27="—","",IF(D27<=0.33,"🟢",IF(D27<=0.38,"🟡","🔴"))) -> 🟡 | F27: 0.38 | G27: =IF(B27=0,"—",IF(D27<=F27,"🟢 OK","🔴 Excede")) -> 🟢 OK | H27: 3 pers. | I27: Nuevo horario sin MA mejora ratio
A28: Jueves | B28: {=IFERROR(SUMPRODUCT((WEEKDAY('Facturación 2026'!$A$4:$A$253,2)=4)*'Facturación 2026'!$F$4:$F$253)/SUMPRODUCT((WEEKDAY('Facturación 2026'!$A$4:$A$253,2)=4)*('Facturación 2026'!$F$4:$F$253>0)*1),0)} -> 1055.4893 | C28: {=IFERROR(SUMPRODUCT((WEEKDAY('Facturación 2026'!$A$4:$A$253,2)=4)*'Facturación 2026'!$J$4:$J$253)/SUMPRODUCT((WEEKDAY('Facturación 2026'!$A$4:$A$253,2)=4)*('Facturación 2026'!$F$4:$F$253>0)*1),0)} -> 293.04067 | D28: =IFERROR(C28/B28,"—") -> 0.27763491 | E28: =IF(D28="—","",IF(D28<=0.33,"🟢",IF(D28<=0.38,"🟡","🔴"))) -> 🟢 | F28: 0.35 | G28: =IF(B28=0,"—",IF(D28<=F28,"🟢 OK","🔴 Excede")) -> 🟢 OK | H28: 4 pers. | I28: Mantener estructura actual
A29: Viernes | B29: {=IFERROR(SUMPRODUCT((WEEKDAY('Facturación 2026'!$A$4:$A$253,2)=5)*'Facturación 2026'!$F$4:$F$253)/SUMPRODUCT((WEEKDAY('Facturación 2026'!$A$4:$A$253,2)=5)*('Facturación 2026'!$F$4:$F$253>0)*1),0)} -> 1390.5263 | C29: {=IFERROR(SUMPRODUCT((WEEKDAY('Facturación 2026'!$A$4:$A$253,2)=5)*'Facturación 2026'!$J$4:$J$253)/SUMPRODUCT((WEEKDAY('Facturación 2026'!$A$4:$A$253,2)=5)*('Facturación 2026'!$F$4:$F$253>0)*1),0)} -> 364.64172 | D29: =IFERROR(C29/B29,"—") -> 0.26223288 | E29: =IF(D29="—","",IF(D29<=0.33,"🟢",IF(D29<=0.38,"🟡","🔴"))) -> 🟢 | F29: 0.32 | G29: =IF(B29=0,"—",IF(D29<=F29,"🟢 OK","🔴 Excede")) -> 🟢 OK | H29: 5 pers. | I29: Reforzar noche esp. en eventos Casino
A30: Sábado | B30: {=IFERROR(SUMPRODUCT((WEEKDAY('Facturación 2026'!$A$4:$A$253,2)=6)*'Facturación 2026'!$F$4:$F$253)/SUMPRODUCT((WEEKDAY('Facturación 2026'!$A$4:$A$253,2)=6)*('Facturación 2026'!$F$4:$F$253>0)*1),0)} -> 2217.3901 | C30: {=IFERROR(SUMPRODUCT((WEEKDAY('Facturación 2026'!$A$4:$A$253,2)=6)*'Facturación 2026'!$J$4:$J$253)/SUMPRODUCT((WEEKDAY('Facturación 2026'!$A$4:$A$253,2)=6)*('Facturación 2026'!$F$4:$F$253>0)*1),0)} -> 406.70617 | D30: =IFERROR(C30/B30,"—") -> 0.1834166 | E30: =IF(D30="—","",IF(D30<=0.33,"🟢",IF(D30<=0.38,"🟡","🔴"))) -> 🟢 | F30: 0.3 | G30: =IF(B30=0,"—",IF(D30<=F30,"🟢 OK","🔴 Excede")) -> 🟢 OK | H30: 6 pers. | I30: Día más rentable — maximizar ocupación
A31: Domingo | B31: {=IFERROR(SUMPRODUCT((WEEKDAY('Facturación 2026'!$A$4:$A$253,2)=7)*'Facturación 2026'!$F$4:$F$253)/SUMPRODUCT((WEEKDAY('Facturación 2026'!$A$4:$A$253,2)=7)*('Facturación 2026'!$F$4:$F$253>0)*1),0)} -> 1485.3766 | C31: {=IFERROR(SUMPRODUCT((WEEKDAY('Facturación 2026'!$A$4:$A$253,2)=7)*'Facturación 2026'!$J$4:$J$253)/SUMPRODUCT((WEEKDAY('Facturación 2026'!$A$4:$A$253,2)=7)*('Facturación 2026'!$F$4:$F$253>0)*1),0)} -> 312.65917 | D31: =IFERROR(C31/B31,"—") -> 0.21049151 | E31: =IF(D31="—","",IF(D31<=0.33,"🟢",IF(D31<=0.38,"🟡","🔴"))) -> 🟢 | F31: 0.33 | G31: =IF(B31=0,"—",IF(D31<=F31,"🟢 OK","🔴 Excede")) -> 🟢 OK | H31: 5 pers. | I31: Noche nueva desde abril — monitorizar
A32: Lunes | B32: {=IFERROR(SUMPRODUCT((WEEKDAY('Facturación 2026'!$A$4:$A$253,2)=1)*'Facturación 2026'!$F$4:$F$253)/SUMPRODUCT((WEEKDAY('Facturación 2026'!$A$4:$A$253,2)=1)*('Facturación 2026'!$F$4:$F$253>0)*1),0)} -> 0 | C32: {=IFERROR(SUMPRODUCT((WEEKDAY('Facturación 2026'!$A$4:$A$253,2)=1)*'Facturación 2026'!$J$4:$J$253)/SUMPRODUCT((WEEKDAY('Facturación 2026'!$A$4:$A$253,2)=1)*('Facturación 2026'!$F$4:$F$253>0)*1),0)} -> 0 | D32: =IFERROR(C32/B32,"—") -> — | E32: =IF(D32="—","",IF(D32<=0.33,"🟢",IF(D32<=0.38,"🟡","🔴"))) | G32: =IF(B32=0,"—",IF(D32<=F32,"🟢 OK","🔴 Excede")) -> — | H32: — | I32: Cierre programado
A33: Martes | B33: {=IFERROR(SUMPRODUCT((WEEKDAY('Facturación 2026'!$A$4:$A$253,2)=2)*'Facturación 2026'!$F$4:$F$253)/SUMPRODUCT((WEEKDAY('Facturación 2026'!$A$4:$A$253,2)=2)*('Facturación 2026'!$F$4:$F$253>0)*1),0)} -> 0 | C33: {=IFERROR(SUMPRODUCT((WEEKDAY('Facturación 2026'!$A$4:$A$253,2)=2)*'Facturación 2026'!$J$4:$J$253)/SUMPRODUCT((WEEKDAY('Facturación 2026'!$A$4:$A$253,2)=2)*('Facturación 2026'!$F$4:$F$253>0)*1),0)} -> 0 | D33: =IFERROR(C33/B33,"—") -> — | E33: =IF(D33="—","",IF(D33<=0.33,"🟢",IF(D33<=0.38,"🟡","🔴"))) | G33: =IF(B33=0,"—",IF(D33<=F33,"🟢 OK","🔴 Excede")) -> — | H33: — | I33: Cierre programado
A36: COSTES DE PERSONAL — TOP EMPLEADOS (ene–abr 2026 corregido)
A37: Empleado | B37: €/hora | C37: Total € | D37: % s/masa | E37: Coste/€vendido | F37: Turno principal | G37: Días semana | H37: Nota gerencia
A38: ='Resumen Empleado'!A4 -> Sonia | B38: ='Resumen Empleado'!B4 -> 16 | C38: {=SUMPRODUCT(('Horarios Personal'!$D$5:$D$816='Resumen Empleado'!A4)*IFERROR('Horarios Personal'!$L$5:$L$816*1,0))} -> 10981.333 | D38: =IFERROR(C38/SUM(C38:C43),0) -> 0.40103832 | E38: =IFERROR(C38/'Facturación 2026'!P16,0) -> 0.10425381 | F38: Todos los turnos | G38: Mié–Dom | H38: Mayor coste unit. — alta productividad domingos
A39: ='Resumen Empleado'!A5 -> Lourdes | B39: ='Resumen Empleado'!B5 -> 10 | C39: {=SUMPRODUCT(('Horarios Personal'!$D$5:$D$816='Resumen Empleado'!A5)*IFERROR('Horarios Personal'!$L$5:$L$816*1,0))} -> 6740 | D39: =IFERROR(C39/SUM(C38:C43),0) -> 0.24614482 | E39: =IFERROR(C39/'Facturación 2026'!P16,0) -> 0.06398774 | F39: Mañana/split | G39: Mié–Dom | H39: Versatilidad: MA+NO. Control fichajes splits
A40: ='Resumen Empleado'!A6 -> Mireia M | B40: ='Resumen Empleado'!B6 -> 17.13 | C40: {=SUMPRODUCT(('Horarios Personal'!$D$5:$D$816='Resumen Empleado'!A6)*IFERROR('Horarios Personal'!$L$5:$L$816*1,0))} -> 308.34 | D40: =IFERROR(C40/SUM(C38:C43),0) -> 0.011260578 | E40: =IFERROR(C40/'Facturación 2026'!P16,0) -> 0.0029272967 | F40: Noche fija | G40: Todos | H40: Coste fijo diario (34,26€). Revisar ROI días bajos
A41: ='Resumen Empleado'!A7 -> Alejandra | B41: ='Resumen Empleado'!B7 -> 6.39 | C41: {=SUMPRODUCT(('Horarios Personal'!$D$5:$D$816='Resumen Empleado'!A7)*IFERROR('Horarios Personal'!$L$5:$L$816*1,0))} -> 2317.9725 | D41: =IFERROR(C41/SUM(C38:C43),0) -> 0.084652362 | E41: =IFERROR(C41/'Facturación 2026'!P16,0) -> 0.022006205 | F41: Mañana/Noche | G41: Mié–Dom | H41: Polivalente. Buena relación coste-rendimiento
A42: ='Resumen Empleado'!A8 -> Jonh | B42: ='Resumen Empleado'!B8 -> 7.25 | C42: {=SUMPRODUCT(('Horarios Personal'!$D$5:$D$816='Resumen Empleado'!A8)*IFERROR('Horarios Personal'!$L$5:$L$816*1,0))} -> 4605.5675 | D42: =IFERROR(C42/SUM(C38:C43),0) -> 0.16819534 | E42: =IFERROR(C42/'Facturación 2026'!P16,0) -> 0.043724015 | F42: Mediodía/Noche | G42: Mié–Dom | H42: Buen perfil noche. Ampliable en alta temporada
A43: ='Resumen Empleado'!A9 -> Rubí | B43: ='Resumen Empleado'!B9 -> 5.17 | C43: {=SUMPRODUCT(('Horarios Personal'!$D$5:$D$816='Resumen Empleado'!A9)*IFERROR('Horarios Personal'!$L$5:$L$816*1,0))} -> 2429.0408 | D43: =IFERROR(C43/SUM(C38:C43),0) -> 0.088708578 | E43: =IFERROR(C43/'Facturación 2026'!P16,0) -> 0.023060658 | F43: Mañana | G43: Mié–Dom | H43: Perfil mañana — revisar disponibilidad verano
A46: ALERTAS OPERATIVAS Y CHECKLIST DE GERENCIA
B47: Prioridad | C47: Concepto | D47: Detalle / Acción
A48: ⚡ | B48: URGENTE | D48: 26/04/2026 — Joan Pera Casino | G48: Confirmado · Reforzar turno noche: +1 sala +1 barra · Prev. 2.800€
A49: 📋 | B49: MENSUAL | D49: Revisar agenda Casino Caldes | G49: 1er lunes mes: tscproducciones.cat + entrapolis.com + @tscproduccionescat
A50: ⚠️ | B50: FICHAJE | D50: Alerta registros >12h/turno | G50: 5 errores detectados ene-abr = −1.366€ coste ficticio. Implementar validación.
A51: 💰 | B51: RATIO | D51: Ratio coste/venta: 33,4% | G51: Objetivo <35% ✓ · Verano bajará 25-28% · Enero fue el mes más alto (40%)
A52: 👥 | B52: PLANTILLA | D52: Mireia M. = coste fijo 34,26€/noche | G52: Evaluar ROI en días <600€ facturación noche. Considerar flexibilizar.
A53: 📈 | B53: PREVISION | D53: Julio–Agosto: pico temporada alta | G53: Reforzar plantilla +2 pers/día. Prever género +40%. Horario mañanas sáb/dom.
A54: 🔄 | B54: HORARIO | D54: Nuevo horario desde 6 abril | G54: Sin mañana Mié-Vie. Domingo noche abierta. Monitorizar impacto en ratio.
A55: 🎭 | B55: CASINO | D55: Programación 2026 sin confirmar (nov) | G55: Contactar tscproducciones.cat para fecha noviembre. Impacto ×2.5 noche viernes.
A57: INDICADORES FINANCIEROS CLAVE — VISIÓN GERENCIA
A58: KPI Financiero | B58: Valor Real | C58: Objetivo | D58: Estado | E58: Tendencia | F58: Comentario
A59: Ratio coste laboral / ventas | B59: {=IFERROR(SUMPRODUCT(('Facturación 2026'!$J$4:$J$253)*1)/'Facturación 2026'!P16,0)} -> 0.24071286 | C59: <35% | D59: =IF(B59<=0.35,"🟢 OK",IF(B59<=0.4,"🟡 Atención","🔴 Excede")) -> 🟢 OK | E59: ↗ Mejorando | F59: Cierre mañanas entre semana desde abril reducirá ~4pp
A60: Margen bruto operativo | B60: =IFERROR(1-B59,0) -> 0.75928714 | C60: >65% | D60: =IF(B60>=0.65,"🟢 OK",IF(B60>=0.6,"🟡 Atención","🔴 Bajo")) -> 🟢 OK | E60: → Estable | F60: Temporada alta empujará al 72-75%
A61: Facturación por día operativo | B61: {=IFERROR('Facturación 2026'!P16/SUMPRODUCT(('Facturación 2026'!$F$4:$F$253>0)*1),0)} -> 1385.9563 | C61: >1.300€ | D61: =IF(B61>=1300,"🟢 OK",IF(B61>=1000,"🟡 Atención","🔴 Bajo")) -> 🟢 OK | E61: ↗ Mejorando | F61: Enero bajo (909€/día); feb-mar recuperando
A62: Crecimiento YoY ene-abr | B62: =IFERROR(('Facturación 2026'!P16-SUM('Facturación 2026'!T4:T7))/SUM('Facturación 2026'!T4:T7),0) -> 0.054625753 | C62: >10% | D62: =IF(B62>=0.1,"🟢 OK",IF(B62>=0,"🟡 Atención","🔴 Caída")) -> 🟡 Atención | E62: ↗ Fuerte | F62: 2026 supera 2025 en 3 de 4 meses con datos
A63: % días con evento Casino | B63: {=IFERROR(SUMPRODUCT(('Facturación 2026'!$L$4:$L$253<>"")*1)/SUMPRODUCT(('Facturación 2026'!$F$4:$F$253>0)*1),0)} -> 0.15789474 | C63: >12% | D63: =IF(B63>=0.12,"🟢 OK",IF(B63>=0.08,"🟡 Mejorar","🔴 Bajo")) -> 🟢 OK | E63: → Estable | F63: Confirmar espectáculo noviembre para subir KPI
A64: Ticket medio noche viernes | B64: {=IFERROR(SUMPRODUCT((WEEKDAY('Facturación 2026'!$A$4:$A$253,2)=5)*'Facturación 2026'!$E$4:$E$253)/SUMPRODUCT((WEEKDAY('Facturación 2026'!$A$4:$A$253,2)=5)*('Facturación 2026'!$E$4:$E$253>0)*1),0)} -> 858.63925 | C64: >1.000€ | D64: =IF(B64>=1000,"🟢 OK",IF(B64>=700,"🟡 Atención","🔴 Bajo")) -> 🟡 Atención | E64: ↗ Mejorando | F64: Efecto Casino muy visible. Monitorizar mensual
A65: Coste personal / día operativo | B65: {=IFERROR(SUMPRODUCT(('Facturación 2026'!$J$4:$J$253)*1)/SUMPRODUCT(('Facturación 2026'!$F$4:$F$253>0)*1),0)} -> 333.6175 | C65: <400€ | D65: =IF(B65<=400,"🟢 OK",IF(B65<=500,"🟡 Atención","🔴 Alto")) -> 🟢 OK | E65: ↗ Mejorando | F65: Post-cambio horario bajará a ~310€/día estimado
A66: Días con ratio >45% coste | B66: {=IFERROR(SUMPRODUCT(('Facturación 2026'!$K$4:$K$253>0.45)*('Facturación 2026'!$F$4:$F$253>0)*1)/SUMPRODUCT(('Facturación 2026'!$F$4:$F$253>0)*1),0)} -> 0.28947368 | C66: <10% | D66: =IF(B66<=0.1,"🟢 OK",IF(B66<=0.15,"🟡 Atención","🔴 Muchos")) -> 🔴 Muchos | E66: ↘ Bajando | F66: Concentrados en miércoles y días bajos enero
A68: ANÁLISIS POR CAJA — COMPARATIVA CAJA 1 vs CAJA 2
A70: Métrica | B70: Caja 1 (Barra) | C70: Caja 2 (Comedor) | D70: Total Negocio | E70: % Caja 1 | F70: % Caja 2
A71: Facturación Total | B71: ='Caja 1'!D191 | C71: ='Caja 2'!E173 -> 185.864 | D71: =B71+C71 -> #VALUE! | E71: =IFERROR(B71/D71,0) -> 0 | F71: =IFERROR(C71/D71,0) -> 0
A72: Ticket Medio | B72: =IFERROR('Caja 1'!D191/'Caja 1'!B191,0) -> 0 | C72: =IFERROR('Caja 2'!E173/'Caja 2'!D173,0) -> 9.2932 | E72: €/turno | F72: €/comensal
A73: Turno más fuerte | B73: Mediodía | C73: Mediodía | E73: =IFERROR('Caja 1'!B202/'Caja 1'!D191,0) -> 0 | F73: =IFERROR('Caja 2'!E178/'Caja 2'!E173,0) -> 4.1552856
A74: Coste Personal | B74: ='Caja 1'!F191 -> 0 | C74: ='Caja 2'!G173 -> 0 | D74: =B74+C74 -> 0 | E74: =IFERROR(B74/B71,0) -> 0 | F74: =IFERROR(C74/C71,0) -> 0
A75: Margen Neto | B75: =B71-B74 -> #VALUE! | C75: =C71-C74 -> 185.864 | D75: =D71-D74 -> #VALUE! | E75: =IFERROR(B75/B71,0) -> 0 | F75: =IFERROR(C75/C71,0) -> 1
A76: Comensales (Caja 2) | B76: — | C76: ='Caja 2'!D173 -> 20 | D76: =C76 -> 20 | E76: n/a | F76: =IFERROR(C71/C76,0) -> 9.2932
A77: Mejor mes | B77: {=INDEX({"Ene","Feb","Mar","Abr"},MATCH(MAX('Caja 1'!D187:'Caja 1'!D190),'Caja 1'!D187:'Caja 1'!D190,0))} -> #N/A | C77: {=INDEX({"Ene","Feb","Mar","Abr"},MATCH(MAX('Caja 2'!E169:'Caja 2'!E172),'Caja 2'!E169:'Caja 2'!E172,0))} -> Feb | E77: =MAX('Caja 1'!D187:'Caja 1'!D190) -> 0 | F77: =MAX('Caja 2'!E169:'Caja 2'!E172) -> 214.773
A78: Ratio Caja2/Caja1 | D78: =IFERROR(C71/B71,0) -> 0 | E78: Caja 2 factura | F78: veces más
A83: PRODUCT MIX — TOP 15 PRODUCTOS Y ANÁLISIS POR FAMILIA (Datos Caja 1 + Caja 2)
A84: # | B84: Producto | C84: Familia | D84: Uds Totales | E84: Importe (€) | F84: % Mix Uds | G84: % Mix € | H84: Ticket Medio
A85: 1 | B85: Cafe amb llet | C85: Cafe | D85: =SUMIF(TBL_Ventas[Producto],B85,TBL_Ventas[Uds]) -> 3873.1 | E85: =SUMIF(TBL_Ventas[Producto],B85,TBL_Ventas[Importe]) -> 6610.84 | F85: =IFERROR(D85/SUM(D$85:D$99),0) -> 0.17370031 | G85: =IFERROR(E85/SUM(E$85:E$99),0) -> 0.080703065 | H85: =IFERROR(E85/D85,0) -> 1.7068601
A86: 2 | B86: Tallat | C86: Café | D86: =SUMIF(TBL_Ventas[Producto],B86,TBL_Ventas[Uds]) -> 3382.5 | E86: =SUMIF(TBL_Ventas[Producto],B86,TBL_Ventas[Importe]) -> 5595.97 | F86: =IFERROR(D86/SUM(D$85:D$99),0) -> 0.15169794 | G86: =IFERROR(E86/SUM(E$85:E$99),0) -> 0.06831385 | H86: =IFERROR(E86/D86,0) -> 1.6543888
A87: 3 | B87: Aigua Vidre | C87: Refrescos | D87: =SUMIF(TBL_Ventas[Producto],B87,TBL_Ventas[Uds]) -> 1877 | E87: =SUMIF(TBL_Ventas[Producto],B87,TBL_Ventas[Importe]) -> 3827.44 | F87: =IFERROR(D87/SUM(D$85:D$99),0) -> 0.084179463 | G87: =IFERROR(E87/SUM(E$85:E$99),0) -> 0.046724189 | H87: =IFERROR(E87/D87,0) -> 2.0391263
A88: 4 | B88: Alhambra C:Copa | C88: Cervezas | D88: =SUMIF(TBL_Ventas[Producto],B88,TBL_Ventas[Uds]) -> 1796 | E88: =SUMIF(TBL_Ventas[Producto],B88,TBL_Ventas[Importe]) -> 15020.69 | F88: =IFERROR(D88/SUM(D$85:D$99),0) -> 0.080546785 | G88: =IFERROR(E88/SUM(E$85:E$99),0) -> 0.18336788 | H88: =IFERROR(E88/D88,0) -> 8.3634131
A89: 5 | B89: Menu | C89: Menu | D89: =SUMIF(TBL_Ventas[Producto],B89,TBL_Ventas[Uds]) -> 1444 | E89: =SUMIF(TBL_Ventas[Producto],B89,TBL_Ventas[Importe]) -> 20938.86 | F89: =IFERROR(D89/SUM(D$85:D$99),0) -> 0.064760333 | G89: =IFERROR(E89/SUM(E$85:E$99),0) -> 0.25561505 | H89: =IFERROR(E89/D89,0) -> 14.500596
A90: 6 | B90: Patates Braves | C90: Tapas Calientes | D90: =SUMIF(TBL_Ventas[Producto],B90,TBL_Ventas[Uds]) -> 1368 | E90: =SUMIF(TBL_Ventas[Producto],B90,TBL_Ventas[Importe]) -> 7500.9 | F90: =IFERROR(D90/SUM(D$85:D$99),0) -> 0.061351894 | G90: =IFERROR(E90/SUM(E$85:E$99),0) -> 0.091568639 | H90: =IFERROR(E90/D90,0) -> 5.483114
A91: 7 | B91: Cafe Sol | C91: Menu Postres | D91: =SUMIF(TBL_Ventas[Producto],B91,TBL_Ventas[Uds]) -> 1917 | E91: =SUMIF(TBL_Ventas[Producto],B91,TBL_Ventas[Importe]) -> 2932.39 | F91: =IFERROR(D91/SUM(D$85:D$99),0) -> 0.085973378 | G91: =IFERROR(E91/SUM(E$85:E$99),0) -> 0.035797699 | H91: =IFERROR(E91/D91,0) -> 1.5296766
A92: 8 | B92: Cafè amb llet | C92: Café | D92: =SUMIF(TBL_Ventas[Producto],B92,TBL_Ventas[Uds]) -> 830 | E92: =SUMIF(TBL_Ventas[Producto],B92,TBL_Ventas[Importe]) -> 1092.69 | F92: =IFERROR(D92/SUM(D$85:D$99),0) -> 0.037223737 | G92: =IFERROR(E92/SUM(E$85:E$99),0) -> 0.013339217 | H92: =IFERROR(E92/D92,0) -> 1.316494
A93: 9 | B93: Cafe sol | C93: Cafe | D93: =SUMIF(TBL_Ventas[Producto],B93,TBL_Ventas[Uds]) -> 1917 | E93: =SUMIF(TBL_Ventas[Producto],B93,TBL_Ventas[Importe]) -> 2932.39 | F93: =IFERROR(D93/SUM(D$85:D$99),0) -> 0.085973378 | G93: =IFERROR(E93/SUM(E$85:E$99),0) -> 0.035797699 | H93: =IFERROR(E93/D93,0) -> 1.5296766
A94: 10 | B94: Croquetes de l'àvia | C94: Tapas Calientes | D94: =SUMIF(TBL_Ventas[Producto],B94,TBL_Ventas[Uds]) -> 754 | E94: =SUMIF(TBL_Ventas[Producto],B94,TBL_Ventas[Importe]) -> 2755.64 | F94: =IFERROR(D94/SUM(D$85:D$99),0) -> 0.033815299 | G94: =IFERROR(E94/SUM(E$85:E$99),0) -> 0.03363999 | H94: =IFERROR(E94/D94,0) -> 3.654695
A95: 11 | B95: Calamars a l'andalusa | C95: Tapas Calientes | D95: =SUMIF(TBL_Ventas[Producto],B95,TBL_Ventas[Uds]) -> 732 | E95: =SUMIF(TBL_Ventas[Producto],B95,TBL_Ventas[Importe]) -> 8008.33 | F95: =IFERROR(D95/SUM(D$85:D$99),0) -> 0.032828645 | G95: =IFERROR(E95/SUM(E$85:E$99),0) -> 0.097763186 | H95: =IFERROR(E95/D95,0) -> 10.940342
A96: 12 | B96: Pa cristal·lí | C96: Suplementos | D96: =SUMIF(TBL_Ventas[Producto],B96,TBL_Ventas[Uds]) -> 645 | E96: =SUMIF(TBL_Ventas[Producto],B96,TBL_Ventas[Importe]) -> 2220.58 | F96: =IFERROR(D96/SUM(D$85:D$99),0) -> 0.02892688 | G96: =IFERROR(E96/SUM(E$85:E$99),0) -> 0.027108145 | H96: =IFERROR(E96/D96,0) -> 3.4427597
... A99: 15 | B99: Gel | C99: Suplementos | D99: =SUMIF(TBL_Ventas[Producto],B99,TBL_Ventas[Uds]) -> 562 | E99: =SUMIF(TBL_Ventas[Producto],B99,TBL_Ventas[Importe]) -> 57.05 | F99: =IFERROR(D99/SUM(D$85:D$99),0) -> 0.025204506 | G99: =IFERROR(E99/SUM(E$85:E$99),0) -> 0.00069644854 | H99: =IFERROR(E99/D99,0) -> 0.10151246
A101: TOP FAMILIAS POR FACTURACIÓN
A102: # | B102: Familia | C102: Nº Productos | D102: Uds Totales | E102: Importe (€) | F102: % Facturación | G102: Ticket Medio | H102: Uds/Semana
A103: 1 | B103: Tapas Calientes | C103: 109 | D103: =SUMIF(TBL_Ventas[Familia],"Tapas Calientes",TBL_Ventas[Uds]) -> 8842 | E103: =SUMIF(TBL_Ventas[Familia],"Tapas Calientes",TBL_Ventas[Importe]) -> 61781.82 | F103: =IFERROR(E103/SUM(E$103:E$112),0) -> 0.37282663 | G103: =IFERROR(E103/D103,0) -> 6.9873128 | H103: =IFERROR(D103/48,0) -> 184.20833
A104: 2 | B104: Cervezas | C104: 52 | D104: =SUMIF(TBL_Ventas[Familia],"Cervezas",TBL_Ventas[Uds]) -> 4485 | E104: =SUMIF(TBL_Ventas[Familia],"Cervezas",TBL_Ventas[Importe]) -> 23912.14 | F104: =IFERROR(E104/SUM(E$103:E$112),0) -> 0.14429945 | G104: =IFERROR(E104/D104,0) -> 5.3315808 | H104: =IFERROR(D104/48,0) -> 93.4375
A105: 3 | B105: Menu | C105: 3 | D105: =SUMIF(TBL_Ventas[Familia],"Menu",TBL_Ventas[Uds]) -> 1469 | E105: =SUMIF(TBL_Ventas[Familia],"Menu",TBL_Ventas[Importe]) -> 20942.5 | F105: =IFERROR(E105/SUM(E$103:E$112),0) -> 0.12637895 | G105: =IFERROR(E105/D105,0) -> 14.256297 | H105: =IFERROR(D105/48,0) -> 30.604167
A106: 4 | B106: Refrescos | C106: 53 | D106: =SUMIF(TBL_Ventas[Familia],"Refrescos",TBL_Ventas[Uds]) -> 4978 | E106: =SUMIF(TBL_Ventas[Familia],"Refrescos",TBL_Ventas[Importe]) -> 10529.8 | F106: =IFERROR(E106/SUM(E$103:E$112),0) -> 0.0635428 | G106: =IFERROR(E106/D106,0) -> 2.1152672 | H106: =IFERROR(D106/48,0) -> 103.70833
A107: 5 | B107: Cafe | C107: 32 | D107: =SUMIF(TBL_Ventas[Familia],"Cafe",TBL_Ventas[Uds]) -> 5472.1 | E107: =SUMIF(TBL_Ventas[Familia],"Cafe",TBL_Ventas[Importe]) -> 9397.55 | F107: =IFERROR(E107/SUM(E$103:E$112),0) -> 0.05671016 | G107: =IFERROR(E107/D107,0) -> 1.7173571 | H107: =IFERROR(D107/48,0) -> 114.00208
A108: 6 | B108: Huevos estrellados | C108: 9 | D108: =SUMIF(TBL_Ventas[Familia],"Huevos estrellados",TBL_Ventas[Uds]) -> 918 | E108: =SUMIF(TBL_Ventas[Familia],"Huevos estrellados",TBL_Ventas[Importe]) -> 10926.94 | F108: =IFERROR(E108/SUM(E$103:E$112),0) -> 0.065939368 | G108: =IFERROR(E108/D108,0) -> 11.902985 | H108: =IFERROR(D108/48,0) -> 19.125
A109: 7 | B109: Postres | C109: 49 | D109: =SUMIF(TBL_Ventas[Familia],"Postres",TBL_Ventas[Uds]) -> 1677 | E109: =SUMIF(TBL_Ventas[Familia],"Postres",TBL_Ventas[Importe]) -> 8031.15 | F109: =IFERROR(E109/SUM(E$103:E$112),0) -> 0.048464525 | G109: =IFERROR(E109/D109,0) -> 4.7889982 | H109: =IFERROR(D109/48,0) -> 34.9375
A110: 8 | B110: Café | C110: 9 | D110: =SUMIF(TBL_Ventas[Familia],"Café",TBL_Ventas[Uds]) -> 4643.5 | E110: =SUMIF(TBL_Ventas[Familia],"Café",TBL_Ventas[Importe]) -> 7564.94 | F110: =IFERROR(E110/SUM(E$103:E$112),0) -> 0.045651149 | G110: =IFERROR(E110/D110,0) -> 1.6291461 | H110: =IFERROR(D110/48,0) -> 96.739583
A111: 9 | B111: Vinos | C111: 70 | D111: =SUMIF(TBL_Ventas[Familia],"Vinos",TBL_Ventas[Uds]) -> 1359 | E111: =SUMIF(TBL_Ventas[Familia],"Vinos",TBL_Ventas[Importe]) -> 6471.84 | F111: =IFERROR(E111/SUM(E$103:E$112),0) -> 0.039054762 | G111: =IFERROR(E111/D111,0) -> 4.7622075 | H111: =IFERROR(D111/48,0) -> 28.3125
A112: 10 | B112: Tosta Pizzas | C112: 9 | D112: =SUMIF(TBL_Ventas[Familia],"Tosta Pizzas",TBL_Ventas[Uds]) -> 526 | E112: =SUMIF(TBL_Ventas[Familia],"Tosta Pizzas",TBL_Ventas[Importe]) -> 6153.25 | F112: =IFERROR(E112/SUM(E$103:E$112),0) -> 0.037132209 | G112: =IFERROR(E112/D112,0) -> 11.698194 | H112: =IFERROR(D112/48,0) -> 10.958333
A113: 🔴 Alta | B113: Confirmar evento Casino noviembre 2026 | C113: Gerencia | D113: 30/05/2026 | E113: Pendiente | F113: +4.000€ noche viernes
A114: 🔴 Alta | B114: Implementar alerta fichajes >12h en sistema | C114: RRHH | D114: 15/05/2026 | E114: Pendiente | F114: −1.400€/año errores
A115: 🟡 Media | B115: Revisar ROI Mireia M. días bajos | C115: Gerencia | D115: 30/04/2026 | E115: En revisión | F115: −500€/mes potencial
A116: 🟡 Media | B116: Plan de personal julio-agosto (+2 pers) | C116: RRHH | D116: 01/06/2026 | E116: Pendiente | F116: Capacidad +25% verano
A117: 🟡 Media | B117: Seguimiento agenda Casino 1er lunes mayo | C117: Gerencia | D117: 05/05/2026 | E117: Recurrente | F117: ×2.5 noches evento
A118: 🟢 Normal | B118: Validar datos reales mayo en previsión | C118: Gerencia | D118: 31/05/2026 | E118: Pendiente | F118: Calibración modelo
...

Sheet Arqueo e incentivos
K4: 2025 | M4: 2026
K5: 5 - 7 Mercado de Navidad
K7: 27-05 carnaval | M7: 12-18 carnaval
I8: segunda quincena | K8: 18-26 fem bullir | M8: 16 - 22 fem bullir
K9: 14 - 21 semana santa | M9: 29 - 06 semana santa
K10: 05-12 escaldarium
K11: 11-18 Fiesta mayor | S11: -27177.279
L14: 30243.025
G17: Incremento IPC | H17: 0.03 | J17: Mes | K17: Ventas 2025 | L17: Previsión | M17: Ventas 2026 | N17: % sobre 24 | O17: Diferencia | P17: Días Trabajados | Q17: In Ven/Dia | R17: Hasta objetivo | S17: Incentivo | T17: Efectivo
G18: Incentivos | H18: 0.1 | J18: Enero | K18: 22382.26 | L18: =K18*H$17+K18 -> 23053.728 | M18: =SUMIFS($P:$P,$D:$D,">="&DATE(2026,MATCH(LOWER(J18),{"enero","febrero","marzo","abril","mayo","junio","julio","agosto","septiembre","octubre","noviembre","diciembre"},0),1),$D:$D,"<"&DATE(2026,MATCH(LOWER(J18),{"enero","febrero","marzo","abril","mayo","junio","julio","agosto","septiembre","octubre","noviembre","diciembre"},0)+1,1)) -> 25876.455 | N18: =-1+M18/K18 -> 0.15611447 | O18: =L18-K18 -> 671.4678 | P18: 23 | Q18: =O18/P18 -> 29.194252 | R18: =M18-L18 -> 2822.7267 | S18: =Tabla14[[#This Row],[Hasta objetivo]]*H$18 -> 282.27267 | T18: =SUMIFS($F:$F,$D:$D,">="&DATE(2026,MATCH(LOWER(J18),{"enero","febrero","marzo","abril","mayo","junio","julio","agosto","septiembre","octubre","noviembre","diciembre"},0),1),$D:$D,"<"&DATE(2026,MATCH(LOWER(J18),{"enero","febrero","marzo","abril","mayo","junio","julio","agosto","septiembre","octubre","noviembre","diciembre"},0)+1,1)) -> 3139
J19: Febrero | K19: 22499.24 | L19: =K19*H$17+K19 -> 23174.217 | M19: =SUMIFS($P:$P,$D:$D,">="&DATE(2026,MATCH(LOWER(J19),{"enero","febrero","marzo","abril","mayo","junio","julio","agosto","septiembre","octubre","noviembre","diciembre"},0),1),$D:$D,"<"&DATE(2026,MATCH(LOWER(J19),{"enero","febrero","marzo","abril","mayo","junio","julio","agosto","septiembre","octubre","noviembre","diciembre"},0)+1,1)) -> 26984.915 | N19: =-1+M19/K19 -> 0.19937009 | O19: 674.98 | P19: 16 | Q19: =O19/P19 -> 42.18625 | R19: =M19-L19 -> 3810.6983 | S19: =Tabla14[[#This Row],[Hasta objetivo]]*H$18 -> 381.06983 | T19: =SUMIFS($F:$F,$D:$D,">="&DATE(2026,MATCH(LOWER(J19),{"enero","febrero","marzo","abril","mayo","junio","julio","agosto","septiembre","octubre","noviembre","diciembre"},0),1),$D:$D,"<"&DATE(2026,MATCH(LOWER(J19),{"enero","febrero","marzo","abril","mayo","junio","julio","agosto","septiembre","octubre","noviembre","diciembre"},0)+1,1)) -> 4526.17
E20: Saldo anterior 2025 | G20: =[1]Hoja10!$G$22 -> 5530.1213 | J20: Marzo | K20: 21443.45 | L20: =K20*H$17+K20 -> 22086.753 | M20: =SUMIFS($P:$P,$D:$D,">="&DATE(2026,MATCH(LOWER(J20),{"enero","febrero","marzo","abril","mayo","junio","julio","agosto","septiembre","octubre","noviembre","diciembre"},0),1),$D:$D,"<"&DATE(2026,MATCH(LOWER(J20),{"enero","febrero","marzo","abril","mayo","junio","julio","agosto","septiembre","octubre","noviembre","diciembre"},0)+1,1)) -> 19903.077 | N20: =-1+M20/K20 -> -0.071834184 | O20: 643.3 | P20: 15 | Q20: =O20/P20 -> 42.886667 | R20: =M20-L20 -> -2183.6762 | S20: =Tabla14[[#This Row],[Hasta objetivo]]*H$18 -> -218.36762 | T20: =SUMIFS($F:$F,$D:$D,">="&DATE(2026,MATCH(LOWER(J20),{"enero","febrero","marzo","abril","mayo","junio","julio","agosto","septiembre","octubre","noviembre","diciembre"},0),1),$D:$D,"<"&DATE(2026,MATCH(LOWER(J20),{"enero","febrero","marzo","abril","mayo","junio","julio","agosto","septiembre","octubre","noviembre","diciembre"},0)+1,1)) -> 3494.85
E21: Arrastre efectivo | G21: =SUM(Tabla15[Ingreso]) -> 13048.68 | J21: Abril | K21: 31530.01 | L21: =K21*H$17+K21 -> 32475.91 | M21: =SUMIFS($P:$P,$D:$D,">="&DATE(2026,MATCH(LOWER(J21),{"enero","febrero","marzo","abril","mayo","junio","julio","agosto","septiembre","octubre","noviembre","diciembre"},0),1),$D:$D,"<"&DATE(2026,MATCH(LOWER(J21),{"enero","febrero","marzo","abril","mayo","junio","julio","agosto","septiembre","octubre","noviembre","diciembre"},0)+1,1)) -> 30141.918 | N21: =-1+M21/K21 -> -0.044024465 | O21: 945.9 | P21: 22 | Q21: =O21/P21 -> 42.995455 | R21: =M21-L21 -> -2333.9921 | S21: =Tabla14[[#This Row],[Hasta objetivo]]*H$18 -> -233.39921 | T21: =SUMIFS($F:$F,$D:$D,">="&DATE(2026,MATCH(LOWER(J21),{"enero","febrero","marzo","abril","mayo","junio","julio","agosto","septiembre","octubre","noviembre","diciembre"},0),1),$D:$D,"<"&DATE(2026,MATCH(LOWER(J21),{"enero","febrero","marzo","abril","mayo","junio","julio","agosto","septiembre","octubre","noviembre","diciembre"},0)+1,1)) -> 5390.6
E22: Ingresado Bbva | G22: 0 | J22: Mayo | K22: 29362.16 | L22: =K22*H$17+K22 -> 30243.025 | M22: =SUMIFS($P:$P,$D:$D,">="&DATE(2026,MATCH(LOWER(J22),{"enero","febrero","marzo","abril","mayo","junio","julio","agosto","septiembre","octubre","noviembre","diciembre"},0),1),$D:$D,"<"&DATE(2026,MATCH(LOWER(J22),{"enero","febrero","marzo","abril","mayo","junio","julio","agosto","septiembre","octubre","noviembre","diciembre"},0)+1,1)) -> 3065.7455 | N22: =-1+M22/K22 -> -0.89558856 | O22: 880.86 | P22: 23 | Q22: =O22/P22 -> 38.298261 | R22: =M22-L22 -> -27177.279 | S22: =Tabla14[[#This Row],[Hasta objetivo]]*H$18 -> -2717.7279 | T22: =SUMIFS($F:$F,$D:$D,">="&DATE(2026,MATCH(LOWER(J22),{"enero","febrero","marzo","abril","mayo","junio","julio","agosto","septiembre","octubre","noviembre","diciembre"},0),1),$D:$D,"<"&DATE(2026,MATCH(LOWER(J22),{"enero","febrero","marzo","abril","mayo","junio","julio","agosto","septiembre","octubre","noviembre","diciembre"},0)+1,1)) -> 77.7
G23: =G20+G21-G22 -> 18578.801 | J23: Junio | K23: 33832.98 | L23: =K23*H$17+K23 -> 34847.969 | M23: =SUMIFS($P:$P,$D:$D,">="&DATE(2026,MATCH(LOWER(J23),{"enero","febrero","marzo","abril","mayo","junio","julio","agosto","septiembre","octubre","noviembre","diciembre"},0),1),$D:$D,"<"&DATE(2026,MATCH(LOWER(J23),{"enero","febrero","marzo","abril","mayo","junio","julio","agosto","septiembre","octubre","noviembre","diciembre"},0)+1,1)) -> 0 | N23: =-1+M23/K23 -> -1 | O23: 1014.99 | P23: 20 | Q23: =O23/P23 -> 50.7495 | R23: =M23-L23 -> -34847.969 | S23: =Tabla14[[#This Row],[Hasta objetivo]]*H$18 -> -3484.7969 | T23: =SUMIFS($F:$F,$D:$D,">="&DATE(2026,MATCH(LOWER(J23),{"enero","febrero","marzo","abril","mayo","junio","julio","agosto","septiembre","octubre","noviembre","diciembre"},0),1),$D:$D,"<"&DATE(2026,MATCH(LOWER(J23),{"enero","febrero","marzo","abril","mayo","junio","julio","agosto","septiembre","octubre","noviembre","diciembre"},0)+1,1)) -> 0
J24: Julio | K24: 32495.01 | L24: =K24*H$17+K24 -> 33469.86 | M24: =SUMIFS($P:$P,$D:$D,">="&DATE(2026,MATCH(LOWER(J24),{"enero","febrero","marzo","abril","mayo","junio","julio","agosto","septiembre","octubre","noviembre","diciembre"},0),1),$D:$D,"<"&DATE(2026,MATCH(LOWER(J24),{"enero","febrero","marzo","abril","mayo","junio","julio","agosto","septiembre","octubre","noviembre","diciembre"},0)+1,1)) -> 0 | N24: =-1+M24/K24 -> -1 | O24: 974.85 | P24: 23 | Q24: =O24/P24 -> 42.384783 | R24: =M24-L24 -> -33469.86 | S24: =Tabla14[[#This Row],[Hasta objetivo]]*H$18 -> -3346.986 | T24: =SUMIFS($F:$F,$D:$D,">="&DATE(2026,MATCH(LOWER(J24),{"enero","febrero","marzo","abril","mayo","junio","julio","agosto","septiembre","octubre","noviembre","diciembre"},0),1),$D:$D,"<"&DATE(2026,MATCH(LOWER(J24),{"enero","febrero","marzo","abril","mayo","junio","julio","agosto","septiembre","octubre","noviembre","diciembre"},0)+1,1)) -> 0
J25: Agosto | K25: 43459.73 | L25: =K25*H$17+K25 -> 44763.522 | M25: =SUMIFS($P:$P,$D:$D,">="&DATE(2026,MATCH(LOWER(J25),{"enero","febrero","marzo","abril","mayo","junio","julio","agosto","septiembre","octubre","noviembre","diciembre"},0),1),$D:$D,"<"&DATE(2026,MATCH(LOWER(J25),{"enero","febrero","marzo","abril","mayo","junio","julio","agosto","septiembre","octubre","noviembre","diciembre"},0)+1,1)) -> 0 | N25: =-1+M25/K25 -> -1 | O25: 1303.79 | P25: 22 | Q25: =O25/P25 -> 59.263182 | R25: =M25-L25 -> -44763.522 | S25: =Tabla14[[#This Row],[Hasta objetivo]]*H$18 -> -4476.3522 | T25: =SUMIFS($F:$F,$D:$D,">="&DATE(2026,MATCH(LOWER(J25),{"enero","febrero","marzo","abril","mayo","junio","julio","agosto","septiembre","octubre","noviembre","diciembre"},0),1),$D:$D,"<"&DATE(2026,MATCH(LOWER(J25),{"enero","febrero","marzo","abril","mayo","junio","julio","agosto","septiembre","octubre","noviembre","diciembre"},0)+1,1)) -> 0
J26: Septiembre | K26: 27943.16 | L26: =K26*H$17+K26 -> 28781.455 | M26: =SUMIFS($P:$P,$D:$D,">="&DATE(2026,MATCH(LOWER(J26),{"enero","febrero","marzo","abril","mayo","junio","julio","agosto","septiembre","octubre","noviembre","diciembre"},0),1),$D:$D,"<"&DATE(2026,MATCH(LOWER(J26),{"enero","febrero","marzo","abril","mayo","junio","julio","agosto","septiembre","octubre","noviembre","diciembre"},0)+1,1)) -> 0 | N26: =-1+M26/K26 -> -1 | O26: 838.29 | P26: 21 | Q26: =O26/P26 -> 39.918571 | R26: =M26-L26 -> -28781.455 | S26: =Tabla14[[#This Row],[Hasta objetivo]]*H$18 -> -2878.1455 | T26: =SUMIFS($F:$F,$D:$D,">="&DATE(2026,MATCH(LOWER(J26),{"enero","febrero","marzo","abril","mayo","junio","julio","agosto","septiembre","octubre","noviembre","diciembre"},0),1),$D:$D,"<"&DATE(2026,MATCH(LOWER(J26),{"enero","febrero","marzo","abril","mayo","junio","julio","agosto","septiembre","octubre","noviembre","diciembre"},0)+1,1)) -> 0
J27: Octubre | K27: 27843.16 | L27: =K27*H$17+K27 -> 28678.455 | M27: =SUMIFS($P:$P,$D:$D,">="&DATE(2026,MATCH(LOWER(J27),{"enero","febrero","marzo","abril","mayo","junio","julio","agosto","septiembre","octubre","noviembre","diciembre"},0),1),$D:$D,"<"&DATE(2026,MATCH(LOWER(J27),{"enero","febrero","marzo","abril","mayo","junio","julio","agosto","septiembre","octubre","noviembre","diciembre"},0)+1,1)) -> 0 | N27: =-1+M27/K27 -> -1 | O27: 835.29 | P27: 23 | Q27: =O27/P27 -> 36.316957 | R27: =M27-L27 -> -28678.455 | S27: =Tabla14[[#This Row],[Hasta objetivo]]*H$18 -> -2867.8455 | T27: =SUMIFS($F:$F,$D:$D,">="&DATE(2026,MATCH(LOWER(J27),{"enero","febrero","marzo","abril","mayo","junio","julio","agosto","septiembre","octubre","noviembre","diciembre"},0),1),$D:$D,"<"&DATE(2026,MATCH(LOWER(J27),{"enero","febrero","marzo","abril","mayo","junio","julio","agosto","septiembre","octubre","noviembre","diciembre"},0)+1,1)) -> 0
J28: Noviembre | K28: 34247.88 | L28: =K28*H$17+K28 -> 35275.316 | M28: =SUMIFS($P:$P,$D:$D,">="&DATE(2026,MATCH(LOWER(J28),{"enero","febrero","marzo","abril","mayo","junio","julio","agosto","septiembre","octubre","noviembre","diciembre"},0),1),$D:$D,"<"&DATE(2026,MATCH(LOWER(J28),{"enero","febrero","marzo","abril","mayo","junio","julio","agosto","septiembre","octubre","noviembre","diciembre"},0)+1,1)) -> 0 | N28: =-1+M28/K28 -> -1 | O28: 1027.44 | P28: 11 | Q28: =O28/P28 -> 93.403636 | R28: =M28-L28 -> -35275.316 | S28: =Tabla14[[#This Row],[Hasta objetivo]]*H$18 -> -3527.5316 | T28: =SUMIFS($F:$F,$D:$D,">="&DATE(2026,MATCH(LOWER(J28),{"enero","febrero","marzo","abril","mayo","junio","julio","agosto","septiembre","octubre","noviembre","diciembre"},0),1),$D:$D,"<"&DATE(2026,MATCH(LOWER(J28),{"enero","febrero","marzo","abril","mayo","junio","julio","agosto","septiembre","octubre","noviembre","diciembre"},0)+1,1)) -> 0
J29: Diciembre | K29: 36351.3 | L29: =K29*H$17+K29 -> 37441.839 | M29: =SUMIFS($P:$P,$D:$D,">="&DATE(2026,MATCH(LOWER(J29),{"enero","febrero","marzo","abril","mayo","junio","julio","agosto","septiembre","octubre","noviembre","diciembre"},0),1),$D:$D,"<"&DATE(2026,MATCH(LOWER(J29),{"enero","febrero","marzo","abril","mayo","junio","julio","agosto","septiembre","octubre","noviembre","diciembre"},0)+1,1)) -> 0 | N29: =-1+M29/K29 -> -1 | O29: 1090.54 | P29: 17 | Q29: =O29/P29 -> 64.149412 | R29: =M29-L29 -> -37441.839 | S29: =Tabla14[[#This Row],[Hasta objetivo]]*H$18 -> -3744.1839 | T29: =SUMIFS($F:$F,$D:$D,">="&DATE(2026,MATCH(LOWER(J29),{"enero","febrero","marzo","abril","mayo","junio","julio","agosto","septiembre","octubre","noviembre","diciembre"},0),1),$D:$D,"<"&DATE(2026,MATCH(LOWER(J29),{"enero","febrero","marzo","abril","mayo","junio","julio","agosto","septiembre","octubre","noviembre","diciembre"},0)+1,1)) -> 0
D33: Fecha | E33: Contado | F33: Tickets | G33: Visa | H33: Eventos | I33: Passo | J33: Reciclajes | K33: Invitaciones | L33: Personal | M33: Retiros | N33: Ingreso | O33: Bbva | P33: Total Caja | Q33: Efectivo | R33: %Tickets | S33: Columna1 | T33: Facturació A/A | U33: Diferencia | V33: Resto | W33: Dif% | X33: Previsión | Y33: Resultado | Z33: Columna2 | AA33: AA % | AB33: Observaciones
C34: 1 | D34: 46023 | E34: 0 | F34: =Tabla15[[#This Row],[Retiros]]-Tabla15[[#This Row],[Contado]] -> 0 | G34: 0 | H34: 0 | I34: 0 | J34: 0 | K34: 0 | L34: 0 | M34: 0 | N34: =Tabla15[[#This Row],[Contado]] -> 0 | P34: =((Tabla15[[#This Row],[Contado]]+Tabla15[[#This Row],[Visa]]+Tabla15[[#This Row],[Eventos]]+Tabla15[[#This Row],[Passo]]+Tabla15[[#This Row],[Reciclajes]])/1.1)+Tabla15[[#This Row],[Tickets]] -> 0 | Q34: =IFERROR(E34/G34,0) -> 0 | R34: =IFERROR(F34/P34,0) -> 0 | T34: 0 | U34: =Tabla15[[#This Row],[Total Caja]]-Tabla15[[#This Row],[Facturació A/A]] -> 0 | V34: 0 | W34: =Tabla15[[#This Row],[Diferencia]]/Tabla15[[#This Row],[Facturació A/A]] -> #DIV/0! | X34: =Tabla15[[#This Row],[Facturació A/A]]*H$17+Tabla15[[#This Row],[Facturació A/A]] -> 0 | Y34: =Tabla15[[#This Row],[Total Caja]]-Tabla15[[#This Row],[Previsión]] -> 0 | AA34: =SUM(INDEX(Tabla15[[#This Row],[Facturació A/A]],1):Tabla15[[#This Row],[Facturació A/A]]) / SUM(INDEX(Tabla15[[#This Row],[Diferencia]],1):Tabla15[[#This Row],[Diferencia]]) -> #DIV/0! | AB34: lluvias
C35: 2 | D35: 46024 | E35: 133.5 | F35: =Tabla15[[#This Row],[Retiros]]-Tabla15[[#This Row],[Contado]] -> 166.5 | G35: 1442.15 | H35: 0 | I35: 0 | J35: 0 | K35: 0 | L35: 0 | M35: 300 | N35: =Tabla15[[#This Row],[Contado]] -> 133.5 | P35: =((Tabla15[[#This Row],[Contado]]+Tabla15[[#This Row],[Visa]]+Tabla15[[#This Row],[Eventos]]+Tabla15[[#This Row],[Passo]]+Tabla15[[#This Row],[Reciclajes]])/1.1)+Tabla15[[#This Row],[Tickets]] -> 1598.9091 | Q35: 0.09 | R35: =IFERROR(F35/P35,0) -> 0.1041335 | T35: 1848.36 | U35: =Tabla15[[#This Row],[Total Caja]]-Tabla15[[#This Row],[Facturació A/A]] -> -249.45091 | V35: =U35+V34 -> -249.45091 | W35: =Tabla15[[#This Row],[Diferencia]]/Tabla15[[#This Row],[Facturació A/A]] -> -0.13495797 | X35: =Tabla15[[#This Row],[Facturació A/A]]*H$17+Tabla15[[#This Row],[Facturació A/A]] -> 1903.8108 | Y35: =Tabla15[[#This Row],[Total Caja]]-Tabla15[[#This Row],[Previsión]] -> -304.90171 | AA35: =SUM(INDEX(Tabla15[[#This Row],[Facturació A/A]],1):Tabla15[[#This Row],[Facturació A/A]]) / SUM(INDEX(Tabla15[[#This Row],[Diferencia]],1):Tabla15[[#This Row],[Diferencia]]) -> -7.4097144 | AB35: lluvias
C36: 3 | D36: 46025 | E36: 291.35 | F36: =Tabla15[[#This Row],[Retiros]]-Tabla15[[#This Row],[Contado]] -> 98.65 | G36: 1271.95 | H36: 0 | I36: 99.1 | J36: 0 | K36: 0 | L36: 0 | M36: 390 | N36: =Tabla15[[#This Row],[Contado]] -> 291.35 | P36: =((Tabla15[[#This Row],[Contado]]+Tabla15[[#This Row],[Visa]]+Tabla15[[#This Row],[Eventos]]+Tabla15[[#This Row],[Passo]]+Tabla15[[#This Row],[Reciclajes]])/1.1)+Tabla15[[#This Row],[Tickets]] -> 1609.9227 | Q36: 0.23 | R36: =IFERROR(F36/P36,0) -> 0.061276233 | T36: 2277.69 | U36: =Tabla15[[#This Row],[Total Caja]]-Tabla15[[#This Row],[Facturació A/A]] -> -667.76727 | V36: =U36+V35 -> -917.21818 | W36: =Tabla15[[#This Row],[Diferencia]]/Tabla15[[#This Row],[Facturació A/A]] -> -0.29317742 | X36: =Tabla15[[#This Row],[Facturació A/A]]*H$17+Tabla15[[#This Row],[Facturació A/A]] -> 2346.0207 | Y36: =Tabla15[[#This Row],[Total Caja]]-Tabla15[[#This Row],[Previsión]] -> -736.09797 | AA36: =SUM(INDEX(Tabla15[[#This Row],[Facturació A/A]],1):Tabla15[[#This Row],[Facturació A/A]]) / SUM(INDEX(Tabla15[[#This Row],[Diferencia]],1):Tabla15[[#This Row],[Diferencia]]) -> -3.4109039 | AB36: lluvias
C37: 4 | D37: 46026 | E37: 9.75 | F37: =Tabla15[[#This Row],[Retiros]]-Tabla15[[#This Row],[Contado]] -> 80.25 | G37: 940.15 | H37: 0 | I37: 0 | J37: 0 | K37: 0 | L37: 0 | M37: 90 | N37: =Tabla15[[#This Row],[Contado]] -> 9.75 | P37: =((Tabla15[[#This Row],[Contado]]+Tabla15[[#This Row],[Visa]]+Tabla15[[#This Row],[Eventos]]+Tabla15[[#This Row],[Passo]]+Tabla15[[#This Row],[Reciclajes]])/1.1)+Tabla15[[#This Row],[Tickets]] -> 943.79545 | Q37: 0.01 | R37: =IFERROR(F37/P37,0) -> 0.085029017 | T37: 1352.24 | U37: =Tabla15[[#This Row],[Total Caja]]-Tabla15[[#This Row],[Facturació A/A]] -> -408.44455 | V37: =U37+V36 -> -1325.6627 | W37: =Tabla15[[#This Row],[Diferencia]]/Tabla15[[#This Row],[Facturació A/A]] -> -0.30205034 | X37: =Tabla15[[#This Row],[Facturació A/A]]*H$17+Tabla15[[#This Row],[Facturació A/A]] -> 1392.8072 | Y37: =Tabla15[[#This Row],[Total Caja]]-Tabla15[[#This Row],[Previsión]] -> -449.01175 | AA37: =SUM(INDEX(Tabla15[[#This Row],[Facturació A/A]],1):Tabla15[[#This Row],[Facturació A/A]]) / SUM(INDEX(Tabla15[[#This Row],[Diferencia]],1):Tabla15[[#This Row],[Diferencia]]) -> -3.3107065 | AB37: lluvias
C38: 5 | D38: 46027 | E38: 0 | F38: =Tabla15[[#This Row],[Retiros]]-Tabla15[[#This Row],[Contado]] -> 0 | G38: 0 | H38: 0 | I38: 0 | J38: 0 | K38: 0 | L38: 0 | M38: 0 | N38: =Tabla15[[#This Row],[Contado]] -> 0 | P38: =((Tabla15[[#This Row],[Contado]]+Tabla15[[#This Row],[Visa]]+Tabla15[[#This Row],[Eventos]]+Tabla15[[#This Row],[Passo]]+Tabla15[[#This Row],[Reciclajes]])/1.1)+Tabla15[[#This Row],[Tickets]] -> 0 | Q38: 0 | R38: =IFERROR(F38/P38,0) -> 0 | T38: 0 | U38: =Tabla15[[#This Row],[Total Caja]]-Tabla15[[#This Row],[Facturació A/A]] -> 0 | V38: =U38+V37 -> -1325.6627 | W38: =Tabla15[[#This Row],[Diferencia]]/Tabla15[[#This Row],[Facturació A/A]] -> #DIV/0! | X38: =Tabla15[[#This Row],[Facturació A/A]]*H$17+Tabla15[[#This Row],[Facturació A/A]] -> 0 | Y38: =Tabla15[[#This Row],[Total Caja]]-Tabla15[[#This Row],[Previsión]] -> 0 | AA38: =SUM(INDEX(Tabla15[[#This Row],[Facturació A/A]],1):Tabla15[[#This Row],[Facturació A/A]]) / SUM(INDEX(Tabla15[[#This Row],[Diferencia]],1):Tabla15[[#This Row],[Diferencia]]) -> #DIV/0! | AB38: lluvias
C39: 6 | D39: 46028 | E39: 0 | F39: =Tabla15[[#This Row],[Retiros]]-Tabla15[[#This Row],[Contado]] -> 0 | G39: 0 | H39: 0 | I39: 0 | J39: 0 | K39: 0 | L39: 0 | M39: 0 | N39: =Tabla15[[#This Row],[Contado]] -> 0 | P39: =((Tabla15[[#This Row],[Contado]]+Tabla15[[#This Row],[Visa]]+Tabla15[[#This Row],[Eventos]]+Tabla15[[#This Row],[Passo]]+Tabla15[[#This Row],[Reciclajes]])/1.1)+Tabla15[[#This Row],[Tickets]] -> 0 | Q39: 0 | R39: =IFERROR(F39/P39,0) -> 0 | T39: 0 | U39: =Tabla15[[#This Row],[Total Caja]]-Tabla15[[#This Row],[Facturació A/A]] -> 0 | V39: =U39+V38 -> -1325.6627 | W39: =Tabla15[[#This Row],[Diferencia]]/Tabla15[[#This Row],[Facturació A/A]] -> #DIV/0! | X39: =Tabla15[[#This Row],[Facturació A/A]]*H$17+Tabla15[[#This Row],[Facturació A/A]] -> 0 | Y39: =Tabla15[[#This Row],[Total Caja]]-Tabla15[[#This Row],[Previsión]] -> 0 | AA39: =SUM(INDEX(Tabla15[[#This Row],[Facturació A/A]],1):Tabla15[[#This Row],[Facturació A/A]]) / SUM(INDEX(Tabla15[[#This Row],[Diferencia]],1):Tabla15[[#This Row],[Diferencia]]) -> #DIV/0! | AB39: lluvias
C40: 7 | D40: 46029 | E40: 26 | F40: =Tabla15[[#This Row],[Retiros]]-Tabla15[[#This Row],[Contado]] -> 194 | G40: 361.5 | H40: 0 | I40: 39.35 | J40: 0 | K40: 0 | L40: 0 | M40: 220 | N40: =Tabla15[[#This Row],[Contado]] -> 26 | P40: =((Tabla15[[#This Row],[Contado]]+Tabla15[[#This Row],[Visa]]+Tabla15[[#This Row],[Eventos]]+Tabla15[[#This Row],[Passo]]+Tabla15[[#This Row],[Reciclajes]])/1.1)+Tabla15[[#This Row],[Tickets]] -> 582.04545 | Q40: 0.07 | R40: =IFERROR(F40/P40,0) -> 0.3333073 | T40: 322.79 | U40: =Tabla15[[#This Row],[Total Caja]]-Tabla15[[#This Row],[Facturació A/A]] -> 259.25545 | V40: =U40+V39 -> -1066.4073 | W40: =Tabla15[[#This Row],[Diferencia]]/Tabla15[[#This Row],[Facturació A/A]] -> 0.80317065 | X40: =Tabla15[[#This Row],[Facturació A/A]]*H$17+Tabla15[[#This Row],[Facturació A/A]] -> 332.4737 | Y40: =Tabla15[[#This Row],[Total Caja]]-Tabla15[[#This Row],[Previsión]] -> 249.57175 | AA40: =SUM(INDEX(Tabla15[[#This Row],[Facturació A/A]],1):Tabla15[[#This Row],[Facturació A/A]]) / SUM(INDEX(Tabla15[[#This Row],[Diferencia]],1):Tabla15[[#This Row],[Diferencia]]) -> 1.2450654 | AB40: lluvias
C41: 8 | D41: 46030 | E41: 0 | F41: =Tabla15[[#This Row],[Retiros]]-Tabla15[[#This Row],[Contado]] -> 243 | G41: 505.1 | H41: 0 | I41: 0 | J41: 0 | K41: 0 | L41: 0 | M41: 243 | N41: =Tabla15[[#This Row],[Contado]] -> 0 | P41: =((Tabla15[[#This Row],[Contado]]+Tabla15[[#This Row],[Visa]]+Tabla15[[#This Row],[Eventos]]+Tabla15[[#This Row],[Passo]]+Tabla15[[#This Row],[Reciclajes]])/1.1)+Tabla15[[#This Row],[Tickets]] -> 702.18182 | Q41: 0 | R41: =IFERROR(F41/P41,0) -> 0.34606422 | T41: 481.23 | U41: =Tabla15[[#This Row],[Total Caja]]-Tabla15[[#This Row],[Facturació A/A]] -> 220.95182 | V41: =U41+V40 -> -845.45545 | W41: =Tabla15[[#This Row],[Diferencia]]/Tabla15[[#This Row],[Facturació A/A]] -> 0.45913974 | X41: =Tabla15[[#This Row],[Facturació A/A]]*H$17+Tabla15[[#This Row],[Facturació A/A]] -> 495.6669 | Y41: =Tabla15[[#This Row],[Total Caja]]-Tabla15[[#This Row],[Previsión]] -> 206.51492 | AA41: =SUM(INDEX(Tabla15[[#This Row],[Facturació A/A]],1):Tabla15[[#This Row],[Facturació A/A]]) / SUM(INDEX(Tabla15[[#This Row],[Diferencia]],1):Tabla15[[#This Row],[Diferencia]]) -> 2.1779862 | AB41: lluvias
C42: 9 | D42: 46031 | E42: 153.15 | F42: =Tabla15[[#This Row],[Retiros]]-Tabla15[[#This Row],[Contado]] -> 216.85 | G42: 681.7 | H42: 0 | I42: 0 | J42: 0 | K42: 0 | L42: 0 | M42: 370 | N42: =Tabla15[[#This Row],[Contado]] -> 153.15 | P42: =((Tabla15[[#This Row],[Contado]]+Tabla15[[#This Row],[Visa]]+Tabla15[[#This Row],[Eventos]]+Tabla15[[#This Row],[Passo]]+Tabla15[[#This Row],[Reciclajes]])/1.1)+Tabla15[[#This Row],[Tickets]] -> 975.80455 | Q42: 0.22 | R42: =IFERROR(F42/P42,0) -> 0.22222688 | T42: 950.95 | U42: =Tabla15[[#This Row],[Total Caja]]-Tabla15[[#This Row],[Facturació A/A]] -> 24.854545 | V42: =U42+V41 -> -820.60091 | W42: =Tabla15[[#This Row],[Diferencia]]/Tabla15[[#This Row],[Facturació A/A]] -> 0.026136543 | X42: =Tabla15[[#This Row],[Facturació A/A]]*H$17+Tabla15[[#This Row],[Facturació A/A]] -> 979.4785 | Y42: =Tabla15[[#This Row],[Total Caja]]-Tabla15[[#This Row],[Previsión]] -> -3.6739545 | AA42: =SUM(INDEX(Tabla15[[#This Row],[Facturació A/A]],1):Tabla15[[#This Row],[Facturació A/A]]) / SUM(INDEX(Tabla15[[#This Row],[Diferencia]],1):Tabla15[[#This Row],[Diferencia]]) -> 38.260607 | AB42: lluvias
C43: 10 | D43: 46032 | E43: 595.7 | F43: =Tabla15[[#This Row],[Retiros]]-Tabla15[[#This Row],[Contado]] -> 129.3 | G43: 1886.65 | H43: 0 | I43: 50.55 | J43: 0 | K43: 0 | L43: 0 | M43: 725 | N43: =Tabla15[[#This Row],[Contado]] -> 595.7 | P43: =((Tabla15[[#This Row],[Contado]]+Tabla15[[#This Row],[Visa]]+Tabla15[[#This Row],[Eventos]]+Tabla15[[#This Row],[Passo]]+Tabla15[[#This Row],[Reciclajes]])/1.1)+Tabla15[[#This Row],[Tickets]] -> 2431.9364 | Q43: 0.32 | R43: =IFERROR(F43/P43,0) -> 0.05316751 | T43: 1330.08 | U43: =Tabla15[[#This Row],[Total Caja]]-Tabla15[[#This Row],[Facturació A/A]] -> 1101.8564 | V43: =U43+V42 -> 281.25545 | W43: =Tabla15[[#This Row],[Diferencia]]/Tabla15[[#This Row],[Facturació A/A]] -> 0.8284136 | X43: =Tabla15[[#This Row],[Facturació A/A]]*H$17+Tabla15[[#This Row],[Facturació A/A]] -> 1369.9824 | Y43: =Tabla15[[#This Row],[Total Caja]]-Tabla15[[#This Row],[Previsión]] -> 1061.954 | AA43: =SUM(INDEX(Tabla15[[#This Row],[Facturació A/A]],1):Tabla15[[#This Row],[Facturació A/A]]) / SUM(INDEX(Tabla15[[#This Row],[Diferencia]],1):Tabla15[[#This Row],[Diferencia]]) -> 1.2071265 | AB43: lluvias
C44: 11 | D44: 46033 | E44: 217.15 | F44: =Tabla15[[#This Row],[Retiros]]-Tabla15[[#This Row],[Contado]] -> 77.85 | G44: 596 | H44: 0 | I44: 53.25 | J44: 0 | K44: 0 | L44: 0 | M44: 295 | N44: =Tabla15[[#This Row],[Contado]] -> 217.15 | P44: =((Tabla15[[#This Row],[Contado]]+Tabla15[[#This Row],[Visa]]+Tabla15[[#This Row],[Eventos]]+Tabla15[[#This Row],[Passo]]+Tabla15[[#This Row],[Reciclajes]])/1.1)+Tabla15[[#This Row],[Tickets]] -> 865.48636 | Q44: 0.36 | R44: =IFERROR(F44/P44,0) -> 0.089949424 | T44: 1023.71 | U44: =Tabla15[[#This Row],[Total Caja]]-Tabla15[[#This Row],[Facturació A/A]] -> -158.22364 | V44: =U44+V43 -> 123.03182 | W44: =Tabla15[[#This Row],[Diferencia]]/Tabla15[[#This Row],[Facturació A/A]] -> -0.15455904 | X44: =Tabla15[[#This Row],[Facturació A/A]]*H$17+Tabla15[[#This Row],[Facturació A/A]] -> 1054.4213 | Y44: =Tabla15[[#This Row],[Total Caja]]-Tabla15[[#This Row],[Previsión]] -> -188.93494 | AA44: =SUM(INDEX(Tabla15[[#This Row],[Facturació A/A]],1):Tabla15[[#This Row],[Facturació A/A]]) / SUM(INDEX(Tabla15[[#This Row],[Diferencia]],1):Tabla15[[#This Row],[Diferencia]]) -> -6.4700194 | AB44: lluvias
C45: 12 | D45: 46034 | E45: 0 | F45: =Tabla15[[#This Row],[Retiros]]-Tabla15[[#This Row],[Contado]] -> 0 | G45: 0 | H45: 0 | I45: 0 | J45: 0 | K45: 0 | L45: 0 | M45: 0 | N45: =Tabla15[[#This Row],[Contado]] -> 0 | P45: =((Tabla15[[#This Row],[Contado]]+Tabla15[[#This Row],[Visa]]+Tabla15[[#This Row],[Eventos]]+Tabla15[[#This Row],[Passo]]+Tabla15[[#This Row],[Reciclajes]])/1.1)+Tabla15[[#This Row],[Tickets]] -> 0 | Q45: 0 | R45: =IFERROR(F45/P45,0) -> 0 | T45: 0 | U45: =Tabla15[[#This Row],[Total Caja]]-Tabla15[[#This Row],[Facturació A/A]] -> 0 | V45: =U45+V44 -> 123.03182 | W45: =Tabla15[[#This Row],[Diferencia]]/Tabla15[[#This Row],[Facturació A/A]] -> #DIV/0! | X45: =Tabla15[[#This Row],[Facturació A/A]]*H$17+Tabla15[[#This Row],[Facturació A/A]] -> 0 | Y45: =Tabla15[[#This Row],[Total Caja]]-Tabla15[[#This Row],[Previsión]] -> 0 | AA45: =SUM(INDEX(Tabla15[[#This Row],[Facturació A/A]],1):Tabla15[[#This Row],[Facturació A/A]]) / SUM(INDEX(Tabla15[[#This Row],[Diferencia]],1):Tabla15[[#This Row],[Diferencia]]) -> #DIV/0! | AB45: lluvias
C46: 13 | D46: 46035 | E46: 0 | F46: =Tabla15[[#This Row],[Retiros]]-Tabla15[[#This Row],[Contado]] -> 0 | G46: 0 | H46: 0 | I46: 0 | J46: 0 | K46: 0 | L46: 0 | M46: 0 | N46: =Tabla15[[#This Row],[Contado]] -> 0 | P46: =((Tabla15[[#This Row],[Contado]]+Tabla15[[#This Row],[Visa]]+Tabla15[[#This Row],[Eventos]]+Tabla15[[#This Row],[Passo]]+Tabla15[[#This Row],[Reciclajes]])/1.1)+Tabla15[[#This Row],[Tickets]] -> 0 | Q46: 0 | R46: =IFERROR(F46/P46,0) -> 0 | T46: 0 | U46: =Tabla15[[#This Row],[Total Caja]]-Tabla15[[#This Row],[Facturació A/A]] -> 0 | V46: =U46+V45 -> 123.03182 | W46: =Tabla15[[#This Row],[Diferencia]]/Tabla15[[#This Row],[Facturació A/A]] -> #DIV/0! | X46: =Tabla15[[#This Row],[Facturació A/A]]*H$17+Tabla15[[#This Row],[Facturació A/A]] -> 0 | Y46: =Tabla15[[#This Row],[Total Caja]]-Tabla15[[#This Row],[Previsión]] -> 0 | AA46: =SUM(INDEX(Tabla15[[#This Row],[Facturació A/A]],1):Tabla15[[#This Row],[Facturació A/A]]) / SUM(INDEX(Tabla15[[#This Row],[Diferencia]],1):Tabla15[[#This Row],[Diferencia]]) -> #DIV/0! | AB46: lluvias
... C54: 21 | D54: 46043 | E54: 47.7 | F54: =Tabla15[[#This Row],[Retiros]]-Tabla15[[#This Row],[Contado]] -> 183.3 | G54: 225 | H54: 0 | I54: 31.05 | J54: 0 | K54: 0 | L54: 0 | M54: 231 | N54: =Tabla15[[#This Row],[Contado]] -> 47.7 | P54: =((Tabla15[[#This Row],[Contado]]+Tabla15[[#This Row],[Visa]]+Tabla15[[#This Row],[Eventos]]+Tabla15[[#This Row],[Passo]]+Tabla15[[#This Row],[Reciclajes]])/1.1)+Tabla15[[#This Row],[Tickets]] -> 459.43636 | Q54: 0.21 | R54: =IFERROR(F54/P54,0) -> 0.39896711 | T54: 764.26 | U54: =Tabla15[[#This Row],[Total Caja]]-Tabla15[[#This Row],[Facturació A/A]] -> -304.82364 | V54: =U54+V53 -> -1296.0555 | W54: =Tabla15[[#This Row],[Diferencia]]/Tabla15[[#This Row],[Facturació A/A]] -> -0.39884808 | X54: =Tabla15[[#This Row],[Facturació A/A]]*H$17+Tabla15[[#This Row],[Facturació A/A]] -> 787.1878 | Y54: =Tabla15[[#This Row],[Total Caja]]-Tabla15[[#This Row],[Previsión]] -> -327.75144 | AA54: =SUM(INDEX(Tabla15[[#This Row],[Facturació A/A]],1):Tabla15[[#This Row],[Facturació A/A]]) / SUM(INDEX(Tabla15[[#This Row],[Diferencia]],1):Tabla15[[#This Row],[Diferencia]]) -> -2.5072203 | AB54: lluvias
C55: 22 | D55: 46044 | E55: 51.65 | F55: =Tabla15[[#This Row],[Retiros]]-Tabla15[[#This Row],[Contado]] -> 168.35 | G55: 678.4 | H55: 0 | I55: 0 | J55: 0 | K55: 0 | L55: 0 | M55: 220 | N55: =Tabla15[[#This Row],[Contado]] -> 51.65 | P55: =((Tabla15[[#This Row],[Contado]]+Tabla15[[#This Row],[Visa]]+Tabla15[[#This Row],[Eventos]]+Tabla15[[#This Row],[Passo]]+Tabla15[[#This Row],[Reciclajes]])/1.1)+Tabla15[[#This Row],[Tickets]] -> 832.03182 | Q55: 0.08 | R55: =IFERROR(F55/P55,0) -> 0.20233601 | T55: 467.08 | U55: =Tabla15[[#This Row],[Total Caja]]-Tabla15[[#This Row],[Facturació A/A]] -> 364.95182 | V55: =U55+V54 -> -931.10364 | W55: =Tabla15[[#This Row],[Diferencia]]/Tabla15[[#This Row],[Facturació A/A]] -> 0.78134756 | X55: =Tabla15[[#This Row],[Facturació A/A]]*H$17+Tabla15[[#This Row],[Facturació A/A]] -> 481.0924 | Y55: =Tabla15[[#This Row],[Total Caja]]-Tabla15[[#This Row],[Previsión]] -> 350.93942 | AA55: =SUM(INDEX(Tabla15[[#This Row],[Facturació A/A]],1):Tabla15[[#This Row],[Facturació A/A]]) / SUM(INDEX(Tabla15[[#This Row],[Diferencia]],1):Tabla15[[#This Row],[Diferencia]]) -> 1.2798402
C56: 23 | D56: 46045 | E56: 18.9 | F56: =Tabla15[[#This Row],[Retiros]]-Tabla15[[#This Row],[Contado]] -> 216.1 | G56: 1056.85 | H56: 0 | I56: 0 | J56: 0 | K56: 0 | L56: 0 | M56: 235 | N56: =Tabla15[[#This Row],[Contado]] -> 18.9 | P56: =((Tabla15[[#This Row],[Contado]]+Tabla15[[#This Row],[Visa]]+Tabla15[[#This Row],[Eventos]]+Tabla15[[#This Row],[Passo]]+Tabla15[[#This Row],[Reciclajes]])/1.1)+Tabla15[[#This Row],[Tickets]] -> 1194.0545 | Q56: 0.02 | R56: =IFERROR(F56/P56,0) -> 0.18098001 | T56: 1203.5 | U56: =Tabla15[[#This Row],[Total Caja]]-Tabla15[[#This Row],[Facturació A/A]] -> -9.4454545 | V56: =U56+V55 -> -940.54909 | W56: =Tabla15[[#This Row],[Diferencia]]/Tabla15[[#This Row],[Facturació A/A]] -> -0.0078483212 | X56: =Tabla15[[#This Row],[Facturació A/A]]*H$17+Tabla15[[#This Row],[Facturació A/A]] -> 1239.605 | Y56: =Tabla15[[#This Row],[Total Caja]]-Tabla15[[#This Row],[Previsión]] -> -45.550455 | AA56: =SUM(INDEX(Tabla15[[#This Row],[Facturació A/A]],1):Tabla15[[#This Row],[Facturació A/A]]) / SUM(INDEX(Tabla15[[#This Row],[Diferencia]],1):Tabla15[[#This Row],[Diferencia]]) -> -127.41578
C57: 24 | D57: 46046 | E57: 393.15 | F57: =Tabla15[[#This Row],[Retiros]]-Tabla15[[#This Row],[Contado]] -> 86.85 | G57: 1203.05 | H57: 0 | I57: 17.5 | J57: 0 | K57: 0 | L57: 0 | M57: 480 | N57: =Tabla15[[#This Row],[Contado]] -> 393.15 | P57: =((Tabla15[[#This Row],[Contado]]+Tabla15[[#This Row],[Visa]]+Tabla15[[#This Row],[Eventos]]+Tabla15[[#This Row],[Passo]]+Tabla15[[#This Row],[Reciclajes]])/1.1)+Tabla15[[#This Row],[Tickets]] -> 1553.85 | Q57: 0.33 | R57: =IFERROR(F57/P57,0) -> 0.055893426 | T57: 2204.06 | U57: =Tabla15[[#This Row],[Total Caja]]-Tabla15[[#This Row],[Facturació A/A]] -> -650.21 | V57: =U57+V56 -> -1590.7591 | W57: =Tabla15[[#This Row],[Diferencia]]/Tabla15[[#This Row],[Facturació A/A]] -> -0.29500558 | X57: =Tabla15[[#This Row],[Facturació A/A]]*H$17+Tabla15[[#This Row],[Facturació A/A]] -> 2270.1818 | Y57: =Tabla15[[#This Row],[Total Caja]]-Tabla15[[#This Row],[Previsión]] -> -716.3318 | AA57: =SUM(INDEX(Tabla15[[#This Row],[Facturació A/A]],1):Tabla15[[#This Row],[Facturació A/A]]) / SUM(INDEX(Tabla15[[#This Row],[Diferencia]],1):Tabla15[[#This Row],[Diferencia]]) -> -3.3897664
C58: 25 | D58: 46047 | E58: 759.1 | F58: =Tabla15[[#This Row],[Retiros]]-Tabla15[[#This Row],[Contado]] -> 140.9 | G58: 1072.5 | H58: 0 | I58: 23.8 | J58: 0 | K58: 0 | L58: 0 | M58: 900 | N58: =Tabla15[[#This Row],[Contado]] -> 759.1 | P58: =((Tabla15[[#This Row],[Contado]]+Tabla15[[#This Row],[Visa]]+Tabla15[[#This Row],[Eventos]]+Tabla15[[#This Row],[Passo]]+Tabla15[[#This Row],[Reciclajes]])/1.1)+Tabla15[[#This Row],[Tickets]] -> 1827.6273 | Q58: 0.71 | R58: =IFERROR(F58/P58,0) -> 0.077094494 | T58: 1303.8 | U58: =Tabla15[[#This Row],[Total Caja]]-Tabla15[[#This Row],[Facturació A/A]] -> 523.82727 | V58: =U58+V57 -> -1066.9318 | W58: =Tabla15[[#This Row],[Diferencia]]/Tabla15[[#This Row],[Facturació A/A]] -> 0.40176965 | X58: =Tabla15[[#This Row],[Facturació A/A]]*H$17+Tabla15[[#This Row],[Facturació A/A]] -> 1342.914 | Y58: =Tabla15[[#This Row],[Total Caja]]-Tabla15[[#This Row],[Previsión]] -> 484.71327 | AA58: =SUM(INDEX(Tabla15[[#This Row],[Facturació A/A]],1):Tabla15[[#This Row],[Facturació A/A]]) / SUM(INDEX(Tabla15[[#This Row],[Diferencia]],1):Tabla15[[#This Row],[Diferencia]]) -> 2.4889884
C59: 26 | D59: 46048 | E59: 0 | F59: =Tabla15[[#This Row],[Retiros]]-Tabla15[[#This Row],[Contado]] -> 0 | G59: 0 | H59: 0 | I59: 0 | J59: 0 | K59: 0 | L59: 0 | M59: 0 | N59: =Tabla15[[#This Row],[Contado]] -> 0 | P59: =((Tabla15[[#This Row],[Contado]]+Tabla15[[#This Row],[Visa]]+Tabla15[[#This Row],[Eventos]]+Tabla15[[#This Row],[Passo]]+Tabla15[[#This Row],[Reciclajes]])/1.1)+Tabla15[[#This Row],[Tickets]] -> 0 | Q59: 0 | R59: =IFERROR(F59/P59,0) -> 0 | T59: 0 | U59: =Tabla15[[#This Row],[Total Caja]]-Tabla15[[#This Row],[Facturació A/A]] -> 0 | V59: =U59+V58 -> -1066.9318 | W59: =Tabla15[[#This Row],[Diferencia]]/Tabla15[[#This Row],[Facturació A/A]] -> #DIV/0! | X59: =Tabla15[[#This Row],[Facturació A/A]]*H$17+Tabla15[[#This Row],[Facturació A/A]] -> 0 | Y59: =Tabla15[[#This Row],[Total Caja]]-Tabla15[[#This Row],[Previsión]] -> 0 | AA59: =SUM(INDEX(Tabla15[[#This Row],[Facturació A/A]],1):Tabla15[[#This Row],[Facturació A/A]]) / SUM(INDEX(Tabla15[[#This Row],[Diferencia]],1):Tabla15[[#This Row],[Diferencia]]) -> #DIV/0!
C60: 27 | D60: 46049 | E60: 0 | F60: =Tabla15[[#This Row],[Retiros]]-Tabla15[[#This Row],[Contado]] -> 0 | G60: 0 | H60: 0 | I60: 0 | J60: 0 | K60: 0 | L60: 0 | M60: 0 | N60: =Tabla15[[#This Row],[Contado]] -> 0 | P60: =((Tabla15[[#This Row],[Contado]]+Tabla15[[#This Row],[Visa]]+Tabla15[[#This Row],[Eventos]]+Tabla15[[#This Row],[Passo]]+Tabla15[[#This Row],[Reciclajes]])/1.1)+Tabla15[[#This Row],[Tickets]] -> 0 | Q60: 0 | R60: =IFERROR(F60/P60,0) -> 0 | T60: 0 | U60: =Tabla15[[#This Row],[Total Caja]]-Tabla15[[#This Row],[Facturació A/A]] -> 0 | V60: =U60+V59 -> -1066.9318 | W60: =Tabla15[[#This Row],[Diferencia]]/Tabla15[[#This Row],[Facturació A/A]] -> #DIV/0! | X60: =Tabla15[[#This Row],[Facturació A/A]]*H$17+Tabla15[[#This Row],[Facturació A/A]] -> 0 | Y60: =Tabla15[[#This Row],[Total Caja]]-Tabla15[[#This Row],[Previsión]] -> 0 | AA60: =SUM(INDEX(Tabla15[[#This Row],[Facturació A/A]],1):Tabla15[[#This Row],[Facturació A/A]]) / SUM(INDEX(Tabla15[[#This Row],[Diferencia]],1):Tabla15[[#This Row],[Diferencia]]) -> #DIV/0!
C61: 28 | D61: 46050 | E61: 0 | F61: =Tabla15[[#This Row],[Retiros]]-Tabla15[[#This Row],[Contado]] -> 180 | G61: 294.75 | H61: 0 | I61: 54.7 | J61: 0 | K61: 0 | L61: 0 | M61: 180 | N61: =Tabla15[[#This Row],[Contado]] -> 0 | P61: =((Tabla15[[#This Row],[Contado]]+Tabla15[[#This Row],[Visa]]+Tabla15[[#This Row],[Eventos]]+Tabla15[[#This Row],[Passo]]+Tabla15[[#This Row],[Reciclajes]])/1.1)+Tabla15[[#This Row],[Tickets]] -> 497.68182 | Q61: 0 | R61: =IFERROR(F61/P61,0) -> 0.36167687 | T61: 736.25 | U61: =Tabla15[[#This Row],[Total Caja]]-Tabla15[[#This Row],[Facturació A/A]] -> -238.56818 | V61: =U61+V60 -> -1305.5 | W61: =Tabla15[[#This Row],[Diferencia]]/Tabla15[[#This Row],[Facturació A/A]] -> -0.32403149 | X61: =Tabla15[[#This Row],[Facturació A/A]]*H$17+Tabla15[[#This Row],[Facturació A/A]] -> 758.3375 | Y61: =Tabla15[[#This Row],[Total Caja]]-Tabla15[[#This Row],[Previsión]] -> -260.65568 | AA61: =SUM(INDEX(Tabla15[[#This Row],[Facturació A/A]],1):Tabla15[[#This Row],[Facturació A/A]]) / SUM(INDEX(Tabla15[[#This Row],[Diferencia]],1):Tabla15[[#This Row],[Diferencia]]) -> -3.0861198
C62: 29 | D62: 46051 | E62: 7.8 | F62: =Tabla15[[#This Row],[Retiros]]-Tabla15[[#This Row],[Contado]] -> 302.2 | G62: 1058.9 | H62: 0 | I62: 88.6 | J62: 0 | K62: 0 | L62: 0 | M62: 310 | N62: =Tabla15[[#This Row],[Contado]] -> 7.8 | P62: =((Tabla15[[#This Row],[Contado]]+Tabla15[[#This Row],[Visa]]+Tabla15[[#This Row],[Eventos]]+Tabla15[[#This Row],[Passo]]+Tabla15[[#This Row],[Reciclajes]])/1.1)+Tabla15[[#This Row],[Tickets]] -> 1352.4727 | Q62: 0.01 | R62: =IFERROR(F62/P62,0) -> 0.22344258 | T62: 497.56 | U62: =Tabla15[[#This Row],[Total Caja]]-Tabla15[[#This Row],[Facturació A/A]] -> 854.91273 | V62: =U62+V61 -> -450.58727 | W62: =Tabla15[[#This Row],[Diferencia]]/Tabla15[[#This Row],[Facturació A/A]] -> 1.7182103 | X62: =Tabla15[[#This Row],[Facturació A/A]]*H$17+Tabla15[[#This Row],[Facturació A/A]] -> 512.4868 | Y62: =Tabla15[[#This Row],[Total Caja]]-Tabla15[[#This Row],[Previsión]] -> 839.98593 | AA62: =SUM(INDEX(Tabla15[[#This Row],[Facturació A/A]],1):Tabla15[[#This Row],[Facturació A/A]]) / SUM(INDEX(Tabla15[[#This Row],[Diferencia]],1):Tabla15[[#This Row],[Diferencia]]) -> 0.58200093
C63: 30 | D63: 46052 | E63: 295.2 | F63: =Tabla15[[#This Row],[Retiros]]-Tabla15[[#This Row],[Contado]] -> 259.8 | G63: 1525 | H63: 0 | I63: 74.8 | J63: 0 | K63: 0 | L63: 0 | M63: 555 | N63: =Tabla15[[#This Row],[Contado]] -> 295.2 | P63: =((Tabla15[[#This Row],[Contado]]+Tabla15[[#This Row],[Visa]]+Tabla15[[#This Row],[Eventos]]+Tabla15[[#This Row],[Passo]]+Tabla15[[#This Row],[Reciclajes]])/1.1)+Tabla15[[#This Row],[Tickets]] -> 1982.5273 | Q63: 0.19 | R63: =IFERROR(F63/P63,0) -> 0.13104486 | T63: 0 | U63: =Tabla15[[#This Row],[Total Caja]]-Tabla15[[#This Row],[Facturació A/A]] -> 1982.5273 | V63: =U63+V62 -> 1531.94 | W63: =Tabla15[[#This Row],[Diferencia]]/Tabla15[[#This Row],[Facturació A/A]] -> #DIV/0! | X63: =Tabla15[[#This Row],[Facturació A/A]]*H$17+Tabla15[[#This Row],[Facturació A/A]] -> 0 | Y63: =Tabla15[[#This Row],[Total Caja]]-Tabla15[[#This Row],[Previsión]] -> 1982.5273 | AA63: =SUM(INDEX(Tabla15[[#This Row],[Facturació A/A]],1):Tabla15[[#This Row],[Facturació A/A]]) / SUM(INDEX(Tabla15[[#This Row],[Diferencia]],1):Tabla15[[#This Row],[Diferencia]]) -> 0
C64: 31 | D64: 46053 | E64: 549.2 | F64: =Tabla15[[#This Row],[Retiros]]-Tabla15[[#This Row],[Contado]] -> 90.8 | G64: 1476.25 | H64: 0 | I64: 33.15 | J64: 0 | K64: 0 | L64: 0 | M64: 640 | N64: =Tabla15[[#This Row],[Contado]] -> 549.2 | P64: =((Tabla15[[#This Row],[Contado]]+Tabla15[[#This Row],[Visa]]+Tabla15[[#This Row],[Eventos]]+Tabla15[[#This Row],[Passo]]+Tabla15[[#This Row],[Reciclajes]])/1.1)+Tabla15[[#This Row],[Tickets]] -> 1962.2545 | Q64: 0.37 | R64: =IFERROR(F64/P64,0) -> 0.046273303 | T64: 0 | U64: =Tabla15[[#This Row],[Total Caja]]-Tabla15[[#This Row],[Facturació A/A]] -> 1962.2545 | V64: =U64+V63 -> 3494.1945 | W64: =Tabla15[[#This Row],[Diferencia]]/Tabla15[[#This Row],[Facturació A/A]] -> #DIV/0! | X64: =Tabla15[[#This Row],[Facturació A/A]]*H$17+Tabla15[[#This Row],[Facturació A/A]] -> 0 | Y64: =Tabla15[[#This Row],[Total Caja]]-Tabla15[[#This Row],[Previsión]] -> 1962.2545 | AA64: =SUM(INDEX(Tabla15[[#This Row],[Facturació A/A]],1):Tabla15[[#This Row],[Facturació A/A]]) / SUM(INDEX(Tabla15[[#This Row],[Diferencia]],1):Tabla15[[#This Row],[Diferencia]]) -> 0
C65: 32 | D65: 46054 | E65: 296.25 | F65: =Tabla15[[#This Row],[Retiros]]-Tabla15[[#This Row],[Contado]] -> 123.75 | G65: 812.6 | H65: 0 | I65: 49.35 | J65: 0 | K65: 0 | L65: 0 | M65: 420 | N65: =Tabla15[[#This Row],[Contado]] -> 296.25 | P65: =((Tabla15[[#This Row],[Contado]]+Tabla15[[#This Row],[Visa]]+Tabla15[[#This Row],[Eventos]]+Tabla15[[#This Row],[Passo]]+Tabla15[[#This Row],[Reciclajes]])/1.1)+Tabla15[[#This Row],[Tickets]] -> 1176.6591 | Q65: 0.36 | R65: =IFERROR(F65/P65,0) -> 0.10517065 | T65: 0 | U65: =Tabla15[[#This Row],[Total Caja]]-Tabla15[[#This Row],[Facturació A/A]] -> 1176.6591 | V65: =U65+V64 -> 4670.8536 | W65: =Tabla15[[#This Row],[Diferencia]]/Tabla15[[#This Row],[Facturació A/A]] -> #DIV/0! | X65: =Tabla15[[#This Row],[Facturació A/A]]*H$17+Tabla15[[#This Row],[Facturació A/A]] -> 0 | Y65: =Tabla15[[#This Row],[Total Caja]]-Tabla15[[#This Row],[Previsión]] -> 1176.6591 | AA65: =SUM(INDEX(Tabla15[[#This Row],[Facturació A/A]],1):Tabla15[[#This Row],[Facturació A/A]]) / SUM(INDEX(Tabla15[[#This Row],[Diferencia]],1):Tabla15[[#This Row],[Diferencia]]) -> 0
C66: 33 | D66: 46055 | E66: 0 | F66: =Tabla15[[#This Row],[Retiros]]-Tabla15[[#This Row],[Contado]] -> 0 | G66: 0 | H66: 0 | I66: 0 | J66: 0 | K66: 0 | L66: 0 | M66: 0 | N66: =Tabla15[[#This Row],[Contado]] -> 0 | P66: =((Tabla15[[#This Row],[Contado]]+Tabla15[[#This Row],[Visa]]+Tabla15[[#This Row],[Eventos]]+Tabla15[[#This Row],[Passo]]+Tabla15[[#This Row],[Reciclajes]])/1.1)+Tabla15[[#This Row],[Tickets]] -> 0 | Q66: 0 | R66: =IFERROR(F66/P66,0) -> 0 | T66: 0 | U66: =Tabla15[[#This Row],[Total Caja]]-Tabla15[[#This Row],[Facturació A/A]] -> 0 | V66: =U66+V65 -> 4670.8536 | W66: =Tabla15[[#This Row],[Diferencia]]/Tabla15[[#This Row],[Facturació A/A]] -> #DIV/0! | X66: =Tabla15[[#This Row],[Facturació A/A]]*H$17+Tabla15[[#This Row],[Facturació A/A]] -> 0 | Y66: =Tabla15[[#This Row],[Total Caja]]-Tabla15[[#This Row],[Previsión]] -> 0 | AA66: =SUM(INDEX(Tabla15[[#This Row],[Facturació A/A]],1):Tabla15[[#This Row],[Facturació A/A]]) / SUM(INDEX(Tabla15[[#This Row],[Diferencia]],1):Tabla15[[#This Row],[Diferencia]]) -> #DIV/0!
... C70: 37 | D70: 46059 | E70: 214.6 | F70: =Tabla15[[#This Row],[Retiros]]-Tabla15[[#This Row],[Contado]] -> 130.4 | G70: 1646.7 | H70: 0 | I70: 128.4 | J70: 0 | K70: 0 | L70: 0 | M70: 345 | N70: =Tabla15[[#This Row],[Contado]] -> 214.6 | P70: =((Tabla15[[#This Row],[Contado]]+Tabla15[[#This Row],[Visa]]+Tabla15[[#This Row],[Eventos]]+Tabla15[[#This Row],[Passo]]+Tabla15[[#This Row],[Reciclajes]])/1.1)+Tabla15[[#This Row],[Tickets]] -> 1939.2182 | Q70: 0.13 | R70: =IFERROR(F70/P70,0) -> 0.067243594 | T70: 1277.05 | U70: =Tabla15[[#This Row],[Total Caja]]-Tabla15[[#This Row],[Facturació A/A]] -> 662.16818 | V70: =U70+V69 -> 6517.7064 | W70: =Tabla15[[#This Row],[Diferencia]]/Tabla15[[#This Row],[Facturació A/A]] -> 0.5185139 | X70: =Tabla15[[#This Row],[Facturació A/A]]*H$17+Tabla15[[#This Row],[Facturació A/A]] -> 1315.3615 | Y70: =Tabla15[[#This Row],[Total Caja]]-Tabla15[[#This Row],[Previsión]] -> 623.85668 | AA70: =SUM(INDEX(Tabla15[[#This Row],[Facturació A/A]],1):Tabla15[[#This Row],[Facturació A/A]]) / SUM(INDEX(Tabla15[[#This Row],[Diferencia]],1):Tabla15[[#This Row],[Diferencia]]) -> 1.9285886
C71: 38 | D71: 46060 | E71: 1516 | F71: =Tabla15[[#This Row],[Retiros]]-Tabla15[[#This Row],[Contado]] -> 44 | G71: 2237.7 | H71: 480.4 | I71: 98.8 | J71: 0 | K71: 0 | L71: 0 | M71: 1560 | N71: =Tabla15[[#This Row],[Contado]] -> 1516 | P71: =((Tabla15[[#This Row],[Contado]]+Tabla15[[#This Row],[Visa]]+Tabla15[[#This Row],[Eventos]]+Tabla15[[#This Row],[Passo]]+Tabla15[[#This Row],[Reciclajes]])/1.1)+Tabla15[[#This Row],[Tickets]] -> 3983 | Q71: 0.68 | R71: =IFERROR(F71/P71,0) -> 0.01104695 | T71: 1724.43 | U71: =Tabla15[[#This Row],[Total Caja]]-Tabla15[[#This Row],[Facturació A/A]] -> 2258.57 | V71: =U71+V70 -> 8776.2764 | W71: =Tabla15[[#This Row],[Diferencia]]/Tabla15[[#This Row],[Facturació A/A]] -> 1.3097487 | X71: =Tabla15[[#This Row],[Facturació A/A]]*H$17+Tabla15[[#This Row],[Facturació A/A]] -> 1776.1629 | Y71: =Tabla15[[#This Row],[Total Caja]]-Tabla15[[#This Row],[Previsión]] -> 2206.8371 | AA71: =SUM(INDEX(Tabla15[[#This Row],[Facturació A/A]],1):Tabla15[[#This Row],[Facturació A/A]]) / SUM(INDEX(Tabla15[[#This Row],[Diferencia]],1):Tabla15[[#This Row],[Diferencia]]) -> 0.76350523 | AB71: equipo de futbol 18 pax
C72: 39 | D72: 46061 | E72: 369.05 | F72: =Tabla15[[#This Row],[Retiros]]-Tabla15[[#This Row],[Contado]] -> 130.95 | G72: 1754.75 | H72: 0 | I72: 23.55 | J72: 0 | K72: 0 | L72: 0 | M72: 500 | N72: =Tabla15[[#This Row],[Contado]] -> 369.05 | P72: =((Tabla15[[#This Row],[Contado]]+Tabla15[[#This Row],[Visa]]+Tabla15[[#This Row],[Eventos]]+Tabla15[[#This Row],[Passo]]+Tabla15[[#This Row],[Reciclajes]])/1.1)+Tabla15[[#This Row],[Tickets]] -> 2083.0864 | Q72: 0.21 | R72: =IFERROR(F72/P72,0) -> 0.062863452 | T72: 1547.4 | U72: =Tabla15[[#This Row],[Total Caja]]-Tabla15[[#This Row],[Facturació A/A]] -> 535.68636 | V72: =U72+V71 -> 9311.9627 | W72: =Tabla15[[#This Row],[Diferencia]]/Tabla15[[#This Row],[Facturació A/A]] -> 0.3461848 | X72: =Tabla15[[#This Row],[Facturació A/A]]*H$17+Tabla15[[#This Row],[Facturació A/A]] -> 1593.822 | Y72: =Tabla15[[#This Row],[Total Caja]]-Tabla15[[#This Row],[Previsión]] -> 489.26436 | AA72: =SUM(INDEX(Tabla15[[#This Row],[Facturació A/A]],1):Tabla15[[#This Row],[Facturació A/A]]) / SUM(INDEX(Tabla15[[#This Row],[Diferencia]],1):Tabla15[[#This Row],[Diferencia]]) -> 2.8886306
C73: 40 | D73: 46062 | E73: 0 | F73: =Tabla15[[#This Row],[Retiros]]-Tabla15[[#This Row],[Contado]] -> 0 | G73: 0 | H73: 0 | I73: 0 | J73: 0 | K73: 0 | L73: 0 | M73: 0 | N73: =Tabla15[[#This Row],[Contado]] -> 0 | P73: =((Tabla15[[#This Row],[Contado]]+Tabla15[[#This Row],[Visa]]+Tabla15[[#This Row],[Eventos]]+Tabla15[[#This Row],[Passo]]+Tabla15[[#This Row],[Reciclajes]])/1.1)+Tabla15[[#This Row],[Tickets]] -> 0 | Q73: 0 | R73: =IFERROR(F73/P73,0) -> 0 | T73: 0 | U73: =Tabla15[[#This Row],[Total Caja]]-Tabla15[[#This Row],[Facturació A/A]] -> 0 | V73: =U73+V72 -> 9311.9627 | W73: =Tabla15[[#This Row],[Diferencia]]/Tabla15[[#This Row],[Facturació A/A]] -> #DIV/0! | X73: =Tabla15[[#This Row],[Facturació A/A]]*H$17+Tabla15[[#This Row],[Facturació A/A]] -> 0 | Y73: =Tabla15[[#This Row],[Total Caja]]-Tabla15[[#This Row],[Previsión]] -> 0 | AA73: =SUM(INDEX(Tabla15[[#This Row],[Facturació A/A]],1):Tabla15[[#This Row],[Facturació A/A]]) / SUM(INDEX(Tabla15[[#This Row],[Diferencia]],1):Tabla15[[#This Row],[Diferencia]]) -> #DIV/0! | AB73: Visi 20 Pax
C74: 41 | D74: 46063 | E74: 0 | F74: =Tabla15[[#This Row],[Retiros]]-Tabla15[[#This Row],[Contado]] -> 0 | G74: 0 | H74: 0 | I74: 0 | J74: 0 | K74: 0 | L74: 0 | M74: 0 | N74: =Tabla15[[#This Row],[Contado]] -> 0 | P74: =((Tabla15[[#This Row],[Contado]]+Tabla15[[#This Row],[Visa]]+Tabla15[[#This Row],[Eventos]]+Tabla15[[#This Row],[Passo]]+Tabla15[[#This Row],[Reciclajes]])/1.1)+Tabla15[[#This Row],[Tickets]] -> 0 | Q74: 0 | R74: =IFERROR(F74/P74,0) -> 0 | T74: 0 | U74: =Tabla15[[#This Row],[Total Caja]]-Tabla15[[#This Row],[Facturació A/A]] -> 0 | V74: =U74+V73 -> 9311.9627 | W74: =Tabla15[[#This Row],[Diferencia]]/Tabla15[[#This Row],[Facturació A/A]] -> #DIV/0! | X74: =Tabla15[[#This Row],[Facturació A/A]]*H$17+Tabla15[[#This Row],[Facturació A/A]] -> 0 | Y74: =Tabla15[[#This Row],[Total Caja]]-Tabla15[[#This Row],[Previsión]] -> 0 | AA74: =SUM(INDEX(Tabla15[[#This Row],[Facturació A/A]],1):Tabla15[[#This Row],[Facturació A/A]]) / SUM(INDEX(Tabla15[[#This Row],[Diferencia]],1):Tabla15[[#This Row],[Diferencia]]) -> #DIV/0! | AB74: Alerta de viento
C75: 42 | D75: 46064 | E75: 7.6 | F75: =Tabla15[[#This Row],[Retiros]]-Tabla15[[#This Row],[Contado]] -> 112.4 | G75: 671.8 | H75: 382.25 | I75: 0 | J75: 0 | K75: 0 | L75: 0 | M75: 120 | N75: =Tabla15[[#This Row],[Contado]] -> 7.6 | P75: =((Tabla15[[#This Row],[Contado]]+Tabla15[[#This Row],[Visa]]+Tabla15[[#This Row],[Eventos]]+Tabla15[[#This Row],[Passo]]+Tabla15[[#This Row],[Reciclajes]])/1.1)+Tabla15[[#This Row],[Tickets]] -> 1077.5364 | Q75: 0.01 | R75: =IFERROR(F75/P75,0) -> 0.10431202 | T75: 364.05 | U75: =Tabla15[[#This Row],[Total Caja]]-Tabla15[[#This Row],[Facturació A/A]] -> 713.48636 | V75: =U75+V74 -> 10025.449 | W75: =Tabla15[[#This Row],[Diferencia]]/Tabla15[[#This Row],[Facturació A/A]] -> 1.9598582 | X75: =Tabla15[[#This Row],[Facturació A/A]]*H$17+Tabla15[[#This Row],[Facturació A/A]] -> 374.9715 | Y75: =Tabla15[[#This Row],[Total Caja]]-Tabla15[[#This Row],[Previsión]] -> 702.56486 | AA75: =SUM(INDEX(Tabla15[[#This Row],[Facturació A/A]],1):Tabla15[[#This Row],[Facturació A/A]]) / SUM(INDEX(Tabla15[[#This Row],[Diferencia]],1):Tabla15[[#This Row],[Diferencia]]) -> 0.51024101
C76: 43 | D76: 46065 | E76: 0 | F76: =Tabla15[[#This Row],[Retiros]]-Tabla15[[#This Row],[Contado]] -> 185 | G76: 435.25 | H76: 0 | I76: 71.8 | J76: 0 | K76: 0 | L76: 0 | M76: 185 | N76: =Tabla15[[#This Row],[Contado]] -> 0 | P76: =((Tabla15[[#This Row],[Contado]]+Tabla15[[#This Row],[Visa]]+Tabla15[[#This Row],[Eventos]]+Tabla15[[#This Row],[Passo]]+Tabla15[[#This Row],[Reciclajes]])/1.1)+Tabla15[[#This Row],[Tickets]] -> 645.95455 | Q76: 0 | R76: =IFERROR(F76/P76,0) -> 0.28639786 | T76: 670.12 | U76: =Tabla15[[#This Row],[Total Caja]]-Tabla15[[#This Row],[Facturació A/A]] -> -24.165455 | V76: =U76+V75 -> 10001.284 | W76: =Tabla15[[#This Row],[Diferencia]]/Tabla15[[#This Row],[Facturació A/A]] -> -0.036061384 | X76: =Tabla15[[#This Row],[Facturació A/A]]*H$17+Tabla15[[#This Row],[Facturació A/A]] -> 690.2236 | Y76: =Tabla15[[#This Row],[Total Caja]]-Tabla15[[#This Row],[Previsión]] -> -44.269055 | AA76: =SUM(INDEX(Tabla15[[#This Row],[Facturació A/A]],1):Tabla15[[#This Row],[Facturació A/A]]) / SUM(INDEX(Tabla15[[#This Row],[Diferencia]],1):Tabla15[[#This Row],[Diferencia]]) -> -27.730494
C77: 44 | D77: 46066 | E77: 46.25 | F77: =Tabla15[[#This Row],[Retiros]]-Tabla15[[#This Row],[Contado]] -> 168.75 | G77: 920.25 | H77: 0 | I77: 75 | J77: 0 | K77: 0 | L77: 0 | M77: 215 | N77: =Tabla15[[#This Row],[Contado]] -> 46.25 | P77: =((Tabla15[[#This Row],[Contado]]+Tabla15[[#This Row],[Visa]]+Tabla15[[#This Row],[Eventos]]+Tabla15[[#This Row],[Passo]]+Tabla15[[#This Row],[Reciclajes]])/1.1)+Tabla15[[#This Row],[Tickets]] -> 1115.5682 | Q77: 0.05 | R77: =IFERROR(F77/P77,0) -> 0.15126821 | T77: 2482.1 | U77: =Tabla15[[#This Row],[Total Caja]]-Tabla15[[#This Row],[Facturació A/A]] -> -1366.5318 | V77: =U77+V76 -> 8634.7518 | W77: =Tabla15[[#This Row],[Diferencia]]/Tabla15[[#This Row],[Facturació A/A]] -> -0.5505547 | X77: =Tabla15[[#This Row],[Facturació A/A]]*H$17+Tabla15[[#This Row],[Facturació A/A]] -> 2556.563 | Y77: =Tabla15[[#This Row],[Total Caja]]-Tabla15[[#This Row],[Previsión]] -> -1440.9948 | AA77: =SUM(INDEX(Tabla15[[#This Row],[Facturació A/A]],1):Tabla15[[#This Row],[Facturació A/A]]) / SUM(INDEX(Tabla15[[#This Row],[Diferencia]],1):Tabla15[[#This Row],[Diferencia]]) -> -1.81635
C78: 45 | D78: 46067 | E78: 624.1 | F78: =Tabla15[[#This Row],[Retiros]]-Tabla15[[#This Row],[Contado]] -> 545.9 | G78: 2585.4 | H78: 0 | I78: 87.55 | J78: 0 | K78: 0 | L78: 0 | M78: 1170 | N78: =Tabla15[[#This Row],[Contado]] -> 624.1 | P78: =((Tabla15[[#This Row],[Contado]]+Tabla15[[#This Row],[Visa]]+Tabla15[[#This Row],[Eventos]]+Tabla15[[#This Row],[Passo]]+Tabla15[[#This Row],[Reciclajes]])/1.1)+Tabla15[[#This Row],[Tickets]] -> 3543.2182 | Q78: 0.24 | R78: =IFERROR(F78/P78,0) -> 0.15406898 | T78: 2505.28 | U78: =Tabla15[[#This Row],[Total Caja]]-Tabla15[[#This Row],[Facturació A/A]] -> 1037.9382 | V78: =U78+V77 -> 9672.69 | W78: =Tabla15[[#This Row],[Diferencia]]/Tabla15[[#This Row],[Facturació A/A]] -> 0.41430027 | X78: =Tabla15[[#This Row],[Facturació A/A]]*H$17+Tabla15[[#This Row],[Facturació A/A]] -> 2580.4384 | Y78: =Tabla15[[#This Row],[Total Caja]]-Tabla15[[#This Row],[Previsión]] -> 962.77978 | AA78: =SUM(INDEX(Tabla15[[#This Row],[Facturació A/A]],1):Tabla15[[#This Row],[Facturació A/A]]) / SUM(INDEX(Tabla15[[#This Row],[Diferencia]],1):Tabla15[[#This Row],[Diferencia]]) -> 2.4137083 | AB78: Enamorados + Carnaval
C79: 46 | D79: 46068 | E79: 51.55 | F79: =Tabla15[[#This Row],[Retiros]]-Tabla15[[#This Row],[Contado]] -> 298.45 | G79: 1272.1 | H79: 0 | I79: 34.85 | J79: 0 | K79: 0 | L79: 0 | M79: 350 | N79: =Tabla15[[#This Row],[Contado]] -> 51.55 | P79: =((Tabla15[[#This Row],[Contado]]+Tabla15[[#This Row],[Visa]]+Tabla15[[#This Row],[Eventos]]+Tabla15[[#This Row],[Passo]]+Tabla15[[#This Row],[Reciclajes]])/1.1)+Tabla15[[#This Row],[Tickets]] -> 1533.45 | Q79: 0.04 | R79: =IFERROR(F79/P79,0) -> 0.1946265 | T79: 1318.1 | U79: =Tabla15[[#This Row],[Total Caja]]-Tabla15[[#This Row],[Facturació A/A]] -> 215.35 | V79: =U79+V78 -> 9888.04 | W79: =Tabla15[[#This Row],[Diferencia]]/Tabla15[[#This Row],[Facturació A/A]] -> 0.16337911 | X79: =Tabla15[[#This Row],[Facturació A/A]]*H$17+Tabla15[[#This Row],[Facturació A/A]] -> 1357.643 | Y79: =Tabla15[[#This Row],[Total Caja]]-Tabla15[[#This Row],[Previsión]] -> 175.807 | AA79: =SUM(INDEX(Tabla15[[#This Row],[Facturació A/A]],1):Tabla15[[#This Row],[Facturació A/A]]) / SUM(INDEX(Tabla15[[#This Row],[Diferencia]],1):Tabla15[[#This Row],[Diferencia]]) -> 6.1207337
C80: 47 | D80: 46069 | E80: 0 | F80: =Tabla15[[#This Row],[Retiros]]-Tabla15[[#This Row],[Contado]] -> 0 | G80: 0 | H80: 0 | I80: 0 | J80: 0 | K80: 0 | L80: 0 | M80: 0 | N80: =Tabla15[[#This Row],[Contado]] -> 0 | P80: =((Tabla15[[#This Row],[Contado]]+Tabla15[[#This Row],[Visa]]+Tabla15[[#This Row],[Eventos]]+Tabla15[[#This Row],[Passo]]+Tabla15[[#This Row],[Reciclajes]])/1.1)+Tabla15[[#This Row],[Tickets]] -> 0 | Q80: 0 | R80: =IFERROR(F80/P80,0) -> 0 | T80: 0 | U80: =Tabla15[[#This Row],[Total Caja]]-Tabla15[[#This Row],[Facturació A/A]] -> 0 | V80: =U80+V79 -> 9888.04 | W80: =Tabla15[[#This Row],[Diferencia]]/Tabla15[[#This Row],[Facturació A/A]] -> #DIV/0! | X80: =Tabla15[[#This Row],[Facturació A/A]]*H$17+Tabla15[[#This Row],[Facturació A/A]] -> 0 | Y80: =Tabla15[[#This Row],[Total Caja]]-Tabla15[[#This Row],[Previsión]] -> 0 | AA80: =SUM(INDEX(Tabla15[[#This Row],[Facturació A/A]],1):Tabla15[[#This Row],[Facturació A/A]]) / SUM(INDEX(Tabla15[[#This Row],[Diferencia]],1):Tabla15[[#This Row],[Diferencia]]) -> #DIV/0!
C81: 48 | D81: 46070 | E81: 0 | F81: =Tabla15[[#This Row],[Retiros]]-Tabla15[[#This Row],[Contado]] -> 0 | G81: 0 | H81: 0 | I81: 0 | J81: 0 | K81: 0 | L81: 0 | M81: 0 | N81: =Tabla15[[#This Row],[Contado]] -> 0 | P81: =((Tabla15[[#This Row],[Contado]]+Tabla15[[#This Row],[Visa]]+Tabla15[[#This Row],[Eventos]]+Tabla15[[#This Row],[Passo]]+Tabla15[[#This Row],[Reciclajes]])/1.1)+Tabla15[[#This Row],[Tickets]] -> 0 | Q81: 0 | R81: =IFERROR(F81/P81,0) -> 0 | T81: 0 | U81: =Tabla15[[#This Row],[Total Caja]]-Tabla15[[#This Row],[Facturació A/A]] -> 0 | V81: =U81+V80 -> 9888.04 | W81: =Tabla15[[#This Row],[Diferencia]]/Tabla15[[#This Row],[Facturació A/A]] -> #DIV/0! | X81: =Tabla15[[#This Row],[Facturació A/A]]*H$17+Tabla15[[#This Row],[Facturació A/A]] -> 0 | Y81: =Tabla15[[#This Row],[Total Caja]]-Tabla15[[#This Row],[Previsión]] -> 0 | AA81: =SUM(INDEX(Tabla15[[#This Row],[Facturació A/A]],1):Tabla15[[#This Row],[Facturació A/A]]) / SUM(INDEX(Tabla15[[#This Row],[Diferencia]],1):Tabla15[[#This Row],[Diferencia]]) -> #DIV/0!
C82: 49 | D82: 46071 | E82: 108.15 | F82: =Tabla15[[#This Row],[Retiros]]-Tabla15[[#This Row],[Contado]] -> 321.85 | G82: 423.4 | H82: 0 | I82: 0 | J82: 0 | K82: 0 | L82: 0 | M82: 430 | N82: =Tabla15[[#This Row],[Contado]] -> 108.15 | P82: =((Tabla15[[#This Row],[Contado]]+Tabla15[[#This Row],[Visa]]+Tabla15[[#This Row],[Eventos]]+Tabla15[[#This Row],[Passo]]+Tabla15[[#This Row],[Reciclajes]])/1.1)+Tabla15[[#This Row],[Tickets]] -> 805.07727 | Q82: 0.26 | R82: =IFERROR(F82/P82,0) -> 0.39977529 | T82: 698.82 | U82: =Tabla15[[#This Row],[Total Caja]]-Tabla15[[#This Row],[Facturació A/A]] -> 106.25727 | V82: =U82+V81 -> 9994.2973 | W82: =Tabla15[[#This Row],[Diferencia]]/Tabla15[[#This Row],[Facturació A/A]] -> 0.15205242 | X82: =Tabla15[[#This Row],[Facturació A/A]]*H$17+Tabla15[[#This Row],[Facturació A/A]] -> 719.7846 | Y82: =Tabla15[[#This Row],[Total Caja]]-Tabla15[[#This Row],[Previsión]] -> 85.292673 | AA82: =SUM(INDEX(Tabla15[[#This Row],[Facturació A/A]],1):Tabla15[[#This Row],[Facturació A/A]]) / SUM(INDEX(Tabla15[[#This Row],[Diferencia]],1):Tabla15[[#This Row],[Diferencia]]) -> 6.5766792
C83: 50 | D83: 46072 | E83: 0 | F83: =Tabla15[[#This Row],[Retiros]]-Tabla15[[#This Row],[Contado]] -> 275 | G83: 564.3 | H83: 0 | I83: 24.4 | J83: 0 | K83: 0 | L83: 0 | M83: 275 | N83: =Tabla15[[#This Row],[Contado]] -> 0 | P83: =((Tabla15[[#This Row],[Contado]]+Tabla15[[#This Row],[Visa]]+Tabla15[[#This Row],[Eventos]]+Tabla15[[#This Row],[Passo]]+Tabla15[[#This Row],[Reciclajes]])/1.1)+Tabla15[[#This Row],[Tickets]] -> 810.18182 | Q83: 0 | R83: =IFERROR(F83/P83,0) -> 0.33942998 | T83: 840.5 | U83: =Tabla15[[#This Row],[Total Caja]]-Tabla15[[#This Row],[Facturació A/A]] -> -30.318182 | V83: =U83+V82 -> 9963.9791 | W83: =Tabla15[[#This Row],[Diferencia]]/Tabla15[[#This Row],[Facturació A/A]] -> -0.036071602 | X83: =Tabla15[[#This Row],[Facturació A/A]]*H$17+Tabla15[[#This Row],[Facturació A/A]] -> 865.715 | Y83: =Tabla15[[#This Row],[Total Caja]]-Tabla15[[#This Row],[Previsión]] -> -55.533182 | AA83: =SUM(INDEX(Tabla15[[#This Row],[Facturació A/A]],1):Tabla15[[#This Row],[Facturació A/A]]) / SUM(INDEX(Tabla15[[#This Row],[Diferencia]],1):Tabla15[[#This Row],[Diferencia]]) -> -27.722639
C84: 51 | D84: 46073 | E84: 24.23 | F84: =Tabla15[[#This Row],[Retiros]]-Tabla15[[#This Row],[Contado]] -> 245.77 | G84: 1020.72 | H84: 0 | I84: 18.6 | J84: 0 | K84: 0 | L84: 0 | M84: 270 | N84: =Tabla15[[#This Row],[Contado]] -> 24.23 | P84: =((Tabla15[[#This Row],[Contado]]+Tabla15[[#This Row],[Visa]]+Tabla15[[#This Row],[Eventos]]+Tabla15[[#This Row],[Passo]]+Tabla15[[#This Row],[Reciclajes]])/1.1)+Tabla15[[#This Row],[Tickets]] -> 1212.6336 | Q84: 0.02 | R84: =IFERROR(F84/P84,0) -> 0.20267457 | T84: 1312.43 | U84: =Tabla15[[#This Row],[Total Caja]]-Tabla15[[#This Row],[Facturació A/A]] -> -99.796364 | V84: =U84+V83 -> 9864.1827 | W84: =Tabla15[[#This Row],[Diferencia]]/Tabla15[[#This Row],[Facturació A/A]] -> -0.07603938 | X84: =Tabla15[[#This Row],[Facturació A/A]]*H$17+Tabla15[[#This Row],[Facturació A/A]] -> 1351.8029 | Y84: =Tabla15[[#This Row],[Total Caja]]-Tabla15[[#This Row],[Previsión]] -> -139.16926 | AA84: =SUM(INDEX(Tabla15[[#This Row],[Facturació A/A]],1):Tabla15[[#This Row],[Facturació A/A]]) / SUM(INDEX(Tabla15[[#This Row],[Diferencia]],1):Tabla15[[#This Row],[Diferencia]]) -> -13.15108
C85: 52 | D85: 46074 | E85: 0 | F85: =Tabla15[[#This Row],[Retiros]]-Tabla15[[#This Row],[Contado]] -> 670 | G85: 2604.67 | H85: 0 | I85: 76.3 | J85: 0 | K85: 0 | L85: 0 | M85: 670 | N85: =Tabla15[[#This Row],[Contado]] -> 0 | P85: =((Tabla15[[#This Row],[Contado]]+Tabla15[[#This Row],[Visa]]+Tabla15[[#This Row],[Eventos]]+Tabla15[[#This Row],[Passo]]+Tabla15[[#This Row],[Reciclajes]])/1.1)+Tabla15[[#This Row],[Tickets]] -> 3107.2455 | Q85: 0 | R85: =IFERROR(F85/P85,0) -> 0.21562506 | T85: 2481.46 | U85: =Tabla15[[#This Row],[Total Caja]]-Tabla15[[#This Row],[Facturació A/A]] -> 625.78545 | V85: =U85+V84 -> 10489.968 | W85: =Tabla15[[#This Row],[Diferencia]]/Tabla15[[#This Row],[Facturació A/A]] -> 0.25218438 | X85: =Tabla15[[#This Row],[Facturació A/A]]*H$17+Tabla15[[#This Row],[Facturació A/A]] -> 2555.9038 | Y85: =Tabla15[[#This Row],[Total Caja]]-Tabla15[[#This Row],[Previsión]] -> 551.34165 | AA85: =SUM(INDEX(Tabla15[[#This Row],[Facturació A/A]],1):Tabla15[[#This Row],[Facturació A/A]]) / SUM(INDEX(Tabla15[[#This Row],[Diferencia]],1):Tabla15[[#This Row],[Diferencia]]) -> 3.9653526
C86: 53 | D86: 46075 | E86: 103.05 | F86: =Tabla15[[#This Row],[Retiros]]-Tabla15[[#This Row],[Contado]] -> 706.95 | G86: 1477.6 | H86: 0 | I86: 30.5 | J86: 0 | K86: 0 | L86: 0 | M86: 810 | N86: =Tabla15[[#This Row],[Contado]] -> 103.05 | P86: =((Tabla15[[#This Row],[Contado]]+Tabla15[[#This Row],[Visa]]+Tabla15[[#This Row],[Eventos]]+Tabla15[[#This Row],[Passo]]+Tabla15[[#This Row],[Reciclajes]])/1.1)+Tabla15[[#This Row],[Tickets]] -> 2171.6318 | Q86: 0.07 | R86: =IFERROR(F86/P86,0) -> 0.32553861 | T86: 1606.82 | U86: =Tabla15[[#This Row],[Total Caja]]-Tabla15[[#This Row],[Facturació A/A]] -> 564.81182 | V86: =U86+V85 -> 11054.78 | W86: =Tabla15[[#This Row],[Diferencia]]/Tabla15[[#This Row],[Facturació A/A]] -> 0.35150908 | X86: =Tabla15[[#This Row],[Facturació A/A]]*H$17+Tabla15[[#This Row],[Facturació A/A]] -> 1655.0246 | Y86: =Tabla15[[#This Row],[Total Caja]]-Tabla15[[#This Row],[Previsión]] -> 516.60722 | AA86: =SUM(INDEX(Tabla15[[#This Row],[Facturació A/A]],1):Tabla15[[#This Row],[Facturació A/A]]) / SUM(INDEX(Tabla15[[#This Row],[Diferencia]],1):Tabla15[[#This Row],[Diferencia]]) -> 2.8448767
C87: 54 | D87: 46076 | E87: 0 | F87: =Tabla15[[#This Row],[Retiros]]-Tabla15[[#This Row],[Contado]] -> 0 | G87: 0 | H87: 0 | I87: 0 | J87: 0 | K87: 0 | L87: 0 | M87: 0 | N87: =Tabla15[[#This Row],[Contado]] -> 0 | P87: =((Tabla15[[#This Row],[Contado]]+Tabla15[[#This Row],[Visa]]+Tabla15[[#This Row],[Eventos]]+Tabla15[[#This Row],[Passo]]+Tabla15[[#This Row],[Reciclajes]])/1.1)+Tabla15[[#This Row],[Tickets]] -> 0 | Q87: 0 | R87: =IFERROR(F87/P87,0) -> 0 | T87: 0 | U87: =Tabla15[[#This Row],[Total Caja]]-Tabla15[[#This Row],[Facturació A/A]] -> 0 | V87: =U87+V86 -> 11054.78 | W87: =Tabla15[[#This Row],[Diferencia]]/Tabla15[[#This Row],[Facturació A/A]] -> #DIV/0! | X87: =Tabla15[[#This Row],[Facturació A/A]]*H$17+Tabla15[[#This Row],[Facturació A/A]] -> 0 | Y87: =Tabla15[[#This Row],[Total Caja]]-Tabla15[[#This Row],[Previsión]] -> 0 | AA87: =SUM(INDEX(Tabla15[[#This Row],[Facturació A/A]],1):Tabla15[[#This Row],[Facturació A/A]]) / SUM(INDEX(Tabla15[[#This Row],[Diferencia]],1):Tabla15[[#This Row],[Diferencia]]) -> #DIV/0!
C88: 55 | D88: 46077 | E88: 0 | F88: =Tabla15[[#This Row],[Retiros]]-Tabla15[[#This Row],[Contado]] -> 0 | G88: 0 | H88: 0 | I88: 0 | J88: 0 | K88: 0 | L88: 0 | M88: 0 | N88: =Tabla15[[#This Row],[Contado]] -> 0 | P88: =((Tabla15[[#This Row],[Contado]]+Tabla15[[#This Row],[Visa]]+Tabla15[[#This Row],[Eventos]]+Tabla15[[#This Row],[Passo]]+Tabla15[[#This Row],[Reciclajes]])/1.1)+Tabla15[[#This Row],[Tickets]] -> 0 | Q88: 0 | R88: =IFERROR(F88/P88,0) -> 0 | T88: 0 | U88: =Tabla15[[#This Row],[Total Caja]]-Tabla15[[#This Row],[Facturació A/A]] -> 0 | V88: =U88+V87 -> 11054.78 | W88: =Tabla15[[#This Row],[Diferencia]]/Tabla15[[#This Row],[Facturació A/A]] -> #DIV/0! | X88: =Tabla15[[#This Row],[Facturació A/A]]*H$17+Tabla15[[#This Row],[Facturació A/A]] -> 0 | Y88: =Tabla15[[#This Row],[Total Caja]]-Tabla15[[#This Row],[Previsión]] -> 0 | AA88: =SUM(INDEX(Tabla15[[#This Row],[Facturació A/A]],1):Tabla15[[#This Row],[Facturació A/A]]) / SUM(INDEX(Tabla15[[#This Row],[Diferencia]],1):Tabla15[[#This Row],[Diferencia]]) -> #DIV/0!
C89: 56 | D89: 46078 | E89: 0 | F89: =Tabla15[[#This Row],[Retiros]]-Tabla15[[#This Row],[Contado]] -> 0 | G89: 0 | H89: 0 | I89: 0 | J89: 0 | K89: 0 | L89: 0 | M89: 0 | N89: =Tabla15[[#This Row],[Contado]] -> 0 | P89: =((Tabla15[[#This Row],[Contado]]+Tabla15[[#This Row],[Visa]]+Tabla15[[#This Row],[Eventos]]+Tabla15[[#This Row],[Passo]]+Tabla15[[#This Row],[Reciclajes]])/1.1)+Tabla15[[#This Row],[Tickets]] -> 0 | Q89: 0 | R89: =IFERROR(F89/P89,0) -> 0 | T89: 708.73 | U89: =Tabla15[[#This Row],[Total Caja]]-Tabla15[[#This Row],[Facturació A/A]] -> -708.73 | V89: =U89+V88 -> 10346.05 | W89: =Tabla15[[#This Row],[Diferencia]]/Tabla15[[#This Row],[Facturació A/A]] -> -1 | X89: =Tabla15[[#This Row],[Facturació A/A]]*H$17+Tabla15[[#This Row],[Facturació A/A]] -> 729.9919 | Y89: =Tabla15[[#This Row],[Total Caja]]-Tabla15[[#This Row],[Previsión]] -> -729.9919 | AA89: =SUM(INDEX(Tabla15[[#This Row],[Facturació A/A]],1):Tabla15[[#This Row],[Facturació A/A]]) / SUM(INDEX(Tabla15[[#This Row],[Diferencia]],1):Tabla15[[#This Row],[Diferencia]]) -> -1
C90: 57 | D90: 46079 | E90: 0 | F90: =Tabla15[[#This Row],[Retiros]]-Tabla15[[#This Row],[Contado]] -> 0 | G90: 0 | H90: 0 | I90: 0 | J90: 0 | K90: 0 | L90: 0 | M90: 0 | N90: =Tabla15[[#This Row],[Contado]] -> 0 | P90: =((Tabla15[[#This Row],[Contado]]+Tabla15[[#This Row],[Visa]]+Tabla15[[#This Row],[Eventos]]+Tabla15[[#This Row],[Passo]]+Tabla15[[#This Row],[Reciclajes]])/1.1)+Tabla15[[#This Row],[Tickets]] -> 0 | Q90: 0 | R90: =IFERROR(F90/P90,0) -> 0 | T90: 834.5 | U90: =Tabla15[[#This Row],[Total Caja]]-Tabla15[[#This Row],[Facturació A/A]] -> -834.5 | V90: =U90+V89 -> 9511.55 | W90: =Tabla15[[#This Row],[Diferencia]]/Tabla15[[#This Row],[Facturació A/A]] -> -1 | X90: =Tabla15[[#This Row],[Facturació A/A]]*H$17+Tabla15[[#This Row],[Facturació A/A]] -> 859.535 | Y90: =Tabla15[[#This Row],[Total Caja]]-Tabla15[[#This Row],[Previsión]] -> -859.535 | AA90: =SUM(INDEX(Tabla15[[#This Row],[Facturació A/A]],1):Tabla15[[#This Row],[Facturació A/A]]) / SUM(INDEX(Tabla15[[#This Row],[Diferencia]],1):Tabla15[[#This Row],[Diferencia]]) -> -1
... C154: 121 | D154: 46143 | E154: 372.3 | F154: =Tabla15[[#This Row],[Retiros]]-Tabla15[[#This Row],[Contado]] -> 77.7 | G154: 2796.85 | H154: 0 | I154: 117.7 | J154: 0 | K154: 0 | L154: 0 | M154: 450 | N154: =Tabla15[[#This Row],[Contado]] -> 372.3 | P154: =((Tabla15[[#This Row],[Contado]]+Tabla15[[#This Row],[Visa]]+Tabla15[[#This Row],[Eventos]]+Tabla15[[#This Row],[Passo]]+Tabla15[[#This Row],[Reciclajes]])/1.1)+Tabla15[[#This Row],[Tickets]] -> 3065.7455 | Q154: 0 | R154: =IFERROR(F154/P154,0) -> 0.02534457 | T154: 1291.63 | U154: =Tabla15[[#This Row],[Total Caja]]-Tabla15[[#This Row],[Facturació A/A]] -> 1774.1155 | V154: =U154+V153 -> 4558.4309 | W154: =Tabla15[[#This Row],[Diferencia]]/Tabla15[[#This Row],[Facturació A/A]] -> 1.3735477 | X154: =Tabla15[[#This Row],[Facturació A/A]]*H$17+Tabla15[[#This Row],[Facturació A/A]] -> 1330.3789 | Y154: =Tabla15[[#This Row],[Total Caja]]-Tabla15[[#This Row],[Previsión]] -> 1735.3666 | AA154: =SUM(INDEX(Tabla15[[#This Row],[Facturació A/A]],1):Tabla15[[#This Row],[Facturació A/A]]) / SUM(INDEX(Tabla15[[#This Row],[Diferencia]],1):Tabla15[[#This Row],[Diferencia]]) -> 0.72804168
C155: 122 | D155: 46144 | F155: =Tabla15[[#This Row],[Retiros]]-Tabla15[[#This Row],[Contado]] -> 0 | N155: =Tabla15[[#This Row],[Contado]] -> 0 | P155: =((Tabla15[[#This Row],[Contado]]+Tabla15[[#This Row],[Visa]]+Tabla15[[#This Row],[Eventos]]+Tabla15[[#This Row],[Passo]]+Tabla15[[#This Row],[Reciclajes]])/1.1)+Tabla15[[#This Row],[Tickets]] -> 0 | Q155: 0 | R155: =IFERROR(F155/P155,0) -> 0 | T155: 2091.93 | U155: =Tabla15[[#This Row],[Total Caja]]-Tabla15[[#This Row],[Facturació A/A]] -> -2091.93 | V155: =U155+V154 -> 2466.5009 | W155: =Tabla15[[#This Row],[Diferencia]]/Tabla15[[#This Row],[Facturació A/A]] -> -1 | X155: =Tabla15[[#This Row],[Facturació A/A]]*H$17+Tabla15[[#This Row],[Facturació A/A]] -> 2154.6879 | Y155: =Tabla15[[#This Row],[Total Caja]]-Tabla15[[#This Row],[Previsión]] -> -2154.6879 | AA155: =SUM(INDEX(Tabla15[[#This Row],[Facturació A/A]],1):Tabla15[[#This Row],[Facturació A/A]]) / SUM(INDEX(Tabla15[[#This Row],[Diferencia]],1):Tabla15[[#This Row],[Diferencia]]) -> -1
C156: 123 | D156: 46145 | F156: =Tabla15[[#This Row],[Retiros]]-Tabla15[[#This Row],[Contado]] -> 0 | N156: =Tabla15[[#This Row],[Contado]] -> 0 | P156: =((Tabla15[[#This Row],[Contado]]+Tabla15[[#This Row],[Visa]]+Tabla15[[#This Row],[Eventos]]+Tabla15[[#This Row],[Passo]]+Tabla15[[#This Row],[Reciclajes]])/1.1)+Tabla15[[#This Row],[Tickets]] -> 0 | Q156: 0 | R156: =IFERROR(F156/P156,0) -> 0 | T156: 1222.36 | U156: =Tabla15[[#This Row],[Total Caja]]-Tabla15[[#This Row],[Facturació A/A]] -> -1222.36 | V156: =U156+V155 -> 1244.1409 | W156: =Tabla15[[#This Row],[Diferencia]]/Tabla15[[#This Row],[Facturació A/A]] -> -1 | X156: =Tabla15[[#This Row],[Facturació A/A]]*H$17+Tabla15[[#This Row],[Facturació A/A]] -> 1259.0308 | Y156: =Tabla15[[#This Row],[Total Caja]]-Tabla15[[#This Row],[Previsión]] -> -1259.0308 | AA156: =SUM(INDEX(Tabla15[[#This Row],[Facturació A/A]],1):Tabla15[[#This Row],[Facturació A/A]]) / SUM(INDEX(Tabla15[[#This Row],[Diferencia]],1):Tabla15[[#This Row],[Diferencia]]) -> -1
C157: 124 | D157: 46146 | F157: =Tabla15[[#This Row],[Retiros]]-Tabla15[[#This Row],[Contado]] -> 0 | N157: =Tabla15[[#This Row],[Contado]] -> 0 | P157: =((Tabla15[[#This Row],[Contado]]+Tabla15[[#This Row],[Visa]]+Tabla15[[#This Row],[Eventos]]+Tabla15[[#This Row],[Passo]]+Tabla15[[#This Row],[Reciclajes]])/1.1)+Tabla15[[#This Row],[Tickets]] -> 0 | Q157: 0 | R157: =IFERROR(F157/P157,0) -> 0 | T157: 0 | U157: =Tabla15[[#This Row],[Total Caja]]-Tabla15[[#This Row],[Facturació A/A]] -> 0 | V157: =U157+V156 -> 1244.1409 | W157: =Tabla15[[#This Row],[Diferencia]]/Tabla15[[#This Row],[Facturació A/A]] -> #DIV/0! | X157: =Tabla15[[#This Row],[Facturació A/A]]*H$17+Tabla15[[#This Row],[Facturació A/A]] -> 0 | Y157: =Tabla15[[#This Row],[Total Caja]]-Tabla15[[#This Row],[Previsión]] -> 0 | AA157: =SUM(INDEX(Tabla15[[#This Row],[Facturació A/A]],1):Tabla15[[#This Row],[Facturació A/A]]) / SUM(INDEX(Tabla15[[#This Row],[Diferencia]],1):Tabla15[[#This Row],[Diferencia]]) -> #DIV/0!
C158: 125 | D158: 46147 | F158: =Tabla15[[#This Row],[Retiros]]-Tabla15[[#This Row],[Contado]] -> 0 | N158: =Tabla15[[#This Row],[Contado]] -> 0 | P158: =((Tabla15[[#This Row],[Contado]]+Tabla15[[#This Row],[Visa]]+Tabla15[[#This Row],[Eventos]]+Tabla15[[#This Row],[Passo]]+Tabla15[[#This Row],[Reciclajes]])/1.1)+Tabla15[[#This Row],[Tickets]] -> 0 | Q158: 0 | R158: =IFERROR(F158/P158,0) -> 0 | T158: 0 | U158: =Tabla15[[#This Row],[Total Caja]]-Tabla15[[#This Row],[Facturació A/A]] -> 0 | V158: =U158+V157 -> 1244.1409 | W158: =Tabla15[[#This Row],[Diferencia]]/Tabla15[[#This Row],[Facturació A/A]] -> #DIV/0! | X158: =Tabla15[[#This Row],[Facturació A/A]]*H$17+Tabla15[[#This Row],[Facturació A/A]] -> 0 | Y158: =Tabla15[[#This Row],[Total Caja]]-Tabla15[[#This Row],[Previsión]] -> 0 | AA158: =SUM(INDEX(Tabla15[[#This Row],[Facturació A/A]],1):Tabla15[[#This Row],[Facturació A/A]]) / SUM(INDEX(Tabla15[[#This Row],[Diferencia]],1):Tabla15[[#This Row],[Diferencia]]) -> #DIV/0!
C159: 126 | D159: 46148 | F159: =Tabla15[[#This Row],[Retiros]]-Tabla15[[#This Row],[Contado]] -> 0 | N159: =Tabla15[[#This Row],[Contado]] -> 0 | P159: =((Tabla15[[#This Row],[Contado]]+Tabla15[[#This Row],[Visa]]+Tabla15[[#This Row],[Eventos]]+Tabla15[[#This Row],[Passo]]+Tabla15[[#This Row],[Reciclajes]])/1.1)+Tabla15[[#This Row],[Tickets]] -> 0 | Q159: 0 | R159: =IFERROR(F159/P159,0) -> 0 | T159: 372.08 | U159: =Tabla15[[#This Row],[Total Caja]]-Tabla15[[#This Row],[Facturació A/A]] -> -372.08 | V159: =U159+V158 -> 872.06091 | W159: =Tabla15[[#This Row],[Diferencia]]/Tabla15[[#This Row],[Facturació A/A]] -> -1 | X159: =Tabla15[[#This Row],[Facturació A/A]]*H$17+Tabla15[[#This Row],[Facturació A/A]] -> 383.2424 | Y159: =Tabla15[[#This Row],[Total Caja]]-Tabla15[[#This Row],[Previsión]] -> -383.2424 | AA159: =SUM(INDEX(Tabla15[[#This Row],[Facturació A/A]],1):Tabla15[[#This Row],[Facturació A/A]]) / SUM(INDEX(Tabla15[[#This Row],[Diferencia]],1):Tabla15[[#This Row],[Diferencia]]) -> -1
C160: 127 | D160: 46149 | F160: =Tabla15[[#This Row],[Retiros]]-Tabla15[[#This Row],[Contado]] -> 0 | N160: =Tabla15[[#This Row],[Contado]] -> 0 | P160: =((Tabla15[[#This Row],[Contado]]+Tabla15[[#This Row],[Visa]]+Tabla15[[#This Row],[Eventos]]+Tabla15[[#This Row],[Passo]]+Tabla15[[#This Row],[Reciclajes]])/1.1)+Tabla15[[#This Row],[Tickets]] -> 0 | Q160: 0 | R160: =IFERROR(F160/P160,0) -> 0 | T160: 451.41 | U160: =Tabla15[[#This Row],[Total Caja]]-Tabla15[[#This Row],[Facturació A/A]] -> -451.41 | V160: =U160+V159 -> 420.65091 | W160: =Tabla15[[#This Row],[Diferencia]]/Tabla15[[#This Row],[Facturació A/A]] -> -1 | X160: =Tabla15[[#This Row],[Facturació A/A]]*H$17+Tabla15[[#This Row],[Facturació A/A]] -> 464.9523 | Y160: =Tabla15[[#This Row],[Total Caja]]-Tabla15[[#This Row],[Previsión]] -> -464.9523 | AA160: =SUM(INDEX(Tabla15[[#This Row],[Facturació A/A]],1):Tabla15[[#This Row],[Facturació A/A]]) / SUM(INDEX(Tabla15[[#This Row],[Diferencia]],1):Tabla15[[#This Row],[Diferencia]]) -> -1
C161: 128 | D161: 46150 | F161: =Tabla15[[#This Row],[Retiros]]-Tabla15[[#This Row],[Contado]] -> 0 | N161: =Tabla15[[#This Row],[Contado]] -> 0 | P161: =((Tabla15[[#This Row],[Contado]]+Tabla15[[#This Row],[Visa]]+Tabla15[[#This Row],[Eventos]]+Tabla15[[#This Row],[Passo]]+Tabla15[[#This Row],[Reciclajes]])/1.1)+Tabla15[[#This Row],[Tickets]] -> 0 | Q161: 0 | R161: =IFERROR(F161/P161,0) -> 0 | T161: 1565.5 | U161: =Tabla15[[#This Row],[Total Caja]]-Tabla15[[#This Row],[Facturació A/A]] -> -1565.5 | V161: =U161+V160 -> -1144.8491 | W161: =Tabla15[[#This Row],[Diferencia]]/Tabla15[[#This Row],[Facturació A/A]] -> -1 | X161: =Tabla15[[#This Row],[Facturació A/A]]*H$17+Tabla15[[#This Row],[Facturació A/A]] -> 1612.465 | Y161: =Tabla15[[#This Row],[Total Caja]]-Tabla15[[#This Row],[Previsión]] -> -1612.465 | AA161: =SUM(INDEX(Tabla15[[#This Row],[Facturació A/A]],1):Tabla15[[#This Row],[Facturació A/A]]) / SUM(INDEX(Tabla15[[#This Row],[Diferencia]],1):Tabla15[[#This Row],[Diferencia]]) -> -1
C162: 129 | D162: 46151 | F162: =Tabla15[[#This Row],[Retiros]]-Tabla15[[#This Row],[Contado]] -> 0 | N162: =Tabla15[[#This Row],[Contado]] -> 0 | P162: =((Tabla15[[#This Row],[Contado]]+Tabla15[[#This Row],[Visa]]+Tabla15[[#This Row],[Eventos]]+Tabla15[[#This Row],[Passo]]+Tabla15[[#This Row],[Reciclajes]])/1.1)+Tabla15[[#This Row],[Tickets]] -> 0 | Q162: 0 | R162: =IFERROR(F162/P162,0) -> 0 | T162: 1378.34 | U162: =Tabla15[[#This Row],[Total Caja]]-Tabla15[[#This Row],[Facturació A/A]] -> -1378.34 | V162: =U162+V161 -> -2523.1891 | W162: =Tabla15[[#This Row],[Diferencia]]/Tabla15[[#This Row],[Facturació A/A]] -> -1 | X162: =Tabla15[[#This Row],[Facturació A/A]]*H$17+Tabla15[[#This Row],[Facturació A/A]] -> 1419.6902 | Y162: =Tabla15[[#This Row],[Total Caja]]-Tabla15[[#This Row],[Previsión]] -> -1419.6902 | AA162: =SUM(INDEX(Tabla15[[#This Row],[Facturació A/A]],1):Tabla15[[#This Row],[Facturació A/A]]) / SUM(INDEX(Tabla15[[#This Row],[Diferencia]],1):Tabla15[[#This Row],[Diferencia]]) -> -1
C163: 130 | D163: 46152 | F163: =Tabla15[[#This Row],[Retiros]]-Tabla15[[#This Row],[Contado]] -> 0 | N163: =Tabla15[[#This Row],[Contado]] -> 0 | P163: =((Tabla15[[#This Row],[Contado]]+Tabla15[[#This Row],[Visa]]+Tabla15[[#This Row],[Eventos]]+Tabla15[[#This Row],[Passo]]+Tabla15[[#This Row],[Reciclajes]])/1.1)+Tabla15[[#This Row],[Tickets]] -> 0 | Q163: 0 | R163: =IFERROR(F163/P163,0) -> 0 | T163: 1092.43 | U163: =Tabla15[[#This Row],[Total Caja]]-Tabla15[[#This Row],[Facturació A/A]] -> -1092.43 | V163: =U163+V162 -> -3615.6191 | W163: =Tabla15[[#This Row],[Diferencia]]/Tabla15[[#This Row],[Facturació A/A]] -> -1 | X163: =Tabla15[[#This Row],[Facturació A/A]]*H$17+Tabla15[[#This Row],[Facturació A/A]] -> 1125.2029 | Y163: =Tabla15[[#This Row],[Total Caja]]-Tabla15[[#This Row],[Previsión]] -> -1125.2029 | AA163: =SUM(INDEX(Tabla15[[#This Row],[Facturació A/A]],1):Tabla15[[#This Row],[Facturació A/A]]) / SUM(INDEX(Tabla15[[#This Row],[Diferencia]],1):Tabla15[[#This Row],[Diferencia]]) -> -1
C164: 131 | D164: 46153 | F164: =Tabla15[[#This Row],[Retiros]]-Tabla15[[#This Row],[Contado]] -> 0 | N164: =Tabla15[[#This Row],[Contado]] -> 0 | P164: =((Tabla15[[#This Row],[Contado]]+Tabla15[[#This Row],[Visa]]+Tabla15[[#This Row],[Eventos]]+Tabla15[[#This Row],[Passo]]+Tabla15[[#This Row],[Reciclajes]])/1.1)+Tabla15[[#This Row],[Tickets]] -> 0 | Q164: 0 | R164: =IFERROR(F164/P164,0) -> 0 | T164: 0 | U164: =Tabla15[[#This Row],[Total Caja]]-Tabla15[[#This Row],[Facturació A/A]] -> 0 | V164: =U164+V163 -> -3615.6191 | W164: =Tabla15[[#This Row],[Diferencia]]/Tabla15[[#This Row],[Facturació A/A]] -> #DIV/0! | X164: =Tabla15[[#This Row],[Facturació A/A]]*H$17+Tabla15[[#This Row],[Facturació A/A]] -> 0 | Y164: =Tabla15[[#This Row],[Total Caja]]-Tabla15[[#This Row],[Previsión]] -> 0 | AA164: =SUM(INDEX(Tabla15[[#This Row],[Facturació A/A]],1):Tabla15[[#This Row],[Facturació A/A]]) / SUM(INDEX(Tabla15[[#This Row],[Diferencia]],1):Tabla15[[#This Row],[Diferencia]]) -> #DIV/0!
C165: 132 | D165: 46154 | F165: =Tabla15[[#This Row],[Retiros]]-Tabla15[[#This Row],[Contado]] -> 0 | N165: =Tabla15[[#This Row],[Contado]] -> 0 | P165: =((Tabla15[[#This Row],[Contado]]+Tabla15[[#This Row],[Visa]]+Tabla15[[#This Row],[Eventos]]+Tabla15[[#This Row],[Passo]]+Tabla15[[#This Row],[Reciclajes]])/1.1)+Tabla15[[#This Row],[Tickets]] -> 0 | Q165: 0 | R165: =IFERROR(F165/P165,0) -> 0 | T165: 0 | U165: =Tabla15[[#This Row],[Total Caja]]-Tabla15[[#This Row],[Facturació A/A]] -> 0 | V165: =U165+V164 -> -3615.6191 | W165: =Tabla15[[#This Row],[Diferencia]]/Tabla15[[#This Row],[Facturació A/A]] -> #DIV/0! | X165: =Tabla15[[#This Row],[Facturació A/A]]*H$17+Tabla15[[#This Row],[Facturació A/A]] -> 0 | Y165: =Tabla15[[#This Row],[Total Caja]]-Tabla15[[#This Row],[Previsión]] -> 0 | AA165: =SUM(INDEX(Tabla15[[#This Row],[Facturació A/A]],1):Tabla15[[#This Row],[Facturació A/A]]) / SUM(INDEX(Tabla15[[#This Row],[Diferencia]],1):Tabla15[[#This Row],[Diferencia]]) -> #DIV/0!
C166: 133 | D166: 46155 | F166: =Tabla15[[#This Row],[Retiros]]-Tabla15[[#This Row],[Contado]] -> 0 | N166: =Tabla15[[#This Row],[Contado]] -> 0 | P166: =((Tabla15[[#This Row],[Contado]]+Tabla15[[#This Row],[Visa]]+Tabla15[[#This Row],[Eventos]]+Tabla15[[#This Row],[Passo]]+Tabla15[[#This Row],[Reciclajes]])/1.1)+Tabla15[[#This Row],[Tickets]] -> 0 | Q166: 0 | R166: =IFERROR(F166/P166,0) -> 0 | T166: 1046.5 | U166: =Tabla15[[#This Row],[Total Caja]]-Tabla15[[#This Row],[Facturació A/A]] -> -1046.5 | V166: =U166+V165 -> -4662.1191 | W166: =Tabla15[[#This Row],[Diferencia]]/Tabla15[[#This Row],[Facturació A/A]] -> -1 | X166: =Tabla15[[#This Row],[Facturació A/A]]*H$17+Tabla15[[#This Row],[Facturació A/A]] -> 1077.895 | Y166: =Tabla15[[#This Row],[Total Caja]]-Tabla15[[#This Row],[Previsión]] -> -1077.895 | AA166: =SUM(INDEX(Tabla15[[#This Row],[Facturació A/A]],1):Tabla15[[#This Row],[Facturació A/A]]) / SUM(INDEX(Tabla15[[#This Row],[Diferencia]],1):Tabla15[[#This Row],[Diferencia]]) -> -1
... C317: 284 | D317: 46306 | F317: =Tabla15[[#This Row],[Retiros]]-Tabla15[[#This Row],[Contado]] -> 0 | N317: =Tabla15[[#This Row],[Contado]] -> 0 | P317: =((Tabla15[[#This Row],[Contado]]+Tabla15[[#This Row],[Visa]]+Tabla15[[#This Row],[Eventos]]+Tabla15[[#This Row],[Passo]]+Tabla15[[#This Row],[Reciclajes]])/1.1)+Tabla15[[#This Row],[Tickets]] -> 0 | Q317: 0 | R317: =IFERROR(F317/P317,0) -> 0 | T317: 2075.44 | U317: =Tabla15[[#This Row],[Total Caja]]-Tabla15[[#This Row],[Facturació A/A]] -> -2075.44 | V317: =U317+V316 -> -176165.25 | W317: =Tabla15[[#This Row],[Diferencia]]/Tabla15[[#This Row],[Facturació A/A]] -> -1 | X317: =Tabla15[[#This Row],[Facturació A/A]]*H$17+Tabla15[[#This Row],[Facturació A/A]] -> 2137.7032 | Y317: =Tabla15[[#This Row],[Total Caja]]-Tabla15[[#This Row],[Previsión]] -> -2137.7032 | AA317: =SUM(INDEX(Tabla15[[#This Row],[Facturació A/A]],1):Tabla15[[#This Row],[Facturació A/A]]) / SUM(INDEX(Tabla15[[#This Row],[Diferencia]],1):Tabla15[[#This Row],[Diferencia]]) -> -1
C318: 285 | D318: 46307 | F318: =Tabla15[[#This Row],[Retiros]]-Tabla15[[#This Row],[Contado]] -> 0 | N318: =Tabla15[[#This Row],[Contado]] -> 0 | P318: =((Tabla15[[#This Row],[Contado]]+Tabla15[[#This Row],[Visa]]+Tabla15[[#This Row],[Eventos]]+Tabla15[[#This Row],[Passo]]+Tabla15[[#This Row],[Reciclajes]])/1.1)+Tabla15[[#This Row],[Tickets]] -> 0 | Q318: 0 | R318: =IFERROR(F318/P318,0) -> 0 | T318: 0 | U318: =Tabla15[[#This Row],[Total Caja]]-Tabla15[[#This Row],[Facturació A/A]] -> 0 | V318: =U318+V317 -> -176165.25 | W318: =Tabla15[[#This Row],[Diferencia]]/Tabla15[[#This Row],[Facturació A/A]] -> #DIV/0! | X318: =Tabla15[[#This Row],[Facturació A/A]]*H$17+Tabla15[[#This Row],[Facturació A/A]] -> 0 | Y318: =Tabla15[[#This Row],[Total Caja]]-Tabla15[[#This Row],[Previsión]] -> 0 | AA318: =SUM(INDEX(Tabla15[[#This Row],[Facturació A/A]],1):Tabla15[[#This Row],[Facturació A/A]]) / SUM(INDEX(Tabla15[[#This Row],[Diferencia]],1):Tabla15[[#This Row],[Diferencia]]) -> #DIV/0! | AC318: #REF!
C319: 286 | D319: 46308 | F319: =Tabla15[[#This Row],[Retiros]]-Tabla15[[#This Row],[Contado]] -> 0 | N319: =Tabla15[[#This Row],[Contado]] -> 0 | P319: =((Tabla15[[#This Row],[Contado]]+Tabla15[[#This Row],[Visa]]+Tabla15[[#This Row],[Eventos]]+Tabla15[[#This Row],[Passo]]+Tabla15[[#This Row],[Reciclajes]])/1.1)+Tabla15[[#This Row],[Tickets]] -> 0 | Q319: 0 | R319: =IFERROR(F319/P319,0) -> 0 | T319: 0 | U319: =Tabla15[[#This Row],[Total Caja]]-Tabla15[[#This Row],[Facturació A/A]] -> 0 | V319: =U319+V318 -> -176165.25 | W319: =Tabla15[[#This Row],[Diferencia]]/Tabla15[[#This Row],[Facturació A/A]] -> #DIV/0! | X319: =Tabla15[[#This Row],[Facturació A/A]]*H$17+Tabla15[[#This Row],[Facturació A/A]] -> 0 | Y319: =Tabla15[[#This Row],[Total Caja]]-Tabla15[[#This Row],[Previsión]] -> 0 | AA319: =SUM(INDEX(Tabla15[[#This Row],[Facturació A/A]],1):Tabla15[[#This Row],[Facturació A/A]]) / SUM(INDEX(Tabla15[[#This Row],[Diferencia]],1):Tabla15[[#This Row],[Diferencia]]) -> #DIV/0!
C320: 287 | D320: 46309 | F320: =Tabla15[[#This Row],[Retiros]]-Tabla15[[#This Row],[Contado]] -> 0 | N320: =Tabla15[[#This Row],[Contado]] -> 0 | P320: =((Tabla15[[#This Row],[Contado]]+Tabla15[[#This Row],[Visa]]+Tabla15[[#This Row],[Eventos]]+Tabla15[[#This Row],[Passo]]+Tabla15[[#This Row],[Reciclajes]])/1.1)+Tabla15[[#This Row],[Tickets]] -> 0 | Q320: 0 | R320: =IFERROR(F320/P320,0) -> 0 | T320: 978.3 | U320: =Tabla15[[#This Row],[Total Caja]]-Tabla15[[#This Row],[Facturació A/A]] -> -978.3 | V320: =U320+V319 -> -177143.55 | W320: =Tabla15[[#This Row],[Diferencia]]/Tabla15[[#This Row],[Facturació A/A]] -> -1 | X320: =Tabla15[[#This Row],[Facturació A/A]]*H$17+Tabla15[[#This Row],[Facturació A/A]] -> 1007.649 | Y320: =Tabla15[[#This Row],[Total Caja]]-Tabla15[[#This Row],[Previsión]] -> -1007.649 | AA320: =SUM(INDEX(Tabla15[[#This Row],[Facturació A/A]],1):Tabla15[[#This Row],[Facturació A/A]]) / SUM(INDEX(Tabla15[[#This Row],[Diferencia]],1):Tabla15[[#This Row],[Diferencia]]) -> -1
C321: 288 | D321: 46310 | F321: =Tabla15[[#This Row],[Retiros]]-Tabla15[[#This Row],[Contado]] -> 0 | N321: =Tabla15[[#This Row],[Contado]] -> 0 | P321: =((Tabla15[[#This Row],[Contado]]+Tabla15[[#This Row],[Visa]]+Tabla15[[#This Row],[Eventos]]+Tabla15[[#This Row],[Passo]]+Tabla15[[#This Row],[Reciclajes]])/1.1)+Tabla15[[#This Row],[Tickets]] -> 0 | Q321: 0 | R321: =IFERROR(F321/P321,0) -> 0 | T321: 773.45 | U321: =Tabla15[[#This Row],[Total Caja]]-Tabla15[[#This Row],[Facturació A/A]] -> -773.45 | V321: =U321+V320 -> -177917 | W321: =Tabla15[[#This Row],[Diferencia]]/Tabla15[[#This Row],[Facturació A/A]] -> -1 | X321: =Tabla15[[#This Row],[Facturació A/A]]*H$17+Tabla15[[#This Row],[Facturació A/A]] -> 796.6535 | Y321: =Tabla15[[#This Row],[Total Caja]]-Tabla15[[#This Row],[Previsión]] -> -796.6535 | AA321: =SUM(INDEX(Tabla15[[#This Row],[Facturació A/A]],1):Tabla15[[#This Row],[Facturació A/A]]) / SUM(INDEX(Tabla15[[#This Row],[Diferencia]],1):Tabla15[[#This Row],[Diferencia]]) -> -1
C322: 289 | D322: 46311 | F322: =Tabla15[[#This Row],[Retiros]]-Tabla15[[#This Row],[Contado]] -> 0 | N322: =Tabla15[[#This Row],[Contado]] -> 0 | P322: =((Tabla15[[#This Row],[Contado]]+Tabla15[[#This Row],[Visa]]+Tabla15[[#This Row],[Eventos]]+Tabla15[[#This Row],[Passo]]+Tabla15[[#This Row],[Reciclajes]])/1.1)+Tabla15[[#This Row],[Tickets]] -> 0 | Q322: 0 | R322: =IFERROR(F322/P322,0) -> 0 | T322: 1260.61 | U322: =Tabla15[[#This Row],[Total Caja]]-Tabla15[[#This Row],[Facturació A/A]] -> -1260.61 | V322: =U322+V321 -> -179177.61 | W322: =Tabla15[[#This Row],[Diferencia]]/Tabla15[[#This Row],[Facturació A/A]] -> -1 | X322: =Tabla15[[#This Row],[Facturació A/A]]*H$17+Tabla15[[#This Row],[Facturació A/A]] -> 1298.4283 | Y322: =Tabla15[[#This Row],[Total Caja]]-Tabla15[[#This Row],[Previsión]] -> -1298.4283 | AA322: =SUM(INDEX(Tabla15[[#This Row],[Facturació A/A]],1):Tabla15[[#This Row],[Facturació A/A]]) / SUM(INDEX(Tabla15[[#This Row],[Diferencia]],1):Tabla15[[#This Row],[Diferencia]]) -> -1
C323: 290 | D323: 46312 | F323: =Tabla15[[#This Row],[Retiros]]-Tabla15[[#This Row],[Contado]] -> 0 | N323: =Tabla15[[#This Row],[Contado]] -> 0 | P323: =((Tabla15[[#This Row],[Contado]]+Tabla15[[#This Row],[Visa]]+Tabla15[[#This Row],[Eventos]]+Tabla15[[#This Row],[Passo]]+Tabla15[[#This Row],[Reciclajes]])/1.1)+Tabla15[[#This Row],[Tickets]] -> 0 | Q323: 0 | R323: =IFERROR(F323/P323,0) -> 0 | T323: 2375.74 | U323: =Tabla15[[#This Row],[Total Caja]]-Tabla15[[#This Row],[Facturació A/A]] -> -2375.74 | V323: =U323+V322 -> -181553.35 | W323: =Tabla15[[#This Row],[Diferencia]]/Tabla15[[#This Row],[Facturació A/A]] -> -1 | X323: =Tabla15[[#This Row],[Facturació A/A]]*H$17+Tabla15[[#This Row],[Facturació A/A]] -> 2447.0122 | Y323: =Tabla15[[#This Row],[Total Caja]]-Tabla15[[#This Row],[Previsión]] -> -2447.0122 | AA323: =SUM(INDEX(Tabla15[[#This Row],[Facturació A/A]],1):Tabla15[[#This Row],[Facturació A/A]]) / SUM(INDEX(Tabla15[[#This Row],[Diferencia]],1):Tabla15[[#This Row],[Diferencia]]) -> -1
C324: 291 | D324: 46313 | F324: =Tabla15[[#This Row],[Retiros]]-Tabla15[[#This Row],[Contado]] -> 0 | N324: =Tabla15[[#This Row],[Contado]] -> 0 | P324: =((Tabla15[[#This Row],[Contado]]+Tabla15[[#This Row],[Visa]]+Tabla15[[#This Row],[Eventos]]+Tabla15[[#This Row],[Passo]]+Tabla15[[#This Row],[Reciclajes]])/1.1)+Tabla15[[#This Row],[Tickets]] -> 0 | Q324: 0 | R324: =IFERROR(F324/P324,0) -> 0 | T324: 1931.89 | U324: =Tabla15[[#This Row],[Total Caja]]-Tabla15[[#This Row],[Facturació A/A]] -> -1931.89 | V324: =U324+V323 -> -183485.24 | W324: =Tabla15[[#This Row],[Diferencia]]/Tabla15[[#This Row],[Facturació A/A]] -> -1 | X324: =Tabla15[[#This Row],[Facturació A/A]]*H$17+Tabla15[[#This Row],[Facturació A/A]] -> 1989.8467 | Y324: =Tabla15[[#This Row],[Total Caja]]-Tabla15[[#This Row],[Previsión]] -> -1989.8467 | AA324: =SUM(INDEX(Tabla15[[#This Row],[Facturació A/A]],1):Tabla15[[#This Row],[Facturació A/A]]) / SUM(INDEX(Tabla15[[#This Row],[Diferencia]],1):Tabla15[[#This Row],[Diferencia]]) -> -1
C325: 292 | D325: 46314 | F325: =Tabla15[[#This Row],[Retiros]]-Tabla15[[#This Row],[Contado]] -> 0 | N325: =Tabla15[[#This Row],[Contado]] -> 0 | P325: =((Tabla15[[#This Row],[Contado]]+Tabla15[[#This Row],[Visa]]+Tabla15[[#This Row],[Eventos]]+Tabla15[[#This Row],[Passo]]+Tabla15[[#This Row],[Reciclajes]])/1.1)+Tabla15[[#This Row],[Tickets]] -> 0 | Q325: 0 | R325: =IFERROR(F325/P325,0) -> 0 | T325: 0 | U325: =Tabla15[[#This Row],[Total Caja]]-Tabla15[[#This Row],[Facturació A/A]] -> 0 | V325: =U325+V324 -> -183485.24 | W325: =Tabla15[[#This Row],[Diferencia]]/Tabla15[[#This Row],[Facturació A/A]] -> #DIV/0! | X325: =Tabla15[[#This Row],[Facturació A/A]]*H$17+Tabla15[[#This Row],[Facturació A/A]] -> 0 | Y325: =Tabla15[[#This Row],[Total Caja]]-Tabla15[[#This Row],[Previsión]] -> 0 | AA325: =SUM(INDEX(Tabla15[[#This Row],[Facturació A/A]],1):Tabla15[[#This Row],[Facturació A/A]]) / SUM(INDEX(Tabla15[[#This Row],[Diferencia]],1):Tabla15[[#This Row],[Diferencia]]) -> #DIV/0!
C326: 293 | D326: 46315 | F326: =Tabla15[[#This Row],[Retiros]]-Tabla15[[#This Row],[Contado]] -> 0 | N326: =Tabla15[[#This Row],[Contado]] -> 0 | P326: =((Tabla15[[#This Row],[Contado]]+Tabla15[[#This Row],[Visa]]+Tabla15[[#This Row],[Eventos]]+Tabla15[[#This Row],[Passo]]+Tabla15[[#This Row],[Reciclajes]])/1.1)+Tabla15[[#This Row],[Tickets]] -> 0 | Q326: 0 | R326: =IFERROR(F326/P326,0) -> 0 | T326: 0 | U326: =Tabla15[[#This Row],[Total Caja]]-Tabla15[[#This Row],[Facturació A/A]] -> 0 | V326: =U326+V325 -> -183485.24 | W326: =Tabla15[[#This Row],[Diferencia]]/Tabla15[[#This Row],[Facturació A/A]] -> #DIV/0! | X326: =Tabla15[[#This Row],[Facturació A/A]]*H$17+Tabla15[[#This Row],[Facturació A/A]] -> 0 | Y326: =Tabla15[[#This Row],[Total Caja]]-Tabla15[[#This Row],[Previsión]] -> 0 | AA326: =SUM(INDEX(Tabla15[[#This Row],[Facturació A/A]],1):Tabla15[[#This Row],[Facturació A/A]]) / SUM(INDEX(Tabla15[[#This Row],[Diferencia]],1):Tabla15[[#This Row],[Diferencia]]) -> #DIV/0!
C327: 294 | D327: 46316 | F327: =Tabla15[[#This Row],[Retiros]]-Tabla15[[#This Row],[Contado]] -> 0 | N327: =Tabla15[[#This Row],[Contado]] -> 0 | P327: =((Tabla15[[#This Row],[Contado]]+Tabla15[[#This Row],[Visa]]+Tabla15[[#This Row],[Eventos]]+Tabla15[[#This Row],[Passo]]+Tabla15[[#This Row],[Reciclajes]])/1.1)+Tabla15[[#This Row],[Tickets]] -> 0 | Q327: 0 | R327: =IFERROR(F327/P327,0) -> 0 | T327: 652.91 | U327: =Tabla15[[#This Row],[Total Caja]]-Tabla15[[#This Row],[Facturació A/A]] -> -652.91 | V327: =U327+V326 -> -184138.15 | W327: =Tabla15[[#This Row],[Diferencia]]/Tabla15[[#This Row],[Facturació A/A]] -> -1 | X327: =Tabla15[[#This Row],[Facturació A/A]]*H$17+Tabla15[[#This Row],[Facturació A/A]] -> 672.4973 | Y327: =Tabla15[[#This Row],[Total Caja]]-Tabla15[[#This Row],[Previsión]] -> -672.4973 | AA327: =SUM(INDEX(Tabla15[[#This Row],[Facturació A/A]],1):Tabla15[[#This Row],[Facturació A/A]]) / SUM(INDEX(Tabla15[[#This Row],[Diferencia]],1):Tabla15[[#This Row],[Diferencia]]) -> -1
B328: 145 | C328: 295 | D328: 46317 | F328: =Tabla15[[#This Row],[Retiros]]-Tabla15[[#This Row],[Contado]] -> 0 | N328: =Tabla15[[#This Row],[Contado]] -> 0 | P328: =((Tabla15[[#This Row],[Contado]]+Tabla15[[#This Row],[Visa]]+Tabla15[[#This Row],[Eventos]]+Tabla15[[#This Row],[Passo]]+Tabla15[[#This Row],[Reciclajes]])/1.1)+Tabla15[[#This Row],[Tickets]] -> 0 | Q328: 0 | R328: =IFERROR(F328/P328,0) -> 0 | T328: 699.21 | U328: =Tabla15[[#This Row],[Total Caja]]-Tabla15[[#This Row],[Facturació A/A]] -> -699.21 | V328: =U328+V327 -> -184837.36 | W328: =Tabla15[[#This Row],[Diferencia]]/Tabla15[[#This Row],[Facturació A/A]] -> -1 | X328: =Tabla15[[#This Row],[Facturació A/A]]*H$17+Tabla15[[#This Row],[Facturació A/A]] -> 720.1863 | Y328: =Tabla15[[#This Row],[Total Caja]]-Tabla15[[#This Row],[Previsión]] -> -720.1863 | AA328: =SUM(INDEX(Tabla15[[#This Row],[Facturació A/A]],1):Tabla15[[#This Row],[Facturació A/A]]) / SUM(INDEX(Tabla15[[#This Row],[Diferencia]],1):Tabla15[[#This Row],[Diferencia]]) -> -1
C329: 296 | D329: 46318 | F329: =Tabla15[[#This Row],[Retiros]]-Tabla15[[#This Row],[Contado]] -> 0 | N329: =Tabla15[[#This Row],[Contado]] -> 0 | P329: =((Tabla15[[#This Row],[Contado]]+Tabla15[[#This Row],[Visa]]+Tabla15[[#This Row],[Eventos]]+Tabla15[[#This Row],[Passo]]+Tabla15[[#This Row],[Reciclajes]])/1.1)+Tabla15[[#This Row],[Tickets]] -> 0 | Q329: 0 | R329: =IFERROR(F329/P329,0) -> 0 | T329: 1174.11 | U329: =Tabla15[[#This Row],[Total Caja]]-Tabla15[[#This Row],[Facturació A/A]] -> -1174.11 | V329: =U329+V328 -> -186011.47 | W329: =Tabla15[[#This Row],[Diferencia]]/Tabla15[[#This Row],[Facturació A/A]] -> -1 | X329: =Tabla15[[#This Row],[Facturació A/A]]*H$17+Tabla15[[#This Row],[Facturació A/A]] -> 1209.3333 | Y329: =Tabla15[[#This Row],[Total Caja]]-Tabla15[[#This Row],[Previsión]] -> -1209.3333 | AA329: =SUM(INDEX(Tabla15[[#This Row],[Facturació A/A]],1):Tabla15[[#This Row],[Facturació A/A]]) / SUM(INDEX(Tabla15[[#This Row],[Diferencia]],1):Tabla15[[#This Row],[Diferencia]]) -> -1
C330: 297 | D330: 46319 | F330: =Tabla15[[#This Row],[Retiros]]-Tabla15[[#This Row],[Contado]] -> 0 | N330: =Tabla15[[#This Row],[Contado]] -> 0 | P330: =((Tabla15[[#This Row],[Contado]]+Tabla15[[#This Row],[Visa]]+Tabla15[[#This Row],[Eventos]]+Tabla15[[#This Row],[Passo]]+Tabla15[[#This Row],[Reciclajes]])/1.1)+Tabla15[[#This Row],[Tickets]] -> 0 | Q330: 0 | R330: =IFERROR(F330/P330,0) -> 0 | T330: 1763.05 | U330: =Tabla15[[#This Row],[Total Caja]]-Tabla15[[#This Row],[Facturació A/A]] -> -1763.05 | V330: =U330+V329 -> -187774.52 | W330: =Tabla15[[#This Row],[Diferencia]]/Tabla15[[#This Row],[Facturació A/A]] -> -1 | X330: =Tabla15[[#This Row],[Facturació A/A]]*H$17+Tabla15[[#This Row],[Facturació A/A]] -> 1815.9415 | Y330: =Tabla15[[#This Row],[Total Caja]]-Tabla15[[#This Row],[Previsión]] -> -1815.9415 | AA330: =SUM(INDEX(Tabla15[[#This Row],[Facturació A/A]],1):Tabla15[[#This Row],[Facturació A/A]]) / SUM(INDEX(Tabla15[[#This Row],[Diferencia]],1):Tabla15[[#This Row],[Diferencia]]) -> -1
C331: 298 | D331: 46320 | F331: =Tabla15[[#This Row],[Retiros]]-Tabla15[[#This Row],[Contado]] -> 0 | N331: =Tabla15[[#This Row],[Contado]] -> 0 | P331: =((Tabla15[[#This Row],[Contado]]+Tabla15[[#This Row],[Visa]]+Tabla15[[#This Row],[Eventos]]+Tabla15[[#This Row],[Passo]]+Tabla15[[#This Row],[Reciclajes]])/1.1)+Tabla15[[#This Row],[Tickets]] -> 0 | Q331: 0 | R331: =IFERROR(F331/P331,0) -> 0 | T331: 1490.57 | U331: =Tabla15[[#This Row],[Total Caja]]-Tabla15[[#This Row],[Facturació A/A]] -> -1490.57 | V331: =U331+V330 -> -189265.09 | W331: =Tabla15[[#This Row],[Diferencia]]/Tabla15[[#This Row],[Facturació A/A]] -> -1 | X331: =Tabla15[[#This Row],[Facturació A/A]]*H$17+Tabla15[[#This Row],[Facturació A/A]] -> 1535.2871 | Y331: =Tabla15[[#This Row],[Total Caja]]-Tabla15[[#This Row],[Previsión]] -> -1535.2871 | AA331: =SUM(INDEX(Tabla15[[#This Row],[Facturació A/A]],1):Tabla15[[#This Row],[Facturació A/A]]) / SUM(INDEX(Tabla15[[#This Row],[Diferencia]],1):Tabla15[[#This Row],[Diferencia]]) -> -1
C332: 299 | D332: 46321 | F332: =Tabla15[[#This Row],[Retiros]]-Tabla15[[#This Row],[Contado]] -> 0 | N332: =Tabla15[[#This Row],[Contado]] -> 0 | P332: =((Tabla15[[#This Row],[Contado]]+Tabla15[[#This Row],[Visa]]+Tabla15[[#This Row],[Eventos]]+Tabla15[[#This Row],[Passo]]+Tabla15[[#This Row],[Reciclajes]])/1.1)+Tabla15[[#This Row],[Tickets]] -> 0 | Q332: 0 | R332: =IFERROR(F332/P332,0) -> 0 | T332: 0 | U332: =Tabla15[[#This Row],[Total Caja]]-Tabla15[[#This Row],[Facturació A/A]] -> 0 | V332: =U332+V331 -> -189265.09 | W332: =Tabla15[[#This Row],[Diferencia]]/Tabla15[[#This Row],[Facturació A/A]] -> #DIV/0! | X332: =Tabla15[[#This Row],[Facturació A/A]]*H$17+Tabla15[[#This Row],[Facturació A/A]] -> 0 | Y332: =Tabla15[[#This Row],[Total Caja]]-Tabla15[[#This Row],[Previsión]] -> 0 | AA332: =SUM(INDEX(Tabla15[[#This Row],[Facturació A/A]],1):Tabla15[[#This Row],[Facturació A/A]]) / SUM(INDEX(Tabla15[[#This Row],[Diferencia]],1):Tabla15[[#This Row],[Diferencia]]) -> #DIV/0!
C333: 300 | D333: 46322 | F333: =Tabla15[[#This Row],[Retiros]]-Tabla15[[#This Row],[Contado]] -> 0 | N333: =Tabla15[[#This Row],[Contado]] -> 0 | P333: =((Tabla15[[#This Row],[Contado]]+Tabla15[[#This Row],[Visa]]+Tabla15[[#This Row],[Eventos]]+Tabla15[[#This Row],[Passo]]+Tabla15[[#This Row],[Reciclajes]])/1.1)+Tabla15[[#This Row],[Tickets]] -> 0 | Q333: 0 | R333: =IFERROR(F333/P333,0) -> 0 | T333: 0 | U333: =Tabla15[[#This Row],[Total Caja]]-Tabla15[[#This Row],[Facturació A/A]] -> 0 | V333: =U333+V332 -> -189265.09 | W333: =Tabla15[[#This Row],[Diferencia]]/Tabla15[[#This Row],[Facturació A/A]] -> #DIV/0! | X333: =Tabla15[[#This Row],[Facturació A/A]]*H$17+Tabla15[[#This Row],[Facturació A/A]] -> 0 | Y333: =Tabla15[[#This Row],[Total Caja]]-Tabla15[[#This Row],[Previsión]] -> 0 | AA333: =SUM(INDEX(Tabla15[[#This Row],[Facturació A/A]],1):Tabla15[[#This Row],[Facturació A/A]]) / SUM(INDEX(Tabla15[[#This Row],[Diferencia]],1):Tabla15[[#This Row],[Diferencia]]) -> #DIV/0! | AC333: 194.45 | AD333: 31.09 | AE333: 0
C334: 301 | D334: 46323 | F334: =Tabla15[[#This Row],[Retiros]]-Tabla15[[#This Row],[Contado]] -> 0 | N334: =Tabla15[[#This Row],[Contado]] -> 0 | P334: =((Tabla15[[#This Row],[Contado]]+Tabla15[[#This Row],[Visa]]+Tabla15[[#This Row],[Eventos]]+Tabla15[[#This Row],[Passo]]+Tabla15[[#This Row],[Reciclajes]])/1.1)+Tabla15[[#This Row],[Tickets]] -> 0 | Q334: 0 | R334: =IFERROR(F334/P334,0) -> 0 | T334: 901.95 | U334: =Tabla15[[#This Row],[Total Caja]]-Tabla15[[#This Row],[Facturació A/A]] -> -901.95 | V334: =U334+V333 -> -190167.04 | W334: =Tabla15[[#This Row],[Diferencia]]/Tabla15[[#This Row],[Facturació A/A]] -> -1 | X334: =Tabla15[[#This Row],[Facturació A/A]]*H$17+Tabla15[[#This Row],[Facturació A/A]] -> 929.0085 | Y334: =Tabla15[[#This Row],[Total Caja]]-Tabla15[[#This Row],[Previsión]] -> -929.0085 | AA334: =SUM(INDEX(Tabla15[[#This Row],[Facturació A/A]],1):Tabla15[[#This Row],[Facturació A/A]]) / SUM(INDEX(Tabla15[[#This Row],[Diferencia]],1):Tabla15[[#This Row],[Diferencia]]) -> -1 | AC334: 455.55 | AD334: 358.91 | AE334: 210
...

Sheet Caja 1
A1: TAPERIA DE CALDES · CAJA 1 — REGISTRO DIARIO DE VENTAS | L1: RESUMEN MENSUAL
A2: 📘 CÓMO USAR: Introduce cada día los importes por turno. Los totales se calculan automáticamente. Azul = dato a introducir · Verde = cálculo automático | L2: Mes | O2: Comensales | P2: Facturación € | Q2: Ticket Medio € | R2: Coste Personal € | S2: Margen € | T2: % Coste
A3: Fecha | B3: Día | C3: Turno | D3: Nº Comensales | E3: Subtotal € | F3: Ticket Medio € | G3: Coste Personal € | H3: Margen € | I3: % Coste | J3: Notas / Evento | L3: Enero | O3: {=SUMPRODUCT(--(MONTH($A$4:$A$919+0)=ROW()-2),$D$4:$D$919)} -> 759 | P3: {=SUMPRODUCT(--(MONTH($A$4:$A$919+0)=ROW()-2),$E$4:$E$919)} -> 3490.48 | Q3: =IFERROR(P3/O3,0) -> 4.5987879 | R3: {=SUMPRODUCT(--(MONTH($A$4:$A$919+0)=ROW()-2),$G$4:$G$919)} -> 0 | S3: =P3-R3 -> 3490.48 | T3: =IFERROR(R3/P3,0) -> 0
A4: 46024 | B4: =IF(A4="","",CHOOSE(WEEKDAY(A4,2),"Lun","Mar","Mié","Jue","Vie","Sáb","Dom")) -> Vie | C4: Mañana | D4: {=IF(A4="","",SUMPRODUCT(('Detalle Turnos'!$I$3:$I$5028=$A4)*('Detalle Turnos'!$N$3:$N$5028=C4)*'Detalle Turnos'!$L$3:$L$5028))} -> 27 | E4: {=IF(A4="","",SUMPRODUCT(('Detalle Turnos'!$I$3:$I$5028=$A4)*('Detalle Turnos'!$N$3:$N$5028=C4)*'Detalle Turnos'!$K$3:$K$5028))} -> 89.25 | F4: =IFERROR(E4/D4,0) -> 3.3055556 | G4: {=IF(E4="","",IFERROR(SUMPRODUCT(('Facturación 2026'!$A$4:$A$920=$A4)*'Facturación 2026'!$J$4:$J$920)*E4/(SUMPRODUCT(('Caja 1'!$A$4:$A$919=$A4)*'Caja 1'!$E$4:$E$919)+SUMPRODUCT(('Caja 2'!$A$4:$A$920=$A4)*'Caja 2'!$E$4:$E$920)),0))} -> 0 | H4: =IF(E4="","",E4-G4) -> 89.25 | I4: =IF(E4="","",IFERROR(G4/E4,0)) -> 0 | J4: =IF(A4="","",IFERROR(INDEX('Facturación 2026'!$L$4:$L$500,MATCH($A4,'Facturación 2026'!$A$4:$A$500,0)),"")) | L4: Febrero | O4: {=SUMPRODUCT(--(MONTH($A$4:$A$919+0)=ROW()-2),$D$4:$D$919)} -> 711 | P4: {=SUMPRODUCT(--(MONTH($A$4:$A$919+0)=ROW()-2),$E$4:$E$919)} -> 4552.59 | Q4: =IFERROR(P4/O4,0) -> 6.4030802 | R4: {=SUMPRODUCT(--(MONTH($A$4:$A$919+0)=ROW()-2),$G$4:$G$919)} -> 0 | S4: =P4-R4 -> 4552.59 | T4: =IFERROR(R4/P4,0) -> 0
A5: 46024 | B5: =IF(A5="","",CHOOSE(WEEKDAY(A5,2),"Lun","Mar","Mié","Jue","Vie","Sáb","Dom")) -> Vie | C5: Mediodia | D5: {=IF(A5="","",SUMPRODUCT(('Detalle Turnos'!$I$3:$I$5028=$A5)*('Detalle Turnos'!$N$3:$N$5028=C5)*'Detalle Turnos'!$L$3:$L$5028))} -> 9 | E5: {=IF(A5="","",SUMPRODUCT(('Detalle Turnos'!$I$3:$I$5028=$A5)*('Detalle Turnos'!$N$3:$N$5028=C5)*'Detalle Turnos'!$K$3:$K$5028))} -> 90.65 | F5: =IFERROR(E5/D5,0) -> 10.072222 | G5: {=IF(E5="","",IFERROR(SUMPRODUCT(('Facturación 2026'!$A$4:$A$920=$A5)*'Facturación 2026'!$J$4:$J$920)*E5/(SUMPRODUCT(('Caja 1'!$A$4:$A$919=$A5)*'Caja 1'!$E$4:$E$919)+SUMPRODUCT(('Caja 2'!$A$4:$A$920=$A5)*'Caja 2'!$E$4:$E$920)),0))} -> 0 | H5: =IF(E5="","",E5-G5) -> 90.65 | I5: =IF(E5="","",IFERROR(G5/E5,0)) -> 0 | J5: =IF(A5="","",IFERROR(INDEX('Facturación 2026'!$L$4:$L$500,MATCH($A5,'Facturación 2026'!$A$4:$A$500,0)),"")) | L5: Marzo | O5: {=SUMPRODUCT(--(MONTH($A$4:$A$919+0)=ROW()-2),$D$4:$D$919)} -> 593 | P5: {=SUMPRODUCT(--(MONTH($A$4:$A$919+0)=ROW()-2),$E$4:$E$919)} -> 3863.29 | Q5: =IFERROR(P5/O5,0) -> 6.5148229 | R5: {=SUMPRODUCT(--(MONTH($A$4:$A$919+0)=ROW()-2),$G$4:$G$919)} -> 0 | S5: =P5-R5 -> 3863.29 | T5: =IFERROR(R5/P5,0) -> 0
A6: 46025 | B6: =IF(A6="","",CHOOSE(WEEKDAY(A6,2),"Lun","Mar","Mié","Jue","Vie","Sáb","Dom")) -> Sáb | C6: Mañana | D6: {=IF(A6="","",SUMPRODUCT(('Detalle Turnos'!$I$3:$I$5028=$A6)*('Detalle Turnos'!$N$3:$N$5028=C6)*'Detalle Turnos'!$L$3:$L$5028))} -> 24 | E6: {=IF(A6="","",SUMPRODUCT(('Detalle Turnos'!$I$3:$I$5028=$A6)*('Detalle Turnos'!$N$3:$N$5028=C6)*'Detalle Turnos'!$K$3:$K$5028))} -> 106.05 | F6: =IFERROR(E6/D6,0) -> 4.41875 | G6: {=IF(E6="","",IFERROR(SUMPRODUCT(('Facturación 2026'!$A$4:$A$920=$A6)*'Facturación 2026'!$J$4:$J$920)*E6/(SUMPRODUCT(('Caja 1'!$A$4:$A$919=$A6)*'Caja 1'!$E$4:$E$919)+SUMPRODUCT(('Caja 2'!$A$4:$A$920=$A6)*'Caja 2'!$E$4:$E$920)),0))} -> 0 | H6: =IF(E6="","",E6-G6) -> 106.05 | I6: =IF(E6="","",IFERROR(G6/E6,0)) -> 0 | J6: =IF(A6="","",IFERROR(INDEX('Facturación 2026'!$L$4:$L$500,MATCH($A6,'Facturación 2026'!$A$4:$A$500,0)),"")) | L6: Abril | O6: {=SUMPRODUCT(--(MONTH($A$4:$A$919+0)=ROW()-2),$D$4:$D$919)} -> 595 | P6: {=SUMPRODUCT(--(MONTH($A$4:$A$919+0)=ROW()-2),$E$4:$E$919)} -> 5126.65 | Q6: =IFERROR(P6/O6,0) -> 8.6162185 | R6: {=SUMPRODUCT(--(MONTH($A$4:$A$919+0)=ROW()-2),$G$4:$G$919)} -> 0 | S6: =P6-R6 -> 5126.65 | T6: =IFERROR(R6/P6,0) -> 0
A7: 46025 | B7: =IF(A7="","",CHOOSE(WEEKDAY(A7,2),"Lun","Mar","Mié","Jue","Vie","Sáb","Dom")) -> Sáb | C7: Mediodia | D7: {=IF(A7="","",SUMPRODUCT(('Detalle Turnos'!$I$3:$I$5028=$A7)*('Detalle Turnos'!$N$3:$N$5028=C7)*'Detalle Turnos'!$L$3:$L$5028))} -> 4 | E7: {=IF(A7="","",SUMPRODUCT(('Detalle Turnos'!$I$3:$I$5028=$A7)*('Detalle Turnos'!$N$3:$N$5028=C7)*'Detalle Turnos'!$K$3:$K$5028))} -> 5.15 | F7: =IFERROR(E7/D7,0) -> 1.2875 | G7: {=IF(E7="","",IFERROR(SUMPRODUCT(('Facturación 2026'!$A$4:$A$920=$A7)*'Facturación 2026'!$J$4:$J$920)*E7/(SUMPRODUCT(('Caja 1'!$A$4:$A$919=$A7)*'Caja 1'!$E$4:$E$919)+SUMPRODUCT(('Caja 2'!$A$4:$A$920=$A7)*'Caja 2'!$E$4:$E$920)),0))} -> 0 | H7: =IF(E7="","",E7-G7) -> 5.15 | I7: =IF(E7="","",IFERROR(G7/E7,0)) -> 0 | J7: =IF(A7="","",IFERROR(INDEX('Facturación 2026'!$L$4:$L$500,MATCH($A7,'Facturación 2026'!$A$4:$A$500,0)),"")) | L7: TOTAL ANUAL | O7: {=SUMPRODUCT(--(MONTH($A$4:$A$919+0)=ROW()-2),$D$4:$D$919)} -> 23 | P7: {=SUMPRODUCT(--(MONTH($A$4:$A$919+0)=ROW()-2),$E$4:$E$919)} -> 75.3 | Q7: =IFERROR(P7/O7,0) -> 3.273913 | R7: {=SUMPRODUCT(--(MONTH($A$4:$A$919+0)=ROW()-2),$G$4:$G$919)} -> 0 | S7: =P7-R7 -> 75.3 | T7: =IFERROR(R7/P7,0) -> 0
A8: 46026 | B8: =IF(A8="","",CHOOSE(WEEKDAY(A8,2),"Lun","Mar","Mié","Jue","Vie","Sáb","Dom")) -> Dom | C8: Mañana | D8: {=IF(A8="","",SUMPRODUCT(('Detalle Turnos'!$I$3:$I$5028=$A8)*('Detalle Turnos'!$N$3:$N$5028=C8)*'Detalle Turnos'!$L$3:$L$5028))} -> 17 | E8: {=IF(A8="","",SUMPRODUCT(('Detalle Turnos'!$I$3:$I$5028=$A8)*('Detalle Turnos'!$N$3:$N$5028=C8)*'Detalle Turnos'!$K$3:$K$5028))} -> 58.4 | F8: =IFERROR(E8/D8,0) -> 3.4352941 | G8: {=IF(E8="","",IFERROR(SUMPRODUCT(('Facturación 2026'!$A$4:$A$920=$A8)*'Facturación 2026'!$J$4:$J$920)*E8/(SUMPRODUCT(('Caja 1'!$A$4:$A$919=$A8)*'Caja 1'!$E$4:$E$919)+SUMPRODUCT(('Caja 2'!$A$4:$A$920=$A8)*'Caja 2'!$E$4:$E$920)),0))} -> 0 | H8: =IF(E8="","",E8-G8) -> 58.4 | I8: =IF(E8="","",IFERROR(G8/E8,0)) -> 0 | J8: =IF(A8="","",IFERROR(INDEX('Facturación 2026'!$L$4:$L$500,MATCH($A8,'Facturación 2026'!$A$4:$A$500,0)),"")) | L8: Total | O8: =SUM(O3:O7) -> 2681 | P8: =SUM(P3:P7) -> 17108.31 | Q8: =IFERROR(P8/O8,0) -> 6.3813167 | R8: =SUM(R3:R7) -> 0 | S8: =P8-R8 -> 17108.31 | T8: =IFERROR(R8/P8,0) -> 0
A9: 46026 | B9: =IF(A9="","",CHOOSE(WEEKDAY(A9,2),"Lun","Mar","Mié","Jue","Vie","Sáb","Dom")) -> Dom | C9: Mediodia | D9: {=IF(A9="","",SUMPRODUCT(('Detalle Turnos'!$I$3:$I$5028=$A9)*('Detalle Turnos'!$N$3:$N$5028=C9)*'Detalle Turnos'!$L$3:$L$5028))} -> 7 | E9: {=IF(A9="","",SUMPRODUCT(('Detalle Turnos'!$I$3:$I$5028=$A9)*('Detalle Turnos'!$N$3:$N$5028=C9)*'Detalle Turnos'!$K$3:$K$5028))} -> 17.7 | F9: =IFERROR(E9/D9,0) -> 2.5285714 | G9: {=IF(E9="","",IFERROR(SUMPRODUCT(('Facturación 2026'!$A$4:$A$920=$A9)*'Facturación 2026'!$J$4:$J$920)*E9/(SUMPRODUCT(('Caja 1'!$A$4:$A$919=$A9)*'Caja 1'!$E$4:$E$919)+SUMPRODUCT(('Caja 2'!$A$4:$A$920=$A9)*'Caja 2'!$E$4:$E$920)),0))} -> 0 | H9: =IF(E9="","",E9-G9) -> 17.7 | I9: =IF(E9="","",IFERROR(G9/E9,0)) -> 0 | J9: =IF(A9="","",IFERROR(INDEX('Facturación 2026'!$L$4:$L$500,MATCH($A9,'Facturación 2026'!$A$4:$A$500,0)),"")) | L9: ANÁLISIS POR TURNO
A10: 46029 | B10: =IF(A10="","",CHOOSE(WEEKDAY(A10,2),"Lun","Mar","Mié","Jue","Vie","Sáb","Dom")) -> Mié | C10: Mañana | D10: {=IF(A10="","",SUMPRODUCT(('Detalle Turnos'!$I$3:$I$5028=$A10)*('Detalle Turnos'!$N$3:$N$5028=C10)*'Detalle Turnos'!$L$3:$L$5028))} -> 22 | E10: {=IF(A10="","",SUMPRODUCT(('Detalle Turnos'!$I$3:$I$5028=$A10)*('Detalle Turnos'!$N$3:$N$5028=C10)*'Detalle Turnos'!$K$3:$K$5028))} -> 58.35 | F10: =IFERROR(E10/D10,0) -> 2.6522727 | G10: {=IF(E10="","",IFERROR(SUMPRODUCT(('Facturación 2026'!$A$4:$A$920=$A10)*'Facturación 2026'!$J$4:$J$920)*E10/(SUMPRODUCT(('Caja 1'!$A$4:$A$919=$A10)*'Caja 1'!$E$4:$E$919)+SUMPRODUCT(('Caja 2'!$A$4:$A$920=$A10)*'Caja 2'!$E$4:$E$920)),0))} -> 0 | H10: =IF(E10="","",E10-G10) -> 58.35 | I10: =IF(E10="","",IFERROR(G10/E10,0)) -> 0 | J10: =IF(A10="","",IFERROR(INDEX('Facturación 2026'!$L$4:$L$500,MATCH($A10,'Facturación 2026'!$A$4:$A$500,0)),"")) | L10: Turno | O10: Comensales | P10: Facturación € | Q10: % del Total | R10: Ticket Medio € | S10: Margen € | T10: % Coste
A11: 46029 | B11: =IF(A11="","",CHOOSE(WEEKDAY(A11,2),"Lun","Mar","Mié","Jue","Vie","Sáb","Dom")) -> Mié | C11: Mediodia | D11: {=IF(A11="","",SUMPRODUCT(('Detalle Turnos'!$I$3:$I$5028=$A11)*('Detalle Turnos'!$N$3:$N$5028=C11)*'Detalle Turnos'!$L$3:$L$5028))} -> 13 | E11: {=IF(A11="","",SUMPRODUCT(('Detalle Turnos'!$I$3:$I$5028=$A11)*('Detalle Turnos'!$N$3:$N$5028=C11)*'Detalle Turnos'!$K$3:$K$5028))} -> 127.75 | F11: =IFERROR(E11/D11,0) -> 9.8269231 | G11: {=IF(E11="","",IFERROR(SUMPRODUCT(('Facturación 2026'!$A$4:$A$920=$A11)*'Facturación 2026'!$J$4:$J$920)*E11/(SUMPRODUCT(('Caja 1'!$A$4:$A$919=$A11)*'Caja 1'!$E$4:$E$919)+SUMPRODUCT(('Caja 2'!$A$4:$A$920=$A11)*'Caja 2'!$E$4:$E$920)),0))} -> 0 | H11: =IF(E11="","",E11-G11) -> 127.75 | I11: =IF(E11="","",IFERROR(G11/E11,0)) -> 0 | J11: =IF(A11="","",IFERROR(INDEX('Facturación 2026'!$L$4:$L$500,MATCH($A11,'Facturación 2026'!$A$4:$A$500,0)),"")) | L11: Mañana | O11: {=SUMPRODUCT(--($C$4:$C$919="Mañana"),$D$4:$D$919)} -> 1480 | P11: {=SUMPRODUCT(--($C$4:$C$919="Mañana"),$E$4:$E$919)} -> 5052.09 | Q11: =IFERROR(P11/SUM($E$4:$E$919),0) -> 0.29530035 | R11: =IFERROR(P11/O11,0) -> 3.4135743 | S11: {=SUMPRODUCT(--($C$4:$C$919="Mañana"),$H$4:$H$919)} -> 5052.09 | T11: =IFERROR(1-S11/P11,0) -> 0
A12: 46029 | B12: =IF(A12="","",CHOOSE(WEEKDAY(A12,2),"Lun","Mar","Mié","Jue","Vie","Sáb","Dom")) -> Mié | C12: Noche | D12: {=IF(A12="","",SUMPRODUCT(('Detalle Turnos'!$I$3:$I$5028=$A12)*('Detalle Turnos'!$N$3:$N$5028=C12)*'Detalle Turnos'!$L$3:$L$5028))} -> 3 | E12: {=IF(A12="","",SUMPRODUCT(('Detalle Turnos'!$I$3:$I$5028=$A12)*('Detalle Turnos'!$N$3:$N$5028=C12)*'Detalle Turnos'!$K$3:$K$5028))} -> 26.75 | F12: =IFERROR(E12/D12,0) -> 8.9166667 | G12: {=IF(E12="","",IFERROR(SUMPRODUCT(('Facturación 2026'!$A$4:$A$920=$A12)*'Facturación 2026'!$J$4:$J$920)*E12/(SUMPRODUCT(('Caja 1'!$A$4:$A$919=$A12)*'Caja 1'!$E$4:$E$919)+SUMPRODUCT(('Caja 2'!$A$4:$A$920=$A12)*'Caja 2'!$E$4:$E$920)),0))} -> 0 | H12: =IF(E12="","",E12-G12) -> 26.75 | I12: =IF(E12="","",IFERROR(G12/E12,0)) -> 0 | J12: =IF(A12="","",IFERROR(INDEX('Facturación 2026'!$L$4:$L$500,MATCH($A12,'Facturación 2026'!$A$4:$A$500,0)),"")) | L12: Mediodía | O12: {=SUMPRODUCT(--($C$4:$C$919="Mediodia"),$D$4:$D$919)} -> 888 | P12: {=SUMPRODUCT(--($C$4:$C$919="Mediodia"),$E$4:$E$919)} -> 8355.07 | Q12: =IFERROR(P12/SUM($E$4:$E$919),0) -> 0.48836326 | R12: =IFERROR(P12/O12,0) -> 9.4088626 | S12: {=SUMPRODUCT(--($C$4:$C$919="Mediodia"),$H$4:$H$919)} -> 8355.07 | T12: =IFERROR(1-S12/P12,0) -> 0
A13: 46030 | B13: =IF(A13="","",CHOOSE(WEEKDAY(A13,2),"Lun","Mar","Mié","Jue","Vie","Sáb","Dom")) -> Jue | C13: Mañana | D13: {=IF(A13="","",SUMPRODUCT(('Detalle Turnos'!$I$3:$I$5028=$A13)*('Detalle Turnos'!$N$3:$N$5028=C13)*'Detalle Turnos'!$L$3:$L$5028))} -> 12 | E13: {=IF(A13="","",SUMPRODUCT(('Detalle Turnos'!$I$3:$I$5028=$A13)*('Detalle Turnos'!$N$3:$N$5028=C13)*'Detalle Turnos'!$K$3:$K$5028))} -> 72.9 | F13: =IFERROR(E13/D13,0) -> 6.075 | G13: {=IF(E13="","",IFERROR(SUMPRODUCT(('Facturación 2026'!$A$4:$A$920=$A13)*'Facturación 2026'!$J$4:$J$920)*E13/(SUMPRODUCT(('Caja 1'!$A$4:$A$919=$A13)*'Caja 1'!$E$4:$E$919)+SUMPRODUCT(('Caja 2'!$A$4:$A$920=$A13)*'Caja 2'!$E$4:$E$920)),0))} -> 0 | H13: =IF(E13="","",E13-G13) -> 72.9 | I13: =IF(E13="","",IFERROR(G13/E13,0)) -> 0 | J13: =IF(A13="","",IFERROR(INDEX('Facturación 2026'!$L$4:$L$500,MATCH($A13,'Facturación 2026'!$A$4:$A$500,0)),"")) | L13: Noche | O13: {=SUMPRODUCT(--($C$4:$C$919="Noche"),$D$4:$D$919)} -> 313 | P13: {=SUMPRODUCT(--($C$4:$C$919="Noche"),$E$4:$E$919)} -> 3701.15 | Q13: =IFERROR(P13/SUM($E$4:$E$919),0) -> 0.21633639 | R13: =IFERROR(P13/O13,0) -> 11.82476 | S13: {=SUMPRODUCT(--($C$4:$C$919="Noche"),$H$4:$H$919)} -> 3701.15 | T13: =IFERROR(1-S13/P13,0) -> 0
A14: 46030 | B14: =IF(A14="","",CHOOSE(WEEKDAY(A14,2),"Lun","Mar","Mié","Jue","Vie","Sáb","Dom")) -> Jue | C14: Mediodia | D14: {=IF(A14="","",SUMPRODUCT(('Detalle Turnos'!$I$3:$I$5028=$A14)*('Detalle Turnos'!$N$3:$N$5028=C14)*'Detalle Turnos'!$L$3:$L$5028))} -> 18 | E14: {=IF(A14="","",SUMPRODUCT(('Detalle Turnos'!$I$3:$I$5028=$A14)*('Detalle Turnos'!$N$3:$N$5028=C14)*'Detalle Turnos'!$K$3:$K$5028))} -> 137.84 | F14: =IFERROR(E14/D14,0) -> 7.6577778 | G14: {=IF(E14="","",IFERROR(SUMPRODUCT(('Facturación 2026'!$A$4:$A$920=$A14)*'Facturación 2026'!$J$4:$J$920)*E14/(SUMPRODUCT(('Caja 1'!$A$4:$A$919=$A14)*'Caja 1'!$E$4:$E$919)+SUMPRODUCT(('Caja 2'!$A$4:$A$920=$A14)*'Caja 2'!$E$4:$E$920)),0))} -> 0 | H14: =IF(E14="","",E14-G14) -> 137.84 | I14: =IF(E14="","",IFERROR(G14/E14,0)) -> 0 | J14: =IF(A14="","",IFERROR(INDEX('Facturación 2026'!$L$4:$L$500,MATCH($A14,'Facturación 2026'!$A$4:$A$500,0)),"")) | L14: Total | O14: =SUM(O11:O13) -> 2681 | P14: =SUM(P11:P13) -> 17108.31 | Q14: =SUM(Q11:Q13) -> 1 | R14: =IFERROR(P14/O14,0) -> 6.3813167 | S14: =SUM(S11:S13) -> 17108.31 | T14: =IFERROR(1-S14/P14,0) -> 0
A15: 46030 | B15: =IF(A15="","",CHOOSE(WEEKDAY(A15,2),"Lun","Mar","Mié","Jue","Vie","Sáb","Dom")) -> Jue | C15: Noche | D15: {=IF(A15="","",SUMPRODUCT(('Detalle Turnos'!$I$3:$I$5028=$A15)*('Detalle Turnos'!$N$3:$N$5028=C15)*'Detalle Turnos'!$L$3:$L$5028))} -> 2 | E15: {=IF(A15="","",SUMPRODUCT(('Detalle Turnos'!$I$3:$I$5028=$A15)*('Detalle Turnos'!$N$3:$N$5028=C15)*'Detalle Turnos'!$K$3:$K$5028))} -> 3.4 | F15: =IFERROR(E15/D15,0) -> 1.7 | G15: {=IF(E15="","",IFERROR(SUMPRODUCT(('Facturación 2026'!$A$4:$A$920=$A15)*'Facturación 2026'!$J$4:$J$920)*E15/(SUMPRODUCT(('Caja 1'!$A$4:$A$919=$A15)*'Caja 1'!$E$4:$E$919)+SUMPRODUCT(('Caja 2'!$A$4:$A$920=$A15)*'Caja 2'!$E$4:$E$920)),0))} -> 0 | H15: =IF(E15="","",E15-G15) -> 3.4 | I15: =IF(E15="","",IFERROR(G15/E15,0)) -> 0 | J15: =IF(A15="","",IFERROR(INDEX('Facturación 2026'!$L$4:$L$500,MATCH($A15,'Facturación 2026'!$A$4:$A$500,0)),"")) | L15: según hoja Horarios.
A16: 46031 | B16: =IF(A16="","",CHOOSE(WEEKDAY(A16,2),"Lun","Mar","Mié","Jue","Vie","Sáb","Dom")) -> Vie | C16: Mañana | D16: {=IF(A16="","",SUMPRODUCT(('Detalle Turnos'!$I$3:$I$5028=$A16)*('Detalle Turnos'!$N$3:$N$5028=C16)*'Detalle Turnos'!$L$3:$L$5028))} -> 18 | E16: {=IF(A16="","",SUMPRODUCT(('Detalle Turnos'!$I$3:$I$5028=$A16)*('Detalle Turnos'!$N$3:$N$5028=C16)*'Detalle Turnos'!$K$3:$K$5028))} -> 96.35 | F16: =IFERROR(E16/D16,0) -> 5.3527778 | G16: {=IF(E16="","",IFERROR(SUMPRODUCT(('Facturación 2026'!$A$4:$A$920=$A16)*'Facturación 2026'!$J$4:$J$920)*E16/(SUMPRODUCT(('Caja 1'!$A$4:$A$919=$A16)*'Caja 1'!$E$4:$E$919)+SUMPRODUCT(('Caja 2'!$A$4:$A$920=$A16)*'Caja 2'!$E$4:$E$920)),0))} -> 0 | H16: =IF(E16="","",E16-G16) -> 96.35 | I16: =IF(E16="","",IFERROR(G16/E16,0)) -> 0 | J16: =IF(A16="","",IFERROR(INDEX('Facturación 2026'!$L$4:$L$500,MATCH($A16,'Facturación 2026'!$A$4:$A$500,0)),"")) | L16: Alertar si >12h/turno.
A17: 46031 | B17: =IF(A17="","",CHOOSE(WEEKDAY(A17,2),"Lun","Mar","Mié","Jue","Vie","Sáb","Dom")) -> Vie | C17: Mediodia | D17: {=IF(A17="","",SUMPRODUCT(('Detalle Turnos'!$I$3:$I$5028=$A17)*('Detalle Turnos'!$N$3:$N$5028=C17)*'Detalle Turnos'!$L$3:$L$5028))} -> 11 | E17: {=IF(A17="","",SUMPRODUCT(('Detalle Turnos'!$I$3:$I$5028=$A17)*('Detalle Turnos'!$N$3:$N$5028=C17)*'Detalle Turnos'!$K$3:$K$5028))} -> 130.79 | F17: =IFERROR(E17/D17,0) -> 11.89 | G17: {=IF(E17="","",IFERROR(SUMPRODUCT(('Facturación 2026'!$A$4:$A$920=$A17)*'Facturación 2026'!$J$4:$J$920)*E17/(SUMPRODUCT(('Caja 1'!$A$4:$A$919=$A17)*'Caja 1'!$E$4:$E$919)+SUMPRODUCT(('Caja 2'!$A$4:$A$920=$A17)*'Caja 2'!$E$4:$E$920)),0))} -> 0 | H17: =IF(E17="","",E17-G17) -> 130.79 | I17: =IF(E17="","",IFERROR(G17/E17,0)) -> 0 | J17: =IF(A17="","",IFERROR(INDEX('Facturación 2026'!$L$4:$L$500,MATCH($A17,'Facturación 2026'!$A$4:$A$500,0)),""))
A18: 46032 | B18: =IF(A18="","",CHOOSE(WEEKDAY(A18,2),"Lun","Mar","Mié","Jue","Vie","Sáb","Dom")) -> Sáb | C18: Mañana | D18: {=IF(A18="","",SUMPRODUCT(('Detalle Turnos'!$I$3:$I$5028=$A18)*('Detalle Turnos'!$N$3:$N$5028=C18)*'Detalle Turnos'!$L$3:$L$5028))} -> 29 | E18: {=IF(A18="","",SUMPRODUCT(('Detalle Turnos'!$I$3:$I$5028=$A18)*('Detalle Turnos'!$N$3:$N$5028=C18)*'Detalle Turnos'!$K$3:$K$5028))} -> 88.85 | F18: =IFERROR(E18/D18,0) -> 3.0637931 | G18: {=IF(E18="","",IFERROR(SUMPRODUCT(('Facturación 2026'!$A$4:$A$920=$A18)*'Facturación 2026'!$J$4:$J$920)*E18/(SUMPRODUCT(('Caja 1'!$A$4:$A$919=$A18)*'Caja 1'!$E$4:$E$919)+SUMPRODUCT(('Caja 2'!$A$4:$A$920=$A18)*'Caja 2'!$E$4:$E$920)),0))} -> 0 | H18: =IF(E18="","",E18-G18) -> 88.85 | I18: =IF(E18="","",IFERROR(G18/E18,0)) -> 0 | J18: =IF(A18="","",IFERROR(INDEX('Facturación 2026'!$L$4:$L$500,MATCH($A18,'Facturación 2026'!$A$4:$A$500,0)),""))
A19: 46032 | B19: =IF(A19="","",CHOOSE(WEEKDAY(A19,2),"Lun","Mar","Mié","Jue","Vie","Sáb","Dom")) -> Sáb | C19: Mediodia | D19: {=IF(A19="","",SUMPRODUCT(('Detalle Turnos'!$I$3:$I$5028=$A19)*('Detalle Turnos'!$N$3:$N$5028=C19)*'Detalle Turnos'!$L$3:$L$5028))} -> 5 | E19: {=IF(A19="","",SUMPRODUCT(('Detalle Turnos'!$I$3:$I$5028=$A19)*('Detalle Turnos'!$N$3:$N$5028=C19)*'Detalle Turnos'!$K$3:$K$5028))} -> 38.8 | F19: =IFERROR(E19/D19,0) -> 7.76 | G19: {=IF(E19="","",IFERROR(SUMPRODUCT(('Facturación 2026'!$A$4:$A$920=$A19)*'Facturación 2026'!$J$4:$J$920)*E19/(SUMPRODUCT(('Caja 1'!$A$4:$A$919=$A19)*'Caja 1'!$E$4:$E$919)+SUMPRODUCT(('Caja 2'!$A$4:$A$920=$A19)*'Caja 2'!$E$4:$E$920)),0))} -> 0 | H19: =IF(E19="","",E19-G19) -> 38.8 | I19: =IF(E19="","",IFERROR(G19/E19,0)) -> 0 | J19: =IF(A19="","",IFERROR(INDEX('Facturación 2026'!$L$4:$L$500,MATCH($A19,'Facturación 2026'!$A$4:$A$500,0)),""))
A20: 46033 | B20: =IF(A20="","",CHOOSE(WEEKDAY(A20,2),"Lun","Mar","Mié","Jue","Vie","Sáb","Dom")) -> Dom | C20: Mañana | D20: {=IF(A20="","",SUMPRODUCT(('Detalle Turnos'!$I$3:$I$5028=$A20)*('Detalle Turnos'!$N$3:$N$5028=C20)*'Detalle Turnos'!$L$3:$L$5028))} -> 7 | E20: {=IF(A20="","",SUMPRODUCT(('Detalle Turnos'!$I$3:$I$5028=$A20)*('Detalle Turnos'!$N$3:$N$5028=C20)*'Detalle Turnos'!$K$3:$K$5028))} -> 28.65 | F20: =IFERROR(E20/D20,0) -> 4.0928571 | G20: {=IF(E20="","",IFERROR(SUMPRODUCT(('Facturación 2026'!$A$4:$A$920=$A20)*'Facturación 2026'!$J$4:$J$920)*E20/(SUMPRODUCT(('Caja 1'!$A$4:$A$919=$A20)*'Caja 1'!$E$4:$E$919)+SUMPRODUCT(('Caja 2'!$A$4:$A$920=$A20)*'Caja 2'!$E$4:$E$920)),0))} -> 0 | H20: =IF(E20="","",E20-G20) -> 28.65 | I20: =IF(E20="","",IFERROR(G20/E20,0)) -> 0 | J20: =IF(A20="","",IFERROR(INDEX('Facturación 2026'!$L$4:$L$500,MATCH($A20,'Facturación 2026'!$A$4:$A$500,0)),""))
A21: 46033 | B21: =IF(A21="","",CHOOSE(WEEKDAY(A21,2),"Lun","Mar","Mié","Jue","Vie","Sáb","Dom")) -> Dom | C21: Mediodia | D21: {=IF(A21="","",SUMPRODUCT(('Detalle Turnos'!$I$3:$I$5028=$A21)*('Detalle Turnos'!$N$3:$N$5028=C21)*'Detalle Turnos'!$L$3:$L$5028))} -> 6 | E21: {=IF(A21="","",SUMPRODUCT(('Detalle Turnos'!$I$3:$I$5028=$A21)*('Detalle Turnos'!$N$3:$N$5028=C21)*'Detalle Turnos'!$K$3:$K$5028))} -> 38.35 | F21: =IFERROR(E21/D21,0) -> 6.3916667 | G21: {=IF(E21="","",IFERROR(SUMPRODUCT(('Facturación 2026'!$A$4:$A$920=$A21)*'Facturación 2026'!$J$4:$J$920)*E21/(SUMPRODUCT(('Caja 1'!$A$4:$A$919=$A21)*'Caja 1'!$E$4:$E$919)+SUMPRODUCT(('Caja 2'!$A$4:$A$920=$A21)*'Caja 2'!$E$4:$E$920)),0))} -> 0 | H21: =IF(E21="","",E21-G21) -> 38.35 | I21: =IF(E21="","",IFERROR(G21/E21,0)) -> 0 | J21: =IF(A21="","",IFERROR(INDEX('Facturación 2026'!$L$4:$L$500,MATCH($A21,'Facturación 2026'!$A$4:$A$500,0)),""))
A22: 46036 | B22: =IF(A22="","",CHOOSE(WEEKDAY(A22,2),"Lun","Mar","Mié","Jue","Vie","Sáb","Dom")) -> Mié | C22: Mañana | D22: {=IF(A22="","",SUMPRODUCT(('Detalle Turnos'!$I$3:$I$5028=$A22)*('Detalle Turnos'!$N$3:$N$5028=C22)*'Detalle Turnos'!$L$3:$L$5028))} -> 32 | E22: {=IF(A22="","",SUMPRODUCT(('Detalle Turnos'!$I$3:$I$5028=$A22)*('Detalle Turnos'!$N$3:$N$5028=C22)*'Detalle Turnos'!$K$3:$K$5028))} -> 82.85 | F22: =IFERROR(E22/D22,0) -> 2.5890625 | G22: {=IF(E22="","",IFERROR(SUMPRODUCT(('Facturación 2026'!$A$4:$A$920=$A22)*'Facturación 2026'!$J$4:$J$920)*E22/(SUMPRODUCT(('Caja 1'!$A$4:$A$919=$A22)*'Caja 1'!$E$4:$E$919)+SUMPRODUCT(('Caja 2'!$A$4:$A$920=$A22)*'Caja 2'!$E$4:$E$920)),0))} -> 0 | H22: =IF(E22="","",E22-G22) -> 82.85 | I22: =IF(E22="","",IFERROR(G22/E22,0)) -> 0 | J22: =IF(A22="","",IFERROR(INDEX('Facturación 2026'!$L$4:$L$500,MATCH($A22,'Facturación 2026'!$A$4:$A$500,0)),""))
A23: 46036 | B23: =IF(A23="","",CHOOSE(WEEKDAY(A23,2),"Lun","Mar","Mié","Jue","Vie","Sáb","Dom")) -> Mié | C23: Mediodia | D23: {=IF(A23="","",SUMPRODUCT(('Detalle Turnos'!$I$3:$I$5028=$A23)*('Detalle Turnos'!$N$3:$N$5028=C23)*'Detalle Turnos'!$L$3:$L$5028))} -> 15 | E23: {=IF(A23="","",SUMPRODUCT(('Detalle Turnos'!$I$3:$I$5028=$A23)*('Detalle Turnos'!$N$3:$N$5028=C23)*'Detalle Turnos'!$K$3:$K$5028))} -> 99.3 | F23: =IFERROR(E23/D23,0) -> 6.62 | G23: {=IF(E23="","",IFERROR(SUMPRODUCT(('Facturación 2026'!$A$4:$A$920=$A23)*'Facturación 2026'!$J$4:$J$920)*E23/(SUMPRODUCT(('Caja 1'!$A$4:$A$919=$A23)*'Caja 1'!$E$4:$E$919)+SUMPRODUCT(('Caja 2'!$A$4:$A$920=$A23)*'Caja 2'!$E$4:$E$920)),0))} -> 0 | H23: =IF(E23="","",E23-G23) -> 99.3 | I23: =IF(E23="","",IFERROR(G23/E23,0)) -> 0 | J23: =IF(A23="","",IFERROR(INDEX('Facturación 2026'!$L$4:$L$500,MATCH($A23,'Facturación 2026'!$A$4:$A$500,0)),""))
A24: 46036 | B24: =IF(A24="","",CHOOSE(WEEKDAY(A24,2),"Lun","Mar","Mié","Jue","Vie","Sáb","Dom")) -> Mié | C24: Noche | D24: {=IF(A24="","",SUMPRODUCT(('Detalle Turnos'!$I$3:$I$5028=$A24)*('Detalle Turnos'!$N$3:$N$5028=C24)*'Detalle Turnos'!$L$3:$L$5028))} -> 3 | E24: {=IF(A24="","",SUMPRODUCT(('Detalle Turnos'!$I$3:$I$5028=$A24)*('Detalle Turnos'!$N$3:$N$5028=C24)*'Detalle Turnos'!$K$3:$K$5028))} -> 16.1 | F24: =IFERROR(E24/D24,0) -> 5.3666667 | G24: {=IF(E24="","",IFERROR(SUMPRODUCT(('Facturación 2026'!$A$4:$A$920=$A24)*'Facturación 2026'!$J$4:$J$920)*E24/(SUMPRODUCT(('Caja 1'!$A$4:$A$919=$A24)*'Caja 1'!$E$4:$E$919)+SUMPRODUCT(('Caja 2'!$A$4:$A$920=$A24)*'Caja 2'!$E$4:$E$920)),0))} -> 0 | H24: =IF(E24="","",E24-G24) -> 16.1 | I24: =IF(E24="","",IFERROR(G24/E24,0)) -> 0 | J24: =IF(A24="","",IFERROR(INDEX('Facturación 2026'!$L$4:$L$500,MATCH($A24,'Facturación 2026'!$A$4:$A$500,0)),""))
A25: 46037 | B25: =IF(A25="","",CHOOSE(WEEKDAY(A25,2),"Lun","Mar","Mié","Jue","Vie","Sáb","Dom")) -> Jue | C25: Mañana | D25: {=IF(A25="","",SUMPRODUCT(('Detalle Turnos'!$I$3:$I$5028=$A25)*('Detalle Turnos'!$N$3:$N$5028=C25)*'Detalle Turnos'!$L$3:$L$5028))} -> 15 | E25: {=IF(A25="","",SUMPRODUCT(('Detalle Turnos'!$I$3:$I$5028=$A25)*('Detalle Turnos'!$N$3:$N$5028=C25)*'Detalle Turnos'!$K$3:$K$5028))} -> 66.45 | F25: =IFERROR(E25/D25,0) -> 4.43 | G25: {=IF(E25="","",IFERROR(SUMPRODUCT(('Facturación 2026'!$A$4:$A$920=$A25)*'Facturación 2026'!$J$4:$J$920)*E25/(SUMPRODUCT(('Caja 1'!$A$4:$A$919=$A25)*'Caja 1'!$E$4:$E$919)+SUMPRODUCT(('Caja 2'!$A$4:$A$920=$A25)*'Caja 2'!$E$4:$E$920)),0))} -> 0 | H25: =IF(E25="","",E25-G25) -> 66.45 | I25: =IF(E25="","",IFERROR(G25/E25,0)) -> 0 | J25: =IF(A25="","",IFERROR(INDEX('Facturación 2026'!$L$4:$L$500,MATCH($A25,'Facturación 2026'!$A$4:$A$500,0)),""))
A26: 46037 | B26: =IF(A26="","",CHOOSE(WEEKDAY(A26,2),"Lun","Mar","Mié","Jue","Vie","Sáb","Dom")) -> Jue | C26: Mediodia | D26: {=IF(A26="","",SUMPRODUCT(('Detalle Turnos'!$I$3:$I$5028=$A26)*('Detalle Turnos'!$N$3:$N$5028=C26)*'Detalle Turnos'!$L$3:$L$5028))} -> 5 | E26: {=IF(A26="","",SUMPRODUCT(('Detalle Turnos'!$I$3:$I$5028=$A26)*('Detalle Turnos'!$N$3:$N$5028=C26)*'Detalle Turnos'!$K$3:$K$5028))} -> 11.7 | F26: =IFERROR(E26/D26,0) -> 2.34 | G26: {=IF(E26="","",IFERROR(SUMPRODUCT(('Facturación 2026'!$A$4:$A$920=$A26)*'Facturación 2026'!$J$4:$J$920)*E26/(SUMPRODUCT(('Caja 1'!$A$4:$A$919=$A26)*'Caja 1'!$E$4:$E$919)+SUMPRODUCT(('Caja 2'!$A$4:$A$920=$A26)*'Caja 2'!$E$4:$E$920)),0))} -> 0 | H26: =IF(E26="","",E26-G26) -> 11.7 | I26: =IF(E26="","",IFERROR(G26/E26,0)) -> 0 | J26: =IF(A26="","",IFERROR(INDEX('Facturación 2026'!$L$4:$L$500,MATCH($A26,'Facturación 2026'!$A$4:$A$500,0)),""))
A27: 46037 | B27: =IF(A27="","",CHOOSE(WEEKDAY(A27,2),"Lun","Mar","Mié","Jue","Vie","Sáb","Dom")) -> Jue | C27: Noche | D27: {=IF(A27="","",SUMPRODUCT(('Detalle Turnos'!$I$3:$I$5028=$A27)*('Detalle Turnos'!$N$3:$N$5028=C27)*'Detalle Turnos'!$L$3:$L$5028))} -> 1 | E27: {=IF(A27="","",SUMPRODUCT(('Detalle Turnos'!$I$3:$I$5028=$A27)*('Detalle Turnos'!$N$3:$N$5028=C27)*'Detalle Turnos'!$K$3:$K$5028))} -> 6.1 | F27: =IFERROR(E27/D27,0) -> 6.1 | G27: {=IF(E27="","",IFERROR(SUMPRODUCT(('Facturación 2026'!$A$4:$A$920=$A27)*'Facturación 2026'!$J$4:$J$920)*E27/(SUMPRODUCT(('Caja 1'!$A$4:$A$919=$A27)*'Caja 1'!$E$4:$E$919)+SUMPRODUCT(('Caja 2'!$A$4:$A$920=$A27)*'Caja 2'!$E$4:$E$920)),0))} -> 0 | H27: =IF(E27="","",E27-G27) -> 6.1 | I27: =IF(E27="","",IFERROR(G27/E27,0)) -> 0 | J27: =IF(A27="","",IFERROR(INDEX('Facturación 2026'!$L$4:$L$500,MATCH($A27,'Facturación 2026'!$A$4:$A$500,0)),""))
A28: 46038 | B28: =IF(A28="","",CHOOSE(WEEKDAY(A28,2),"Lun","Mar","Mié","Jue","Vie","Sáb","Dom")) -> Vie | C28: Mañana | D28: {=IF(A28="","",SUMPRODUCT(('Detalle Turnos'!$I$3:$I$5028=$A28)*('Detalle Turnos'!$N$3:$N$5028=C28)*'Detalle Turnos'!$L$3:$L$5028))} -> 15 | E28: {=IF(A28="","",SUMPRODUCT(('Detalle Turnos'!$I$3:$I$5028=$A28)*('Detalle Turnos'!$N$3:$N$5028=C28)*'Detalle Turnos'!$K$3:$K$5028))} -> 41.3 | F28: =IFERROR(E28/D28,0) -> 2.7533333 | G28: {=IF(E28="","",IFERROR(SUMPRODUCT(('Facturación 2026'!$A$4:$A$920=$A28)*'Facturación 2026'!$J$4:$J$920)*E28/(SUMPRODUCT(('Caja 1'!$A$4:$A$919=$A28)*'Caja 1'!$E$4:$E$919)+SUMPRODUCT(('Caja 2'!$A$4:$A$920=$A28)*'Caja 2'!$E$4:$E$920)),0))} -> 0 | H28: =IF(E28="","",E28-G28) -> 41.3 | I28: =IF(E28="","",IFERROR(G28/E28,0)) -> 0 | J28: =IF(A28="","",IFERROR(INDEX('Facturación 2026'!$L$4:$L$500,MATCH($A28,'Facturación 2026'!$A$4:$A$500,0)),""))
... A171: 46134 | B171: =IF(A171="","",CHOOSE(WEEKDAY(A171,2),"Lun","Mar","Mié","Jue","Vie","Sáb","Dom")) -> Mié | C171: Noche | D171: {=IF(A171="","",SUMPRODUCT(('Detalle Turnos'!$I$3:$I$5028=$A171)*('Detalle Turnos'!$N$3:$N$5028=C171)*'Detalle Turnos'!$L$3:$L$5028))} -> 7 | E171: {=IF(A171="","",SUMPRODUCT(('Detalle Turnos'!$I$3:$I$5028=$A171)*('Detalle Turnos'!$N$3:$N$5028=C171)*'Detalle Turnos'!$K$3:$K$5028))} -> 118.25 | F171: =IFERROR(E171/D171,0) -> 16.892857 | G171: {=IF(E171="","",IFERROR(SUMPRODUCT(('Facturación 2026'!$A$4:$A$920=$A171)*'Facturación 2026'!$J$4:$J$920)*E171/(SUMPRODUCT(('Caja 1'!$A$4:$A$919=$A171)*'Caja 1'!$E$4:$E$919)+SUMPRODUCT(('Caja 2'!$A$4:$A$920=$A171)*'Caja 2'!$E$4:$E$920)),0))} -> 0 | H171: =IF(E171="","",E171-G171) -> 118.25 | I171: =IF(E171="","",IFERROR(G171/E171,0)) -> 0 | J171: =IF(A171="","",IFERROR(INDEX('Facturación 2026'!$L$4:$L$500,MATCH($A171,'Facturación 2026'!$A$4:$A$500,0)),""))
A172: 46135 | B172: =IF(A172="","",CHOOSE(WEEKDAY(A172,2),"Lun","Mar","Mié","Jue","Vie","Sáb","Dom")) -> Jue | C172: Mañana | D172: {=IF(A172="","",SUMPRODUCT(('Detalle Turnos'!$I$3:$I$5028=$A172)*('Detalle Turnos'!$N$3:$N$5028=C172)*'Detalle Turnos'!$L$3:$L$5028))} -> 15 | E172: {=IF(A172="","",SUMPRODUCT(('Detalle Turnos'!$I$3:$I$5028=$A172)*('Detalle Turnos'!$N$3:$N$5028=C172)*'Detalle Turnos'!$K$3:$K$5028))} -> 65.95 | F172: =IFERROR(E172/D172,0) -> 4.3966667 | G172: {=IF(E172="","",IFERROR(SUMPRODUCT(('Facturación 2026'!$A$4:$A$920=$A172)*'Facturación 2026'!$J$4:$J$920)*E172/(SUMPRODUCT(('Caja 1'!$A$4:$A$919=$A172)*'Caja 1'!$E$4:$E$919)+SUMPRODUCT(('Caja 2'!$A$4:$A$920=$A172)*'Caja 2'!$E$4:$E$920)),0))} -> 0 | H172: =IF(E172="","",E172-G172) -> 65.95 | I172: =IF(E172="","",IFERROR(G172/E172,0)) -> 0 | J172: Sant Jordi
A173: 46135 | B173: =IF(A173="","",CHOOSE(WEEKDAY(A173,2),"Lun","Mar","Mié","Jue","Vie","Sáb","Dom")) -> Jue | C173: Mediodia | D173: {=IF(A173="","",SUMPRODUCT(('Detalle Turnos'!$I$3:$I$5028=$A173)*('Detalle Turnos'!$N$3:$N$5028=C173)*'Detalle Turnos'!$L$3:$L$5028))} -> 27 | E173: {=IF(A173="","",SUMPRODUCT(('Detalle Turnos'!$I$3:$I$5028=$A173)*('Detalle Turnos'!$N$3:$N$5028=C173)*'Detalle Turnos'!$K$3:$K$5028))} -> 295.7 | F173: =IFERROR(E173/D173,0) -> 10.951852 | G173: {=IF(E173="","",IFERROR(SUMPRODUCT(('Facturación 2026'!$A$4:$A$920=$A173)*'Facturación 2026'!$J$4:$J$920)*E173/(SUMPRODUCT(('Caja 1'!$A$4:$A$919=$A173)*'Caja 1'!$E$4:$E$919)+SUMPRODUCT(('Caja 2'!$A$4:$A$920=$A173)*'Caja 2'!$E$4:$E$920)),0))} -> 0 | H173: =IF(E173="","",E173-G173) -> 295.7 | I173: =IF(E173="","",IFERROR(G173/E173,0)) -> 0 | J173: Sant Jordi
A174: 46136 | B174: =IF(A174="","",CHOOSE(WEEKDAY(A174,2),"Lun","Mar","Mié","Jue","Vie","Sáb","Dom")) -> Vie | C174: Noche | D174: {=IF(A174="","",SUMPRODUCT(('Detalle Turnos'!$I$3:$I$5028=$A174)*('Detalle Turnos'!$N$3:$N$5028=C174)*'Detalle Turnos'!$L$3:$L$5028))} -> 19 | E174: {=IF(A174="","",SUMPRODUCT(('Detalle Turnos'!$I$3:$I$5028=$A174)*('Detalle Turnos'!$N$3:$N$5028=C174)*'Detalle Turnos'!$K$3:$K$5028))} -> 241.8 | F174: =IFERROR(E174/D174,0) -> 12.726316 | G174: {=IF(E174="","",IFERROR(SUMPRODUCT(('Facturación 2026'!$A$4:$A$920=$A174)*'Facturación 2026'!$J$4:$J$920)*E174/(SUMPRODUCT(('Caja 1'!$A$4:$A$919=$A174)*'Caja 1'!$E$4:$E$919)+SUMPRODUCT(('Caja 2'!$A$4:$A$920=$A174)*'Caja 2'!$E$4:$E$920)),0))} -> 0 | H174: =IF(E174="","",E174-G174) -> 241.8 | I174: =IF(E174="","",IFERROR(G174/E174,0)) -> 0 | J174: =IF(A174="","",IFERROR(INDEX('Facturación 2026'!$L$4:$L$500,MATCH($A174,'Facturación 2026'!$A$4:$A$500,0)),""))
A175: 46136 | B175: =IF(A175="","",CHOOSE(WEEKDAY(A175,2),"Lun","Mar","Mié","Jue","Vie","Sáb","Dom")) -> Vie | C175: Mediodia | D175: {=IF(A175="","",SUMPRODUCT(('Detalle Turnos'!$I$3:$I$5028=$A175)*('Detalle Turnos'!$N$3:$N$5028=C175)*'Detalle Turnos'!$L$3:$L$5028))} -> 8 | E175: {=IF(A175="","",SUMPRODUCT(('Detalle Turnos'!$I$3:$I$5028=$A175)*('Detalle Turnos'!$N$3:$N$5028=C175)*'Detalle Turnos'!$K$3:$K$5028))} -> 41.7 | F175: =IFERROR(E175/D175,0) -> 5.2125 | G175: {=IF(E175="","",IFERROR(SUMPRODUCT(('Facturación 2026'!$A$4:$A$920=$A175)*'Facturación 2026'!$J$4:$J$920)*E175/(SUMPRODUCT(('Caja 1'!$A$4:$A$919=$A175)*'Caja 1'!$E$4:$E$919)+SUMPRODUCT(('Caja 2'!$A$4:$A$920=$A175)*'Caja 2'!$E$4:$E$920)),0))} -> 0 | H175: =IF(E175="","",E175-G175) -> 41.7 | I175: =IF(E175="","",IFERROR(G175/E175,0)) -> 0 | J175: =IF(A175="","",IFERROR(INDEX('Facturación 2026'!$L$4:$L$500,MATCH($A175,'Facturación 2026'!$A$4:$A$500,0)),""))
A176: 46137 | B176: =IF(A176="","",CHOOSE(WEEKDAY(A176,2),"Lun","Mar","Mié","Jue","Vie","Sáb","Dom")) -> Sáb | C176: Mediodia | D176: {=IF(A176="","",SUMPRODUCT(('Detalle Turnos'!$I$3:$I$5028=$A176)*('Detalle Turnos'!$N$3:$N$5028=C176)*'Detalle Turnos'!$L$3:$L$5028))} -> 19 | E176: {=IF(A176="","",SUMPRODUCT(('Detalle Turnos'!$I$3:$I$5028=$A176)*('Detalle Turnos'!$N$3:$N$5028=C176)*'Detalle Turnos'!$K$3:$K$5028))} -> 99 | F176: =IFERROR(E176/D176,0) -> 5.2105263 | G176: {=IF(E176="","",IFERROR(SUMPRODUCT(('Facturación 2026'!$A$4:$A$920=$A176)*'Facturación 2026'!$J$4:$J$920)*E176/(SUMPRODUCT(('Caja 1'!$A$4:$A$919=$A176)*'Caja 1'!$E$4:$E$919)+SUMPRODUCT(('Caja 2'!$A$4:$A$920=$A176)*'Caja 2'!$E$4:$E$920)),0))} -> 0 | H176: =IF(E176="","",E176-G176) -> 99 | I176: =IF(E176="","",IFERROR(G176/E176,0)) -> 0 | J176: =IF(A176="","",IFERROR(INDEX('Facturación 2026'!$L$4:$L$500,MATCH($A176,'Facturación 2026'!$A$4:$A$500,0)),""))
A177: 46137 | B177: =IF(A177="","",CHOOSE(WEEKDAY(A177,2),"Lun","Mar","Mié","Jue","Vie","Sáb","Dom")) -> Sáb | C177: Mañana | D177: {=IF(A177="","",SUMPRODUCT(('Detalle Turnos'!$I$3:$I$5028=$A177)*('Detalle Turnos'!$N$3:$N$5028=C177)*'Detalle Turnos'!$L$3:$L$5028))} -> 26 | E177: {=IF(A177="","",SUMPRODUCT(('Detalle Turnos'!$I$3:$I$5028=$A177)*('Detalle Turnos'!$N$3:$N$5028=C177)*'Detalle Turnos'!$K$3:$K$5028))} -> 99.2 | F177: =IFERROR(E177/D177,0) -> 3.8153846 | G177: {=IF(E177="","",IFERROR(SUMPRODUCT(('Facturación 2026'!$A$4:$A$920=$A177)*'Facturación 2026'!$J$4:$J$920)*E177/(SUMPRODUCT(('Caja 1'!$A$4:$A$919=$A177)*'Caja 1'!$E$4:$E$919)+SUMPRODUCT(('Caja 2'!$A$4:$A$920=$A177)*'Caja 2'!$E$4:$E$920)),0))} -> 0 | H177: =IF(E177="","",E177-G177) -> 99.2 | I177: =IF(E177="","",IFERROR(G177/E177,0)) -> 0 | J177: =IF(A177="","",IFERROR(INDEX('Facturación 2026'!$L$4:$L$500,MATCH($A177,'Facturación 2026'!$A$4:$A$500,0)),""))
A178: 46138 | B178: =IF(A178="","",CHOOSE(WEEKDAY(A178,2),"Lun","Mar","Mié","Jue","Vie","Sáb","Dom")) -> Dom | C178: Noche | D178: {=IF(A178="","",SUMPRODUCT(('Detalle Turnos'!$I$3:$I$5028=$A178)*('Detalle Turnos'!$N$3:$N$5028=C178)*'Detalle Turnos'!$L$3:$L$5028))} -> 9 | E178: {=IF(A178="","",SUMPRODUCT(('Detalle Turnos'!$I$3:$I$5028=$A178)*('Detalle Turnos'!$N$3:$N$5028=C178)*'Detalle Turnos'!$K$3:$K$5028))} -> 87.7 | F178: =IFERROR(E178/D178,0) -> 9.7444444 | G178: {=IF(E178="","",IFERROR(SUMPRODUCT(('Facturación 2026'!$A$4:$A$920=$A178)*'Facturación 2026'!$J$4:$J$920)*E178/(SUMPRODUCT(('Caja 1'!$A$4:$A$919=$A178)*'Caja 1'!$E$4:$E$919)+SUMPRODUCT(('Caja 2'!$A$4:$A$920=$A178)*'Caja 2'!$E$4:$E$920)),0))} -> 0 | H178: =IF(E178="","",E178-G178) -> 87.7 | I178: =IF(E178="","",IFERROR(G178/E178,0)) -> 0 | J178: =IF(A178="","",IFERROR(INDEX('Facturación 2026'!$L$4:$L$500,MATCH($A178,'Facturación 2026'!$A$4:$A$500,0)),"")) -> Joan Pera — Casino
A179: 46141 | B179: =IF(A179="","",CHOOSE(WEEKDAY(A179,2),"Lun","Mar","Mié","Jue","Vie","Sáb","Dom")) -> Mié | C179: Mediodia | D179: {=IF(A179="","",SUMPRODUCT(('Detalle Turnos'!$I$3:$I$5028=$A179)*('Detalle Turnos'!$N$3:$N$5028=C179)*'Detalle Turnos'!$L$3:$L$5028))} -> 11 | E179: {=IF(A179="","",SUMPRODUCT(('Detalle Turnos'!$I$3:$I$5028=$A179)*('Detalle Turnos'!$N$3:$N$5028=C179)*'Detalle Turnos'!$K$3:$K$5028))} -> 105.15 | F179: =IFERROR(E179/D179,0) -> 9.5590909 | G179: {=IF(E179="","",IFERROR(SUMPRODUCT(('Facturación 2026'!$A$4:$A$920=$A179)*'Facturación 2026'!$J$4:$J$920)*E179/(SUMPRODUCT(('Caja 1'!$A$4:$A$919=$A179)*'Caja 1'!$E$4:$E$919)+SUMPRODUCT(('Caja 2'!$A$4:$A$920=$A179)*'Caja 2'!$E$4:$E$920)),0))} -> 0 | H179: =IF(E179="","",E179-G179) -> 105.15 | I179: =IF(E179="","",IFERROR(G179/E179,0)) -> 0 | J179: =IF(A179="","",IFERROR(INDEX('Facturación 2026'!$L$4:$L$500,MATCH($A179,'Facturación 2026'!$A$4:$A$500,0)),""))
A180: 46141 | B180: =IF(A180="","",CHOOSE(WEEKDAY(A180,2),"Lun","Mar","Mié","Jue","Vie","Sáb","Dom")) -> Mié | C180: Noche | D180: {=IF(A180="","",SUMPRODUCT(('Detalle Turnos'!$I$3:$I$5028=$A180)*('Detalle Turnos'!$N$3:$N$5028=C180)*'Detalle Turnos'!$L$3:$L$5028))} -> 6 | E180: {=IF(A180="","",SUMPRODUCT(('Detalle Turnos'!$I$3:$I$5028=$A180)*('Detalle Turnos'!$N$3:$N$5028=C180)*'Detalle Turnos'!$K$3:$K$5028))} -> 95.5 | F180: =IFERROR(E180/D180,0) -> 15.916667 | G180: {=IF(E180="","",IFERROR(SUMPRODUCT(('Facturación 2026'!$A$4:$A$920=$A180)*'Facturación 2026'!$J$4:$J$920)*E180/(SUMPRODUCT(('Caja 1'!$A$4:$A$919=$A180)*'Caja 1'!$E$4:$E$919)+SUMPRODUCT(('Caja 2'!$A$4:$A$920=$A180)*'Caja 2'!$E$4:$E$920)),0))} -> 0 | H180: =IF(E180="","",E180-G180) -> 95.5 | I180: =IF(E180="","",IFERROR(G180/E180,0)) -> 0 | J180: =IF(A180="","",IFERROR(INDEX('Facturación 2026'!$L$4:$L$500,MATCH($A180,'Facturación 2026'!$A$4:$A$500,0)),""))
A181: 46142 | B181: =IF(A181="","",CHOOSE(WEEKDAY(A181,2),"Lun","Mar","Mié","Jue","Vie","Sáb","Dom")) -> Jue | C181: Mediodia | D181: {=IF(A181="","",SUMPRODUCT(('Detalle Turnos'!$I$3:$I$5024=$A181)*('Detalle Turnos'!$N$3:$N$5024=C181)*'Detalle Turnos'!$L$3:$L$5024))} -> 10 | E181: {=IF(A181="","",SUMPRODUCT(('Detalle Turnos'!$I$3:$I$5024=$A181)*('Detalle Turnos'!$N$3:$N$5024=C181)*'Detalle Turnos'!$K$3:$K$5024))} -> 130.3 | F181: =IFERROR(E181/D181,0) -> 13.03 | G181: {=IF(E181="","",IFERROR(SUMPRODUCT(('Facturación 2026'!$A$4:$A$920=$A181)*'Facturación 2026'!$J$4:$J$920)*E181/(SUMPRODUCT(('Caja 1'!$A$4:$A$920=$A181)*'Caja 1'!$E$4:$E$920)+SUMPRODUCT(('Caja 2'!$A$4:$A$920=$A181)*'Caja 2'!$E$4:$E$920)),0))} -> 0 | H181: =IF(E181="","",E181-G181) -> 130.3 | I181: =IF(E181="","",IFERROR(G181/E181,0)) -> 0 | J181: =IF(A181="","",IFERROR(INDEX('Facturación 2026'!$L$4:$L$500,MATCH($A181,'Facturación 2026'!$A$4:$A$500,0)),""))
A182: 46142 | B182: =IF(A182="","",CHOOSE(WEEKDAY(A182,2),"Lun","Mar","Mié","Jue","Vie","Sáb","Dom")) -> Jue | C182: Noche | D182: {=IF(A182="","",SUMPRODUCT(('Detalle Turnos'!$I$3:$I$5020=$A182)*('Detalle Turnos'!$N$3:$N$5020=C182)*'Detalle Turnos'!$L$3:$L$5020))} -> 8 | E182: {=IF(A182="","",SUMPRODUCT(('Detalle Turnos'!$I$3:$I$5020=$A182)*('Detalle Turnos'!$N$3:$N$5020=C182)*'Detalle Turnos'!$K$3:$K$5020))} -> 145.75 | F182: =IFERROR(E182/D182,0) -> 18.21875 | G182: {=IF(E182="","",IFERROR(SUMPRODUCT(('Facturación 2026'!$A$4:$A$920=$A182)*'Facturación 2026'!$J$4:$J$920)*E182/(SUMPRODUCT(('Caja 1'!$A$4:$A$920=$A182)*'Caja 1'!$E$4:$E$920)+SUMPRODUCT(('Caja 2'!$A$4:$A$920=$A182)*'Caja 2'!$E$4:$E$920)),0))} -> 0 | H182: =IF(E182="","",E182-G182) -> 145.75 | I182: =IF(E182="","",IFERROR(G182/E182,0)) -> 0 | J182: =IF(A182="","",IFERROR(INDEX('Facturación 2026'!$L$4:$L$500,MATCH($A182,'Facturación 2026'!$A$4:$A$500,0)),""))
A183: 46143 | B183: =IF(A183="","",CHOOSE(WEEKDAY(A183,2),"Lun","Mar","Mié","Jue","Vie","Sáb","Dom")) -> Vie | C183: Mañana | D183: {=IF(A183="","",SUMPRODUCT(('Detalle Turnos'!$I$3:$I$5011=$A183)*('Detalle Turnos'!$N$3:$N$5011=C183)*'Detalle Turnos'!$L$3:$L$5011))} -> 18 | E183: {=IF(A183="","",SUMPRODUCT(('Detalle Turnos'!$I$3:$I$5011=$A183)*('Detalle Turnos'!$N$3:$N$5011=C183)*'Detalle Turnos'!$K$3:$K$5011))} -> 43.25 | F183: =IFERROR(E183/D183,0) -> 2.4027778 | G183: {=IF(E183="","",IFERROR(SUMPRODUCT(('Facturación 2026'!$A$4:$A$920=$A183)*'Facturación 2026'!$J$4:$J$920)*E183/(SUMPRODUCT(('Caja 1'!$A$4:$A$920=$A183)*'Caja 1'!$E$4:$E$920)+SUMPRODUCT(('Caja 2'!$A$4:$A$920=$A183)*'Caja 2'!$E$4:$E$920)),0))} -> 0 | H183: =IF(E183="","",E183-G183) -> 43.25 | I183: =IF(E183="","",IFERROR(G183/E183,0)) -> 0 | J183: =IF(A183="","",IFERROR(INDEX('Facturación 2026'!$L$4:$L$500,MATCH($A183,'Facturación 2026'!$A$4:$A$500,0)),""))
A184: 46143 | B184: =IF(A184="","",CHOOSE(WEEKDAY(A184,2),"Lun","Mar","Mié","Jue","Vie","Sáb","Dom")) -> Vie | C184: Mediodia | D184: {=IF(A184="","",SUMPRODUCT(('Detalle Turnos'!$I$3:$I$5006=$A184)*('Detalle Turnos'!$N$3:$N$5006=C184)*'Detalle Turnos'!$L$3:$L$5006))} -> 3 | E184: {=IF(A184="","",SUMPRODUCT(('Detalle Turnos'!$I$3:$I$5006=$A184)*('Detalle Turnos'!$N$3:$N$5006=C184)*'Detalle Turnos'!$K$3:$K$5006))} -> 20.75 | F184: =IFERROR(E184/D184,0) -> 6.9166667 | G184: {=IF(E184="","",IFERROR(SUMPRODUCT(('Facturación 2026'!$A$4:$A$920=$A184)*'Facturación 2026'!$J$4:$J$920)*E184/(SUMPRODUCT(('Caja 1'!$A$4:$A$920=$A184)*'Caja 1'!$E$4:$E$920)+SUMPRODUCT(('Caja 2'!$A$4:$A$920=$A184)*'Caja 2'!$E$4:$E$920)),0))} -> 0 | H184: =IF(E184="","",E184-G184) -> 20.75 | I184: =IF(E184="","",IFERROR(G184/E184,0)) -> 0 | J184: =IF(A184="","",IFERROR(INDEX('Facturación 2026'!$L$4:$L$500,MATCH($A184,'Facturación 2026'!$A$4:$A$500,0)),""))
A185: 46143 | B185: =IF(A185="","",CHOOSE(WEEKDAY(A185,2),"Lun","Mar","Mié","Jue","Vie","Sáb","Dom")) -> Vie | C185: Noche | D185: {=IF(A185="","",SUMPRODUCT(('Detalle Turnos'!$I$3:$I$5006=$A185)*('Detalle Turnos'!$N$3:$N$5006=C185)*'Detalle Turnos'!$L$3:$L$5006))} -> 2 | E185: {=IF(A185="","",SUMPRODUCT(('Detalle Turnos'!$I$3:$I$5006=$A185)*('Detalle Turnos'!$N$3:$N$5006=C185)*'Detalle Turnos'!$K$3:$K$5006))} -> 11.3 | F185: =IFERROR(E185/D185,0) -> 5.65 | G185: {=IF(E185="","",IFERROR(SUMPRODUCT(('Facturación 2026'!$A$4:$A$920=$A185)*'Facturación 2026'!$J$4:$J$920)*E185/(SUMPRODUCT(('Caja 1'!$A$4:$A$920=$A185)*'Caja 1'!$E$4:$E$920)+SUMPRODUCT(('Caja 2'!$A$4:$A$920=$A185)*'Caja 2'!$E$4:$E$920)),0))} -> 0 | H185: =IF(E185="","",E185-G185) -> 11.3 | I185: =IF(E185="","",IFERROR(G185/E185,0)) -> 0 | J185: =IF(A185="","",IFERROR(INDEX('Facturación 2026'!$L$4:$L$500,MATCH($A185,'Facturación 2026'!$A$4:$A$500,0)),""))
B186: =IF(A186="","",CHOOSE(WEEKDAY(A186,2),"Lun","Mar","Mié","Jue","Vie","Sáb","Dom")) | D186: {=IF(A186="","",SUMPRODUCT(('Detalle Turnos'!$I$3:$I$5028=$A186)*('Detalle Turnos'!$N$3:$N$5028=C186)*'Detalle Turnos'!$L$3:$L$5028))} | E186: {=IF(A186="","",SUMPRODUCT(('Detalle Turnos'!$I$3:$I$5028=$A186)*('Detalle Turnos'!$N$3:$N$5028=C186)*'Detalle Turnos'!$K$3:$K$5028))} | F186: =IFERROR(E186/D186,0) -> 0 | G186: {=IF(E186="","",IFERROR(SUMPRODUCT(('Facturación 2026'!$A$4:$A$920=$A186)*'Facturación 2026'!$J$4:$J$920)*E186/(SUMPRODUCT(('Caja 1'!$A$4:$A$919=$A186)*'Caja 1'!$E$4:$E$919)+SUMPRODUCT(('Caja 2'!$A$4:$A$920=$A186)*'Caja 2'!$E$4:$E$920)),0))} | H186: =IF(E186="","",E186-G186) | I186: =IF(E186="","",IFERROR(G186/E186,0)) | J186: =IF(A186="","",IFERROR(INDEX('Facturación 2026'!$L$4:$L$500,MATCH($A186,'Facturación 2026'!$A$4:$A$500,0)),""))
B187: =IF(A187="","",CHOOSE(WEEKDAY(A187,2),"Lun","Mar","Mié","Jue","Vie","Sáb","Dom")) | D187: {=IF(A187="","",SUMPRODUCT(('Detalle Turnos'!$I$3:$I$5028=$A187)*('Detalle Turnos'!$N$3:$N$5028=C187)*'Detalle Turnos'!$L$3:$L$5028))} | E187: {=IF(A187="","",SUMPRODUCT(('Detalle Turnos'!$I$3:$I$5028=$A187)*('Detalle Turnos'!$N$3:$N$5028=C187)*'Detalle Turnos'!$K$3:$K$5028))} | F187: =IFERROR(E187/D187,0) -> 0 | G187: {=IF(E187="","",IFERROR(SUMPRODUCT(('Facturación 2026'!$A$4:$A$920=$A187)*'Facturación 2026'!$J$4:$J$920)*E187/(SUMPRODUCT(('Caja 1'!$A$4:$A$919=$A187)*'Caja 1'!$E$4:$E$919)+SUMPRODUCT(('Caja 2'!$A$4:$A$920=$A187)*'Caja 2'!$E$4:$E$920)),0))} | H187: =IF(E187="","",E187-G187) | I187: =IF(E187="","",IFERROR(G187/E187,0)) | J187: =IF(A187="","",IFERROR(INDEX('Facturación 2026'!$L$4:$L$500,MATCH($A187,'Facturación 2026'!$A$4:$A$500,0)),""))
B188: =IF(A188="","",CHOOSE(WEEKDAY(A188,2),"Lun","Mar","Mié","Jue","Vie","Sáb","Dom")) | D188: {=IF(A188="","",SUMPRODUCT(('Detalle Turnos'!$I$3:$I$5028=$A188)*('Detalle Turnos'!$N$3:$N$5028=C188)*'Detalle Turnos'!$L$3:$L$5028))} | E188: {=IF(A188="","",SUMPRODUCT(('Detalle Turnos'!$I$3:$I$5028=$A188)*('Detalle Turnos'!$N$3:$N$5028=C188)*'Detalle Turnos'!$K$3:$K$5028))} | F188: =IFERROR(E188/D188,0) -> 0 | G188: {=IF(E188="","",IFERROR(SUMPRODUCT(('Facturación 2026'!$A$4:$A$920=$A188)*'Facturación 2026'!$J$4:$J$920)*E188/(SUMPRODUCT(('Caja 1'!$A$4:$A$919=$A188)*'Caja 1'!$E$4:$E$919)+SUMPRODUCT(('Caja 2'!$A$4:$A$920=$A188)*'Caja 2'!$E$4:$E$920)),0))} | H188: =IF(E188="","",E188-G188) | I188: =IF(E188="","",IFERROR(G188/E188,0)) | J188: =IF(A188="","",IFERROR(INDEX('Facturación 2026'!$L$4:$L$500,MATCH($A188,'Facturación 2026'!$A$4:$A$500,0)),""))
B189: =IF(A189="","",CHOOSE(WEEKDAY(A189,2),"Lun","Mar","Mié","Jue","Vie","Sáb","Dom")) | D189: {=IF(A189="","",SUMPRODUCT(('Detalle Turnos'!$I$3:$I$5028=$A189)*('Detalle Turnos'!$N$3:$N$5028=C189)*'Detalle Turnos'!$L$3:$L$5028))} | E189: {=IF(A189="","",SUMPRODUCT(('Detalle Turnos'!$I$3:$I$5028=$A189)*('Detalle Turnos'!$N$3:$N$5028=C189)*'Detalle Turnos'!$K$3:$K$5028))} | F189: =IFERROR(E189/D189,0) -> 0 | G189: {=IF(E189="","",IFERROR(SUMPRODUCT(('Facturación 2026'!$A$4:$A$920=$A189)*'Facturación 2026'!$J$4:$J$920)*E189/(SUMPRODUCT(('Caja 1'!$A$4:$A$919=$A189)*'Caja 1'!$E$4:$E$919)+SUMPRODUCT(('Caja 2'!$A$4:$A$920=$A189)*'Caja 2'!$E$4:$E$920)),0))} | H189: =IF(E189="","",E189-G189) | I189: =IF(E189="","",IFERROR(G189/E189,0)) | J189: =IF(A189="","",IFERROR(INDEX('Facturación 2026'!$L$4:$L$500,MATCH($A189,'Facturación 2026'!$A$4:$A$500,0)),""))
B190: =IF(A190="","",CHOOSE(WEEKDAY(A190,2),"Lun","Mar","Mié","Jue","Vie","Sáb","Dom")) | D190: {=IF(A190="","",SUMPRODUCT(('Detalle Turnos'!$I$3:$I$5028=$A190)*('Detalle Turnos'!$N$3:$N$5028=C190)*'Detalle Turnos'!$L$3:$L$5028))} | E190: {=IF(A190="","",SUMPRODUCT(('Detalle Turnos'!$I$3:$I$5028=$A190)*('Detalle Turnos'!$N$3:$N$5028=C190)*'Detalle Turnos'!$K$3:$K$5028))} | F190: =IFERROR(E190/D190,0) -> 0 | G190: {=IF(E190="","",IFERROR(SUMPRODUCT(('Facturación 2026'!$A$4:$A$920=$A190)*'Facturación 2026'!$J$4:$J$920)*E190/(SUMPRODUCT(('Caja 1'!$A$4:$A$919=$A190)*'Caja 1'!$E$4:$E$919)+SUMPRODUCT(('Caja 2'!$A$4:$A$920=$A190)*'Caja 2'!$E$4:$E$920)),0))} | H190: =IF(E190="","",E190-G190) | I190: =IF(E190="","",IFERROR(G190/E190,0)) | J190: =IF(A190="","",IFERROR(INDEX('Facturación 2026'!$L$4:$L$500,MATCH($A190,'Facturación 2026'!$A$4:$A$500,0)),""))
B191: =IF(A191="","",CHOOSE(WEEKDAY(A191,2),"Lun","Mar","Mié","Jue","Vie","Sáb","Dom")) | D191: {=IF(A191="","",SUMPRODUCT(('Detalle Turnos'!$I$3:$I$5028=$A191)*('Detalle Turnos'!$N$3:$N$5028=C191)*'Detalle Turnos'!$L$3:$L$5028))} | E191: {=IF(A191="","",SUMPRODUCT(('Detalle Turnos'!$I$3:$I$5028=$A191)*('Detalle Turnos'!$N$3:$N$5028=C191)*'Detalle Turnos'!$K$3:$K$5028))} | F191: =IFERROR(E191/D191,0) -> 0 | G191: {=IF(E191="","",IFERROR(SUMPRODUCT(('Facturación 2026'!$A$4:$A$920=$A191)*'Facturación 2026'!$J$4:$J$920)*E191/(SUMPRODUCT(('Caja 1'!$A$4:$A$919=$A191)*'Caja 1'!$E$4:$E$919)+SUMPRODUCT(('Caja 2'!$A$4:$A$920=$A191)*'Caja 2'!$E$4:$E$920)),0))} | H191: =IF(E191="","",E191-G191) | I191: =IF(E191="","",IFERROR(G191/E191,0)) | J191: =IF(A191="","",IFERROR(INDEX('Facturación 2026'!$L$4:$L$500,MATCH($A191,'Facturación 2026'!$A$4:$A$500,0)),""))
B192: =IF(A192="","",CHOOSE(WEEKDAY(A192,2),"Lun","Mar","Mié","Jue","Vie","Sáb","Dom")) | D192: {=IF(A192="","",SUMPRODUCT(('Detalle Turnos'!$I$3:$I$5028=$A192)*('Detalle Turnos'!$N$3:$N$5028=C192)*'Detalle Turnos'!$L$3:$L$5028))} | E192: {=IF(A192="","",SUMPRODUCT(('Detalle Turnos'!$I$3:$I$5028=$A192)*('Detalle Turnos'!$N$3:$N$5028=C192)*'Detalle Turnos'!$K$3:$K$5028))} | F192: =IFERROR(E192/D192,0) -> 0 | G192: {=IF(E192="","",IFERROR(SUMPRODUCT(('Facturación 2026'!$A$4:$A$920=$A192)*'Facturación 2026'!$J$4:$J$920)*E192/(SUMPRODUCT(('Caja 1'!$A$4:$A$919=$A192)*'Caja 1'!$E$4:$E$919)+SUMPRODUCT(('Caja 2'!$A$4:$A$920=$A192)*'Caja 2'!$E$4:$E$920)),0))} | H192: =IF(E192="","",E192-G192) | I192: =IF(E192="","",IFERROR(G192/E192,0)) | J192: =IF(A192="","",IFERROR(INDEX('Facturación 2026'!$L$4:$L$500,MATCH($A192,'Facturación 2026'!$A$4:$A$500,0)),""))
B193: =IF(A193="","",CHOOSE(WEEKDAY(A193,2),"Lun","Mar","Mié","Jue","Vie","Sáb","Dom")) | D193: {=IF(A193="","",SUMPRODUCT(('Detalle Turnos'!$I$3:$I$5028=$A193)*('Detalle Turnos'!$N$3:$N$5028=C193)*'Detalle Turnos'!$L$3:$L$5028))} | E193: {=IF(A193="","",SUMPRODUCT(('Detalle Turnos'!$I$3:$I$5028=$A193)*('Detalle Turnos'!$N$3:$N$5028=C193)*'Detalle Turnos'!$K$3:$K$5028))} | F193: =IFERROR(E193/D193,0) -> 0 | G193: {=IF(E193="","",IFERROR(SUMPRODUCT(('Facturación 2026'!$A$4:$A$920=$A193)*'Facturación 2026'!$J$4:$J$920)*E193/(SUMPRODUCT(('Caja 1'!$A$4:$A$919=$A193)*'Caja 1'!$E$4:$E$919)+SUMPRODUCT(('Caja 2'!$A$4:$A$920=$A193)*'Caja 2'!$E$4:$E$920)),0))} | H193: =IF(E193="","",E193-G193) | I193: =IF(E193="","",IFERROR(G193/E193,0)) | J193: =IF(A193="","",IFERROR(INDEX('Facturación 2026'!$L$4:$L$500,MATCH($A193,'Facturación 2026'!$A$4:$A$500,0)),""))
B194: =IF(A194="","",CHOOSE(WEEKDAY(A194,2),"Lun","Mar","Mié","Jue","Vie","Sáb","Dom")) | D194: {=IF(A194="","",SUMPRODUCT(('Detalle Turnos'!$I$3:$I$5028=$A194)*('Detalle Turnos'!$N$3:$N$5028=C194)*'Detalle Turnos'!$L$3:$L$5028))} | E194: {=IF(A194="","",SUMPRODUCT(('Detalle Turnos'!$I$3:$I$5028=$A194)*('Detalle Turnos'!$N$3:$N$5028=C194)*'Detalle Turnos'!$K$3:$K$5028))} | F194: =IFERROR(E194/D194,0) -> 0 | G194: {=IF(E194="","",IFERROR(SUMPRODUCT(('Facturación 2026'!$A$4:$A$920=$A194)*'Facturación 2026'!$J$4:$J$920)*E194/(SUMPRODUCT(('Caja 1'!$A$4:$A$919=$A194)*'Caja 1'!$E$4:$E$919)+SUMPRODUCT(('Caja 2'!$A$4:$A$920=$A194)*'Caja 2'!$E$4:$E$920)),0))} | H194: =IF(E194="","",E194-G194) | I194: =IF(E194="","",IFERROR(G194/E194,0)) | J194: =IF(A194="","",IFERROR(INDEX('Facturación 2026'!$L$4:$L$500,MATCH($A194,'Facturación 2026'!$A$4:$A$500,0)),""))
B195: =IF(A195="","",CHOOSE(WEEKDAY(A195,2),"Lun","Mar","Mié","Jue","Vie","Sáb","Dom")) | D195: {=IF(A195="","",SUMPRODUCT(('Detalle Turnos'!$I$3:$I$5028=$A195)*('Detalle Turnos'!$N$3:$N$5028=C195)*'Detalle Turnos'!$L$3:$L$5028))} | E195: {=IF(A195="","",SUMPRODUCT(('Detalle Turnos'!$I$3:$I$5028=$A195)*('Detalle Turnos'!$N$3:$N$5028=C195)*'Detalle Turnos'!$K$3:$K$5028))} | F195: =IFERROR(E195/D195,0) -> 0 | G195: {=IF(E195="","",IFERROR(SUMPRODUCT(('Facturación 2026'!$A$4:$A$920=$A195)*'Facturación 2026'!$J$4:$J$920)*E195/(SUMPRODUCT(('Caja 1'!$A$4:$A$919=$A195)*'Caja 1'!$E$4:$E$919)+SUMPRODUCT(('Caja 2'!$A$4:$A$920=$A195)*'Caja 2'!$E$4:$E$920)),0))} | H195: =IF(E195="","",E195-G195) | I195: =IF(E195="","",IFERROR(G195/E195,0)) | J195: =IF(A195="","",IFERROR(INDEX('Facturación 2026'!$L$4:$L$500,MATCH($A195,'Facturación 2026'!$A$4:$A$500,0)),""))
B196: =IF(A196="","",CHOOSE(WEEKDAY(A196,2),"Lun","Mar","Mié","Jue","Vie","Sáb","Dom")) | D196: {=IF(A196="","",SUMPRODUCT(('Detalle Turnos'!$I$3:$I$5028=$A196)*('Detalle Turnos'!$N$3:$N$5028=C196)*'Detalle Turnos'!$L$3:$L$5028))} | E196: {=IF(A196="","",SUMPRODUCT(('Detalle Turnos'!$I$3:$I$5028=$A196)*('Detalle Turnos'!$N$3:$N$5028=C196)*'Detalle Turnos'!$K$3:$K$5028))} | F196: =IFERROR(E196/D196,0) -> 0 | G196: {=IF(E196="","",IFERROR(SUMPRODUCT(('Facturación 2026'!$A$4:$A$920=$A196)*'Facturación 2026'!$J$4:$J$920)*E196/(SUMPRODUCT(('Caja 1'!$A$4:$A$919=$A196)*'Caja 1'!$E$4:$E$919)+SUMPRODUCT(('Caja 2'!$A$4:$A$920=$A196)*'Caja 2'!$E$4:$E$920)),0))} | H196: =IF(E196="","",E196-G196) | I196: =IF(E196="","",IFERROR(G196/E196,0)) | J196: =IF(A196="","",IFERROR(INDEX('Facturación 2026'!$L$4:$L$500,MATCH($A196,'Facturación 2026'!$A$4:$A$500,0)),""))
B197: =IF(A197="","",CHOOSE(WEEKDAY(A197,2),"Lun","Mar","Mié","Jue","Vie","Sáb","Dom")) | D197: {=IF(A197="","",SUMPRODUCT(('Detalle Turnos'!$I$3:$I$5028=$A197)*('Detalle Turnos'!$N$3:$N$5028=C197)*'Detalle Turnos'!$L$3:$L$5028))} | E197: {=IF(A197="","",SUMPRODUCT(('Detalle Turnos'!$I$3:$I$5028=$A197)*('Detalle Turnos'!$N$3:$N$5028=C197)*'Detalle Turnos'!$K$3:$K$5028))} | F197: =IFERROR(E197/D197,0) -> 0 | G197: {=IF(E197="","",IFERROR(SUMPRODUCT(('Facturación 2026'!$A$4:$A$920=$A197)*'Facturación 2026'!$J$4:$J$920)*E197/(SUMPRODUCT(('Caja 1'!$A$4:$A$919=$A197)*'Caja 1'!$E$4:$E$919)+SUMPRODUCT(('Caja 2'!$A$4:$A$920=$A197)*'Caja 2'!$E$4:$E$920)),0))} | H197: =IF(E197="","",E197-G197) | I197: =IF(E197="","",IFERROR(G197/E197,0)) | J197: =IF(A197="","",IFERROR(INDEX('Facturación 2026'!$L$4:$L$500,MATCH($A197,'Facturación 2026'!$A$4:$A$500,0)),""))
... B919: =IF(A919="","",CHOOSE(WEEKDAY(A919,2),"Lun","Mar","Mié","Jue","Vie","Sáb","Dom")) | D919: {=IF(A919="","",SUMPRODUCT(('Detalle Turnos'!$I$3:$I$5028=$A919)*('Detalle Turnos'!$N$3:$N$5028=C919)*'Detalle Turnos'!$L$3:$L$5028))} | E919: {=IF(A919="","",SUMPRODUCT(('Detalle Turnos'!$I$3:$I$5028=$A919)*('Detalle Turnos'!$N$3:$N$5028=C919)*'Detalle Turnos'!$K$3:$K$5028))} | F919: =IFERROR(E919/D919,0) -> 0 | G919: {=IF(E919="","",IFERROR(SUMPRODUCT(('Facturación 2026'!$A$4:$A$920=$A919)*'Facturación 2026'!$J$4:$J$920)*E919/(SUMPRODUCT(('Caja 1'!$A$4:$A$919=$A919)*'Caja 1'!$E$4:$E$919)+SUMPRODUCT(('Caja 2'!$A$4:$A$920=$A919)*'Caja 2'!$E$4:$E$920)),0))} | H919: =IF(E919="","",E919-G919) | I919: =IF(E919="","",IFERROR(G919/E919,0)) | J919: =IF(A919="","",IFERROR(INDEX('Facturación 2026'!$L$4:$L$500,MATCH($A919,'Facturación 2026'!$A$4:$A$500,0)),""))

Sheet Caja 2
A1: TAPERIA DE CALDES · CAJA 2 — COMENSALES Y FACTURACIÓN | L1: RESUMEN MENSUAL
L2: Mes | O2: Comensales | P2: Facturación € | Q2: Ticket Medio € | R2: Coste Personal € | S2: Margen € | T2: % Coste
A3: Fecha | B3: Día | C3: Turno | D3: Nº Comensales | E3: Subtotal € | F3: Ticket Medio € | G3: Coste Personal € | H3: Margen € | I3: % Coste | J3: Notas / Evento | L3: Enero | O3: {=SUMPRODUCT((MONTH($A$4:$A$166)=1)*IFERROR($D$4:$D$166*1,0))} -> 1828 | P3: {=SUMPRODUCT((MONTH($A$4:$A$166)=1)*IFERROR($E$4:$E$166*1,0))} -> 22953.64 | Q3: =IFERROR(P3/O3,0) -> 12.556696 | R3: {=SUMPRODUCT((MONTH($A$4:$A$166)=1)*IFERROR($G$4:$G$166*1,0))} -> 9050.7232 | S3: =P3-R3 -> 13902.917 | T3: =IFERROR(R3/P3,0) -> 0.39430449
A4: 46024 | B4: Vie | C4: Mañana | D4: {=IF(A4="","",SUMPRODUCT(('Detalle Turnos'!$Q$3:$Q$500=$A4)*('Detalle Turnos'!$S$3:$S$500=C4)*'Detalle Turnos'!$T$3:$T$500))} -> 23 | E4: {=IF(A4="","",SUMPRODUCT(('Detalle Turnos'!$Q$3:$Q$500=$A4)*('Detalle Turnos'!$S$3:$S$500=C4)*'Detalle Turnos'!$U$3:$U$500))} -> 92.73 | F4: =IFERROR(E4/D4,0) -> 4.0317391 | G4: {=IFERROR(SUMPRODUCT(('Facturación 2026'!$A$4:$A$253=A4)*'Facturación 2026'!$J$4:$J$253)*E4/SUMPRODUCT(('Facturación 2026'!$A$4:$A$253=A4)*'Facturación 2026'!$F$4:$F$253),0)} -> 30.99028 | H4: =E4-G4 -> 61.73972 | I4: =IFERROR(G4/E4,0) -> 0.33419907 | J4: =IFERROR(INDEX('Facturación 2026'!$L$4:$L$253,MATCH(A4,'Facturación 2026'!$A$4:$A$253,0)),"") | L4: Febrero | O4: {=SUMPRODUCT((MONTH($A$4:$A$166)=2)*IFERROR($D$4:$D$166*1,0))} -> 1739 | P4: {=SUMPRODUCT((MONTH($A$4:$A$166)=2)*IFERROR($E$4:$E$166*1,0))} -> 22438.92 | Q4: =IFERROR(P4/O4,0) -> 12.903347 | R4: {=SUMPRODUCT((MONTH($A$4:$A$166)=2)*IFERROR($G$4:$G$166*1,0))} -> 6799.6937 | S4: =P4-R4 -> 15639.226 | T4: =IFERROR(R4/P4,0) -> 0.30303124
A5: 46024 | B5: Vie | C5: Mediodia | D5: {=IF(A5="","",SUMPRODUCT(('Detalle Turnos'!$Q$3:$Q$500=$A5)*('Detalle Turnos'!$S$3:$S$500=C5)*'Detalle Turnos'!$T$3:$T$500))} -> 36 | E5: {=IF(A5="","",SUMPRODUCT(('Detalle Turnos'!$Q$3:$Q$500=$A5)*('Detalle Turnos'!$S$3:$S$500=C5)*'Detalle Turnos'!$U$3:$U$500))} -> 612 | F5: =IFERROR(E5/D5,0) -> 17 | G5: {=IFERROR(SUMPRODUCT(('Facturación 2026'!$A$4:$A$253=A5)*'Facturación 2026'!$J$4:$J$253)*E5/SUMPRODUCT(('Facturación 2026'!$A$4:$A$253=A5)*'Facturación 2026'!$F$4:$F$253),0)} -> 204.52983 | H5: =E5-G5 -> 407.47017 | I5: =IFERROR(G5/E5,0) -> 0.33419907 | J5: =IFERROR(INDEX('Facturación 2026'!$L$4:$L$253,MATCH(A5,'Facturación 2026'!$A$4:$A$253,0)),"") | L5: Marzo | O5: {=SUMPRODUCT((MONTH($A$4:$A$166)=3)*IFERROR($D$4:$D$166*1,0))} -> 1337 | P5: {=SUMPRODUCT((MONTH($A$4:$A$166)=3)*IFERROR($E$4:$E$166*1,0))} -> 16379.43 | Q5: =IFERROR(P5/O5,0) -> 12.250883 | R5: {=SUMPRODUCT((MONTH($A$4:$A$166)=3)*IFERROR($G$4:$G$166*1,0))} -> 4888.7507 | S5: =P5-R5 -> 11490.679 | T5: =IFERROR(R5/P5,0) -> 0.29846892
A6: 46024 | B6: Vie | C6: Noche | D6: {=IF(A6="","",SUMPRODUCT(('Detalle Turnos'!$Q$3:$Q$500=$A6)*('Detalle Turnos'!$S$3:$S$500=C6)*'Detalle Turnos'!$T$3:$T$500))} -> 51 | E6: {=IF(A6="","",SUMPRODUCT(('Detalle Turnos'!$Q$3:$Q$500=$A6)*('Detalle Turnos'!$S$3:$S$500=C6)*'Detalle Turnos'!$U$3:$U$500))} -> 727.68 | F6: =IFERROR(E6/D6,0) -> 14.268235 | G6: {=IFERROR(SUMPRODUCT(('Facturación 2026'!$A$4:$A$253=A6)*'Facturación 2026'!$J$4:$J$253)*E6/SUMPRODUCT(('Facturación 2026'!$A$4:$A$253=A6)*'Facturación 2026'!$F$4:$F$253),0)} -> 243.18998 | H6: =E6-G6 -> 484.49002 | I6: =IFERROR(G6/E6,0) -> 0.33419907 | J6: =IFERROR(INDEX('Facturación 2026'!$L$4:$L$253,MATCH(A6,'Facturación 2026'!$A$4:$A$253,0)),"") | L6: Abril | O6: {=SUMPRODUCT((MONTH($A$4:$A$166)=4)*IFERROR($D$4:$D$166*1,0))} -> 525 | P6: {=SUMPRODUCT((MONTH($A$4:$A$166)=4)*IFERROR($E$4:$E$166*1,0))} -> 7382.972 | Q6: =IFERROR(P6/O6,0) -> 14.062804 | R6: {=SUMPRODUCT((MONTH($A$4:$A$166)=4)*IFERROR($G$4:$G$166*1,0))} -> 0 | S6: =P6-R6 -> 7382.972 | T6: =IFERROR(R6/P6,0) -> 0
A7: 46025 | B7: Sáb | C7: Mañana | D7: {=IF(A7="","",SUMPRODUCT(('Detalle Turnos'!$Q$3:$Q$500=$A7)*('Detalle Turnos'!$S$3:$S$500=C7)*'Detalle Turnos'!$T$3:$T$500))} -> 19 | E7: {=IF(A7="","",SUMPRODUCT(('Detalle Turnos'!$Q$3:$Q$500=$A7)*('Detalle Turnos'!$S$3:$S$500=C7)*'Detalle Turnos'!$U$3:$U$500))} -> 74.14 | F7: =IFERROR(E7/D7,0) -> 3.9021053 | G7: {=IFERROR(SUMPRODUCT(('Facturación 2026'!$A$4:$A$253=A7)*'Facturación 2026'!$J$4:$J$253)*E7/SUMPRODUCT(('Facturación 2026'!$A$4:$A$253=A7)*'Facturación 2026'!$F$4:$F$253),0)} -> 25.4766 | H7: =E7-G7 -> 48.6634 | I7: =IFERROR(G7/E7,0) -> 0.34362827 | J7: =IFERROR(INDEX('Facturación 2026'!$L$4:$L$253,MATCH(A7,'Facturación 2026'!$A$4:$A$253,0)),"") | L7: TOTAL ANUAL | O7: =SUM(O3:O6) -> 5429 | P7: =SUM(P3:P6) -> 69154.962 | Q7: =IFERROR(P7/O7,0) -> 12.738066 | R7: =SUM(R3:R6) -> 20739.168 | S7: =P7-R7 -> 48415.794 | T7: =IFERROR(R7/P7,0) -> 0.29989414
A8: 46025 | B8: Sáb | C8: Mediodia | D8: {=IF(A8="","",SUMPRODUCT(('Detalle Turnos'!$Q$3:$Q$500=$A8)*('Detalle Turnos'!$S$3:$S$500=C8)*'Detalle Turnos'!$T$3:$T$500))} -> 73 | E8: {=IF(A8="","",SUMPRODUCT(('Detalle Turnos'!$Q$3:$Q$500=$A8)*('Detalle Turnos'!$S$3:$S$500=C8)*'Detalle Turnos'!$U$3:$U$500))} -> 1054.32 | F8: =IFERROR(E8/D8,0) -> 14.44274 | G8: {=IFERROR(SUMPRODUCT(('Facturación 2026'!$A$4:$A$253=A8)*'Facturación 2026'!$J$4:$J$253)*E8/SUMPRODUCT(('Facturación 2026'!$A$4:$A$253=A8)*'Facturación 2026'!$F$4:$F$253),0)} -> 362.29416 | H8: =E8-G8 -> 692.02584 | I8: =IFERROR(G8/E8,0) -> 0.34362827 | J8: =IFERROR(INDEX('Facturación 2026'!$L$4:$L$253,MATCH(A8,'Facturación 2026'!$A$4:$A$253,0)),"") | L8: Total | O8: =SUM(O3:O7) -> 10858 | P8: =SUM(P3:P7) -> 138309.92 | Q8: =IFERROR(P8/O8,0) -> 12.738066 | R8: =SUM(R3:R7) -> 41478.335 | S8: =P8-R8 -> 96831.589 | T8: =IFERROR(R8/P8,0) -> 0.29989414
A9: 46025 | B9: Sáb | C9: Noche | D9: {=IF(A9="","",SUMPRODUCT(('Detalle Turnos'!$Q$3:$Q$500=$A9)*('Detalle Turnos'!$S$3:$S$500=C9)*'Detalle Turnos'!$T$3:$T$500))} -> 30 | E9: {=IF(A9="","",SUMPRODUCT(('Detalle Turnos'!$Q$3:$Q$500=$A9)*('Detalle Turnos'!$S$3:$S$500=C9)*'Detalle Turnos'!$U$3:$U$500))} -> 382.82 | F9: =IFERROR(E9/D9,0) -> 12.760667 | G9: {=IFERROR(SUMPRODUCT(('Facturación 2026'!$A$4:$A$253=A9)*'Facturación 2026'!$J$4:$J$253)*E9/SUMPRODUCT(('Facturación 2026'!$A$4:$A$253=A9)*'Facturación 2026'!$F$4:$F$253),0)} -> 131.54778 | H9: =E9-G9 -> 251.27222 | I9: =IFERROR(G9/E9,0) -> 0.34362827 | J9: =IFERROR(INDEX('Facturación 2026'!$L$4:$L$253,MATCH(A9,'Facturación 2026'!$A$4:$A$253,0)),"") | L9: ANÁLISIS POR TURNO
A10: 46026 | B10: Dom | C10: Mañana | D10: {=IF(A10="","",SUMPRODUCT(('Detalle Turnos'!$Q$3:$Q$500=$A10)*('Detalle Turnos'!$S$3:$S$500=C10)*'Detalle Turnos'!$T$3:$T$500))} -> 11 | E10: {=IF(A10="","",SUMPRODUCT(('Detalle Turnos'!$Q$3:$Q$500=$A10)*('Detalle Turnos'!$S$3:$S$500=C10)*'Detalle Turnos'!$U$3:$U$500))} -> 47.41 | F10: =IFERROR(E10/D10,0) -> 4.31 | G10: {=IFERROR(SUMPRODUCT(('Facturación 2026'!$A$4:$A$253=A10)*'Facturación 2026'!$J$4:$J$253)*E10/SUMPRODUCT(('Facturación 2026'!$A$4:$A$253=A10)*'Facturación 2026'!$F$4:$F$253),0)} -> 23.326966 | H10: =E10-G10 -> 24.083034 | I10: =IFERROR(G10/E10,0) -> 0.49202629 | J10: =IFERROR(INDEX('Facturación 2026'!$L$4:$L$253,MATCH(A10,'Facturación 2026'!$A$4:$A$253,0)),"") | L10: Turno | O10: Comensales | P10: Facturación € | Q10: % del Total | R10: Ticket Medio € | S10: Margen € | T10: % Coste
A11: 46026 | B11: Dom | C11: Mediodia | D11: {=IF(A11="","",SUMPRODUCT(('Detalle Turnos'!$Q$3:$Q$500=$A11)*('Detalle Turnos'!$S$3:$S$500=C11)*'Detalle Turnos'!$T$3:$T$500))} -> 62 | E11: {=IF(A11="","",SUMPRODUCT(('Detalle Turnos'!$Q$3:$Q$500=$A11)*('Detalle Turnos'!$S$3:$S$500=C11)*'Detalle Turnos'!$U$3:$U$500))} -> 816.14 | F11: =IFERROR(E11/D11,0) -> 13.163548 | G11: {=IFERROR(SUMPRODUCT(('Facturación 2026'!$A$4:$A$253=A11)*'Facturación 2026'!$J$4:$J$253)*E11/SUMPRODUCT(('Facturación 2026'!$A$4:$A$253=A11)*'Facturación 2026'!$F$4:$F$253),0)} -> 401.56233 | H11: =E11-G11 -> 414.57767 | I11: =IFERROR(G11/E11,0) -> 0.49202629 | J11: =IFERROR(INDEX('Facturación 2026'!$L$4:$L$253,MATCH(A11,'Facturación 2026'!$A$4:$A$253,0)),"") | L11: Mañana | O11: {=SUMPRODUCT(($C$4:$C$166="Mañana")*IFERROR($D$4:$D$166*1,0))} -> 1050 | P11: {=SUMPRODUCT(($C$4:$C$166="Mañana")*IFERROR($E$4:$E$166*1,0))} -> 4466.539 | Q11: =IFERROR(P11/$E$173,0) -> 24.031222 | R11: =IFERROR(P11/O11,0) -> 4.2538467 | S11: {=SUMPRODUCT(($C$4:$C$164="Mañana")*$H$4:$H$164)} -> 2741.6265 | T11: =IFERROR(1-S11/P11,0) -> 0.38618548
A12: 46029 | B12: Mié | C12: Mañana | D12: {=IF(A12="","",SUMPRODUCT(('Detalle Turnos'!$Q$3:$Q$500=$A12)*('Detalle Turnos'!$S$3:$S$500=C12)*'Detalle Turnos'!$T$3:$T$500))} -> 9 | E12: {=IF(A12="","",SUMPRODUCT(('Detalle Turnos'!$Q$3:$Q$500=$A12)*('Detalle Turnos'!$S$3:$S$500=C12)*'Detalle Turnos'!$U$3:$U$500))} -> 39.05 | F12: =IFERROR(E12/D12,0) -> 4.3388889 | G12: {=IFERROR(SUMPRODUCT(('Facturación 2026'!$A$4:$A$253=A12)*'Facturación 2026'!$J$4:$J$253)*E12/SUMPRODUCT(('Facturación 2026'!$A$4:$A$253=A12)*'Facturación 2026'!$F$4:$F$253),0)} -> 28.916431 | H12: =E12-G12 -> 10.133569 | I12: =IFERROR(G12/E12,0) -> 0.74049759 | J12: =IFERROR(INDEX('Facturación 2026'!$L$4:$L$253,MATCH(A12,'Facturación 2026'!$A$4:$A$253,0)),"") | L12: Mediodía | O12: {=SUMPRODUCT(($C$4:$C$166="Mediodia")*IFERROR($D$4:$D$166*1,0))} -> 2686 | P12: {=SUMPRODUCT(($C$4:$C$166="Mediodia")*IFERROR($E$4:$E$166*1,0))} -> 37622.943 | Q12: =IFERROR(P12/$E$173,0) -> 202.42189 | R12: =IFERROR(P12/O12,0) -> 14.007052 | S12: {=SUMPRODUCT(($C$4:$C$164="Mediodia")*$H$4:$H$164)} -> 25620.672 | T12: =IFERROR(1-S12/P12,0) -> 0.31901467
A13: 46029 | B13: Mié | C13: Mediodia | D13: {=IF(A13="","",SUMPRODUCT(('Detalle Turnos'!$Q$3:$Q$500=$A13)*('Detalle Turnos'!$S$3:$S$500=C13)*'Detalle Turnos'!$T$3:$T$500))} -> 27 | E13: {=IF(A13="","",SUMPRODUCT(('Detalle Turnos'!$Q$3:$Q$500=$A13)*('Detalle Turnos'!$S$3:$S$500=C13)*'Detalle Turnos'!$U$3:$U$500))} -> 215.77 | F13: =IFERROR(E13/D13,0) -> 7.9914815 | G13: {=IFERROR(SUMPRODUCT(('Facturación 2026'!$A$4:$A$253=A13)*'Facturación 2026'!$J$4:$J$253)*E13/SUMPRODUCT(('Facturación 2026'!$A$4:$A$253=A13)*'Facturación 2026'!$F$4:$F$253),0)} -> 159.77716 | H13: =E13-G13 -> 55.992836 | I13: =IFERROR(G13/E13,0) -> 0.74049759 | J13: =IFERROR(INDEX('Facturación 2026'!$L$4:$L$253,MATCH(A13,'Facturación 2026'!$A$4:$A$253,0)),"") | L13: Noche | O13: {=SUMPRODUCT(($C$4:$C$166="Noche")*IFERROR($D$4:$D$166*1,0))} -> 1693 | P13: {=SUMPRODUCT(($C$4:$C$166="Noche")*IFERROR($E$4:$E$166*1,0))} -> 27065.48 | Q13: =IFERROR(P13/$E$173,0) -> 145.61981 | R13: =IFERROR(P13/O13,0) -> 15.986698 | S13: {=SUMPRODUCT(($C$4:$C$164="Noche")*$H$4:$H$164)} -> 18794.814 | T13: =IFERROR(1-S13/P13,0) -> 0.30557989
A14: 46029 | B14: Mié | C14: Noche | D14: {=IF(A14="","",SUMPRODUCT(('Detalle Turnos'!$Q$3:$Q$500=$A14)*('Detalle Turnos'!$S$3:$S$500=C14)*'Detalle Turnos'!$T$3:$T$500))} -> 12 | E14: {=IF(A14="","",SUMPRODUCT(('Detalle Turnos'!$Q$3:$Q$500=$A14)*('Detalle Turnos'!$S$3:$S$500=C14)*'Detalle Turnos'!$U$3:$U$500))} -> 133.23 | F14: =IFERROR(E14/D14,0) -> 11.1025 | G14: {=IFERROR(SUMPRODUCT(('Facturación 2026'!$A$4:$A$253=A14)*'Facturación 2026'!$J$4:$J$253)*E14/SUMPRODUCT(('Facturación 2026'!$A$4:$A$253=A14)*'Facturación 2026'!$F$4:$F$253),0)} -> 98.656494 | H14: =E14-G14 -> 34.573506 | I14: =IFERROR(G14/E14,0) -> 0.74049759 | J14: =IFERROR(INDEX('Facturación 2026'!$L$4:$L$253,MATCH(A14,'Facturación 2026'!$A$4:$A$253,0)),"") | L14: Total | O14: =SUM(O11:O13) -> 5429 | P14: =SUM(P11:P13) -> 69154.962 | Q14: =SUM(Q11:Q13) -> 372.07292 | R14: =IFERROR(P14/O14,0) -> 12.738066 | S14: =SUM(S11:S13) -> 47157.112 | T14: =IFERROR(1-S14/P14,0) -> 0.31809503
A15: 46030 | B15: Jue | C15: Mañana | D15: {=IF(A15="","",SUMPRODUCT(('Detalle Turnos'!$Q$3:$Q$500=$A15)*('Detalle Turnos'!$S$3:$S$500=C15)*'Detalle Turnos'!$T$3:$T$500))} -> 4 | E15: {=IF(A15="","",SUMPRODUCT(('Detalle Turnos'!$Q$3:$Q$500=$A15)*('Detalle Turnos'!$S$3:$S$500=C15)*'Detalle Turnos'!$U$3:$U$500))} -> 7.41 | F15: =IFERROR(E15/D15,0) -> 1.8525 | G15: {=IFERROR(SUMPRODUCT(('Facturación 2026'!$A$4:$A$253=A15)*'Facturación 2026'!$J$4:$J$253)*E15/SUMPRODUCT(('Facturación 2026'!$A$4:$A$253=A15)*'Facturación 2026'!$F$4:$F$253),0)} -> 5.5200555 | H15: =E15-G15 -> 1.8899445 | I15: =IFERROR(G15/E15,0) -> 0.74494676 | J15: =IFERROR(INDEX('Facturación 2026'!$L$4:$L$253,MATCH(A15,'Facturación 2026'!$A$4:$A$253,0)),"")
A16: 46030 | B16: Jue | C16: Mediodia | D16: {=IF(A16="","",SUMPRODUCT(('Detalle Turnos'!$Q$3:$Q$500=$A16)*('Detalle Turnos'!$S$3:$S$500=C16)*'Detalle Turnos'!$T$3:$T$500))} -> 20 | E16: {=IF(A16="","",SUMPRODUCT(('Detalle Turnos'!$Q$3:$Q$500=$A16)*('Detalle Turnos'!$S$3:$S$500=C16)*'Detalle Turnos'!$U$3:$U$500))} -> 415.55 | F16: =IFERROR(E16/D16,0) -> 20.7775 | G16: {=IFERROR(SUMPRODUCT(('Facturación 2026'!$A$4:$A$253=A16)*'Facturación 2026'!$J$4:$J$253)*E16/SUMPRODUCT(('Facturación 2026'!$A$4:$A$253=A16)*'Facturación 2026'!$F$4:$F$253),0)} -> 309.56262 | H16: =E16-G16 -> 105.98738 | I16: =IFERROR(G16/E16,0) -> 0.74494676 | J16: =IFERROR(INDEX('Facturación 2026'!$L$4:$L$253,MATCH(A16,'Facturación 2026'!$A$4:$A$253,0)),"")
A17: 46030 | B17: Jue | C17: Noche | D17: {=IF(A17="","",SUMPRODUCT(('Detalle Turnos'!$Q$3:$Q$500=$A17)*('Detalle Turnos'!$S$3:$S$500=C17)*'Detalle Turnos'!$T$3:$T$500))} -> 2 | E17: {=IF(A17="","",SUMPRODUCT(('Detalle Turnos'!$Q$3:$Q$500=$A17)*('Detalle Turnos'!$S$3:$S$500=C17)*'Detalle Turnos'!$U$3:$U$500))} -> 36.23 | F17: =IFERROR(E17/D17,0) -> 18.115 | G17: {=IFERROR(SUMPRODUCT(('Facturación 2026'!$A$4:$A$253=A17)*'Facturación 2026'!$J$4:$J$253)*E17/SUMPRODUCT(('Facturación 2026'!$A$4:$A$253=A17)*'Facturación 2026'!$F$4:$F$253),0)} -> 26.989421 | H17: =E17-G17 -> 9.240579 | I17: =IFERROR(G17/E17,0) -> 0.74494676 | J17: =IFERROR(INDEX('Facturación 2026'!$L$4:$L$253,MATCH(A17,'Facturación 2026'!$A$4:$A$253,0)),"")
A18: 46031 | B18: Vie | C18: Mañana | D18: {=IF(A18="","",SUMPRODUCT(('Detalle Turnos'!$Q$3:$Q$500=$A18)*('Detalle Turnos'!$S$3:$S$500=C18)*'Detalle Turnos'!$T$3:$T$500))} -> 9 | E18: {=IF(A18="","",SUMPRODUCT(('Detalle Turnos'!$Q$3:$Q$500=$A18)*('Detalle Turnos'!$S$3:$S$500=C18)*'Detalle Turnos'!$U$3:$U$500))} -> 26.91 | F18: =IFERROR(E18/D18,0) -> 2.99 | G18: {=IFERROR(SUMPRODUCT(('Facturación 2026'!$A$4:$A$253=A18)*'Facturación 2026'!$J$4:$J$253)*E18/SUMPRODUCT(('Facturación 2026'!$A$4:$A$253=A18)*'Facturación 2026'!$F$4:$F$253),0)} -> 11.737137 | H18: =E18-G18 -> 15.172863 | I18: =IFERROR(G18/E18,0) -> 0.43616266 | J18: =IFERROR(INDEX('Facturación 2026'!$L$4:$L$253,MATCH(A18,'Facturación 2026'!$A$4:$A$253,0)),"")
A19: 46031 | B19: Vie | C19: Mediodia | D19: {=IF(A19="","",SUMPRODUCT(('Detalle Turnos'!$Q$3:$Q$500=$A19)*('Detalle Turnos'!$S$3:$S$500=C19)*'Detalle Turnos'!$T$3:$T$500))} -> 9 | E19: {=IF(A19="","",SUMPRODUCT(('Detalle Turnos'!$Q$3:$Q$500=$A19)*('Detalle Turnos'!$S$3:$S$500=C19)*'Detalle Turnos'!$U$3:$U$500))} -> 79.96 | F19: =IFERROR(E19/D19,0) -> 8.8844444 | G19: {=IFERROR(SUMPRODUCT(('Facturación 2026'!$A$4:$A$253=A19)*'Facturación 2026'!$J$4:$J$253)*E19/SUMPRODUCT(('Facturación 2026'!$A$4:$A$253=A19)*'Facturación 2026'!$F$4:$F$253),0)} -> 34.875566 | H19: =E19-G19 -> 45.084434 | I19: =IFERROR(G19/E19,0) -> 0.43616266 | J19: =IFERROR(INDEX('Facturación 2026'!$L$4:$L$253,MATCH(A19,'Facturación 2026'!$A$4:$A$253,0)),"")
A20: 46031 | B20: Vie | C20: Noche | D20: {=IF(A20="","",SUMPRODUCT(('Detalle Turnos'!$Q$3:$Q$500=$A20)*('Detalle Turnos'!$S$3:$S$500=C20)*'Detalle Turnos'!$T$3:$T$500))} -> 35 | E20: {=IF(A20="","",SUMPRODUCT(('Detalle Turnos'!$Q$3:$Q$500=$A20)*('Detalle Turnos'!$S$3:$S$500=C20)*'Detalle Turnos'!$U$3:$U$500))} -> 652.09 | F20: =IFERROR(E20/D20,0) -> 18.631143 | G20: {=IFERROR(SUMPRODUCT(('Facturación 2026'!$A$4:$A$253=A20)*'Facturación 2026'!$J$4:$J$253)*E20/SUMPRODUCT(('Facturación 2026'!$A$4:$A$253=A20)*'Facturación 2026'!$F$4:$F$253),0)} -> 284.41731 | H20: =E20-G20 -> 367.67269 | I20: =IFERROR(G20/E20,0) -> 0.43616266 | J20: =IFERROR(INDEX('Facturación 2026'!$L$4:$L$253,MATCH(A20,'Facturación 2026'!$A$4:$A$253,0)),"")
A21: 46032 | B21: Sáb | C21: Mañana | D21: {=IF(A21="","",SUMPRODUCT(('Detalle Turnos'!$Q$3:$Q$500=$A21)*('Detalle Turnos'!$S$3:$S$500=C21)*'Detalle Turnos'!$T$3:$T$500))} -> 15 | E21: {=IF(A21="","",SUMPRODUCT(('Detalle Turnos'!$Q$3:$Q$500=$A21)*('Detalle Turnos'!$S$3:$S$500=C21)*'Detalle Turnos'!$U$3:$U$500))} -> 42 | F21: =IFERROR(E21/D21,0) -> 2.8 | G21: {=IFERROR(SUMPRODUCT(('Facturación 2026'!$A$4:$A$253=A21)*'Facturación 2026'!$J$4:$J$253)*E21/SUMPRODUCT(('Facturación 2026'!$A$4:$A$253=A21)*'Facturación 2026'!$F$4:$F$253),0)} -> 10.48989 | H21: =E21-G21 -> 31.51011 | I21: =IFERROR(G21/E21,0) -> 0.24975929 | J21: =IFERROR(INDEX('Facturación 2026'!$L$4:$L$253,MATCH(A21,'Facturación 2026'!$A$4:$A$253,0)),"")
A22: 46032 | B22: Sáb | C22: Mediodia | D22: {=IF(A22="","",SUMPRODUCT(('Detalle Turnos'!$Q$3:$Q$500=$A22)*('Detalle Turnos'!$S$3:$S$500=C22)*'Detalle Turnos'!$T$3:$T$500))} -> 66 | E22: {=IF(A22="","",SUMPRODUCT(('Detalle Turnos'!$Q$3:$Q$500=$A22)*('Detalle Turnos'!$S$3:$S$500=C22)*'Detalle Turnos'!$U$3:$U$500))} -> 1129.41 | F22: =IFERROR(E22/D22,0) -> 17.112273 | G22: {=IFERROR(SUMPRODUCT(('Facturación 2026'!$A$4:$A$253=A22)*'Facturación 2026'!$J$4:$J$253)*E22/SUMPRODUCT(('Facturación 2026'!$A$4:$A$253=A22)*'Facturación 2026'!$F$4:$F$253),0)} -> 282.08064 | H22: =E22-G22 -> 847.32936 | I22: =IFERROR(G22/E22,0) -> 0.24975929 | J22: =IFERROR(INDEX('Facturación 2026'!$L$4:$L$253,MATCH(A22,'Facturación 2026'!$A$4:$A$253,0)),"")
A23: 46032 | B23: Sáb | C23: Noche | D23: {=IF(A23="","",SUMPRODUCT(('Detalle Turnos'!$Q$3:$Q$500=$A23)*('Detalle Turnos'!$S$3:$S$500=C23)*'Detalle Turnos'!$T$3:$T$500))} -> 63 | E23: {=IF(A23="","",SUMPRODUCT(('Detalle Turnos'!$Q$3:$Q$500=$A23)*('Detalle Turnos'!$S$3:$S$500=C23)*'Detalle Turnos'!$U$3:$U$500))} -> 1131.23 | F23: =IFERROR(E23/D23,0) -> 17.956032 | G23: {=IFERROR(SUMPRODUCT(('Facturación 2026'!$A$4:$A$253=A23)*'Facturación 2026'!$J$4:$J$253)*E23/SUMPRODUCT(('Facturación 2026'!$A$4:$A$253=A23)*'Facturación 2026'!$F$4:$F$253),0)} -> 282.5352 | H23: =E23-G23 -> 848.6948 | I23: =IFERROR(G23/E23,0) -> 0.24975929 | J23: =IFERROR(INDEX('Facturación 2026'!$L$4:$L$253,MATCH(A23,'Facturación 2026'!$A$4:$A$253,0)),"")
A24: 46033 | B24: Dom | C24: Mañana | D24: {=IF(A24="","",SUMPRODUCT(('Detalle Turnos'!$Q$3:$Q$500=$A24)*('Detalle Turnos'!$S$3:$S$500=C24)*'Detalle Turnos'!$T$3:$T$500))} -> 17 | E24: {=IF(A24="","",SUMPRODUCT(('Detalle Turnos'!$Q$3:$Q$500=$A24)*('Detalle Turnos'!$S$3:$S$500=C24)*'Detalle Turnos'!$U$3:$U$500))} -> 67.14 | F24: =IFERROR(E24/D24,0) -> 3.9494118 | G24: {=IFERROR(SUMPRODUCT(('Facturación 2026'!$A$4:$A$253=A24)*'Facturación 2026'!$J$4:$J$253)*E24/SUMPRODUCT(('Facturación 2026'!$A$4:$A$253=A24)*'Facturación 2026'!$F$4:$F$253),0)} -> 30.971059 | H24: =E24-G24 -> 36.168941 | I24: =IFERROR(G24/E24,0) -> 0.46129072 | J24: =IFERROR(INDEX('Facturación 2026'!$L$4:$L$253,MATCH(A24,'Facturación 2026'!$A$4:$A$253,0)),"")
A25: 46033 | B25: Dom | C25: Mediodia | D25: {=IF(A25="","",SUMPRODUCT(('Detalle Turnos'!$Q$3:$Q$500=$A25)*('Detalle Turnos'!$S$3:$S$500=C25)*'Detalle Turnos'!$T$3:$T$500))} -> 61 | E25: {=IF(A25="","",SUMPRODUCT(('Detalle Turnos'!$Q$3:$Q$500=$A25)*('Detalle Turnos'!$S$3:$S$500=C25)*'Detalle Turnos'!$U$3:$U$500))} -> 720.5 | F25: =IFERROR(E25/D25,0) -> 11.811475 | G25: {=IFERROR(SUMPRODUCT(('Facturación 2026'!$A$4:$A$253=A25)*'Facturación 2026'!$J$4:$J$253)*E25/SUMPRODUCT(('Facturación 2026'!$A$4:$A$253=A25)*'Facturación 2026'!$F$4:$F$253),0)} -> 332.35996 | H25: =E25-G25 -> 388.14004 | I25: =IFERROR(G25/E25,0) -> 0.46129072 | J25: =IFERROR(INDEX('Facturación 2026'!$L$4:$L$253,MATCH(A25,'Facturación 2026'!$A$4:$A$253,0)),"")
A26: 46036 | B26: Mié | C26: Mañana | D26: {=IF(A26="","",SUMPRODUCT(('Detalle Turnos'!$Q$3:$Q$500=$A26)*('Detalle Turnos'!$S$3:$S$500=C26)*'Detalle Turnos'!$T$3:$T$500))} -> 17 | E26: {=IF(A26="","",SUMPRODUCT(('Detalle Turnos'!$Q$3:$Q$500=$A26)*('Detalle Turnos'!$S$3:$S$500=C26)*'Detalle Turnos'!$U$3:$U$500))} -> 135.23 | F26: =IFERROR(E26/D26,0) -> 7.9547059 | G26: {=IFERROR(SUMPRODUCT(('Facturación 2026'!$A$4:$A$253=A26)*'Facturación 2026'!$J$4:$J$253)*E26/SUMPRODUCT(('Facturación 2026'!$A$4:$A$253=A26)*'Facturación 2026'!$F$4:$F$253),0)} -> 86.738537 | H26: =E26-G26 -> 48.491463 | I26: =IFERROR(G26/E26,0) -> 0.6414149 | J26: =IFERROR(INDEX('Facturación 2026'!$L$4:$L$253,MATCH(A26,'Facturación 2026'!$A$4:$A$253,0)),"")
... A164: 46116 | B164: Sáb | C164: Noche | D164: {=IF(A164="","",SUMPRODUCT(('Detalle Turnos'!$Q$3:$Q$500=$A164)*('Detalle Turnos'!$S$3:$S$500=C164)*'Detalle Turnos'!$T$3:$T$500))} -> 32 | E164: {=IF(A164="","",SUMPRODUCT(('Detalle Turnos'!$Q$3:$Q$500=$A164)*('Detalle Turnos'!$S$3:$S$500=C164)*'Detalle Turnos'!$U$3:$U$500))} -> 528.59 | F164: =IFERROR(E164/D164,0) -> 16.518438 | G164: {=IFERROR(SUMPRODUCT(('Facturación 2026'!$A$4:$A$253=A164)*'Facturación 2026'!$J$4:$J$253)*E164/SUMPRODUCT(('Facturación 2026'!$A$4:$A$253=A164)*'Facturación 2026'!$F$4:$F$253),0)} -> 0 | H164: =E164-G164 -> 528.59 | I164: =IFERROR(G164/E164,0) -> 0 | J164: =IFERROR(INDEX('Facturación 2026'!$L$4:$L$253,MATCH(A164,'Facturación 2026'!$A$4:$A$253,0)),"")
A165: =46117 -> 46117 | B165: =IF(A165="","",CHOOSE(WEEKDAY(A165,2),"Lun","Mar","Mié","Jue","Vie","Sáb","Dom")) -> Dom | C165: Mañana | D165: {=IF(A165="","",SUMPRODUCT(('Detalle Turnos'!$Q$3:$Q$500=A165)*('Detalle Turnos'!$S$3:$S$500=C165)*'Detalle Turnos'!$T$3:$T$500))} -> 26 | E165: {=IF(A165="","",SUMPRODUCT(('Detalle Turnos'!$Q$3:$Q$500=A165)*('Detalle Turnos'!$S$3:$S$500=C165)*'Detalle Turnos'!$U$3:$U$500))} -> 106.409 | F165: =IFERROR(E165/D165,0) -> 4.0926538 | G165: {=IFERROR(SUMPRODUCT(('Facturación 2026'!$A$4:$A$253=A165)*'Facturación 2026'!$J$4:$J$253)*E165/SUMPRODUCT(('Facturación 2026'!$A$4:$A$253=A165)*'Facturación 2026'!$F$4:$F$253),0)} -> 0 | H165: =IF(E165="","",E165-G165) -> 106.409 | I165: =IFERROR(G165/E165,0) -> 0 | J165: =IFERROR(INDEX('Facturación 2026'!$L$4:$L$253,MATCH(A165,'Facturación 2026'!$A$4:$A$253,0)),"")
A166: =46117 -> 46117 | B166: =IF(A166="","",CHOOSE(WEEKDAY(A166,2),"Lun","Mar","Mié","Jue","Vie","Sáb","Dom")) -> Dom | C166: Mediodia | D166: {=IF(A166="","",SUMPRODUCT(('Detalle Turnos'!$Q$3:$Q$500=A166)*('Detalle Turnos'!$S$3:$S$500=C166)*'Detalle Turnos'!$T$3:$T$500))} -> 82 | E166: {=IF(A166="","",SUMPRODUCT(('Detalle Turnos'!$Q$3:$Q$500=A166)*('Detalle Turnos'!$S$3:$S$500=C166)*'Detalle Turnos'!$U$3:$U$500))} -> 1152.273 | F166: =IFERROR(E166/D166,0) -> 14.05211 | G166: {=IFERROR(SUMPRODUCT(('Facturación 2026'!$A$4:$A$253=A166)*'Facturación 2026'!$J$4:$J$253)*E166/SUMPRODUCT(('Facturación 2026'!$A$4:$A$253=A166)*'Facturación 2026'!$F$4:$F$253),0)} -> 0 | H166: =IF(E166="","",E166-G166) -> 1152.273 | I166: =IFERROR(G166/E166,0) -> 0 | J166: =IFERROR(INDEX('Facturación 2026'!$L$4:$L$253,MATCH(A166,'Facturación 2026'!$A$4:$A$253,0)),"")
